Workbook

Sheet Look Up Mobile
A1: Ladies Ring | E1: Discount
A2: Sn | B2: 217 | E2: 37.5 | F2: Cert Check
E3: =IF(G5>30,"G",IF(AND(G5>25,G5<30),"A",IF(AND(G5>20,G5<25),"B","C"))) -> B | F3: {=XLOOKUP(A1&B2, 'Certificate Data'!A:A, 'Certificate Data'!P:P)} -> SGLJNPJ342336E
A4: Net Weight | B4: {=VLOOKUP($B$2,INDIRECT("'"&A1&"'!$A$2:$S$999"), 2, 0)} -> 4.14 | C4: {=VLOOKUP($B$2,INDIRECT("'"&A1&"'!$A$2:$S$999"), 3, 0)} -> 1.035 | D4: {=VLOOKUP($B$2,INDIRECT("'"&A1&"'!$A$2:$S$999"), 4, 0)} -> 5.175 | E4: {=VLOOKUP($B$2,INDIRECT("'"&A1&"'!$A$2:$S$999"), 17, 0)} -> 92373.75 | F4: =IFERROR(E4/D4,0) -> 17850 | G4: =(((D4*0.6)/11.664)*Prices!A4)+D5*38000+D6*51900+D7*60900+D8*140000+D9*2000+D10*8000+D11*1200 -> 105855.56
A5: Dmd < 0.06 | D5: {=VLOOKUP($B$2,INDIRECT("'"&A1&"'!$A$2:$S$999"), 5, 0)} -> 0.6 | E5: {=VLOOKUP($B$2,INDIRECT("'"&A1&"'!$A$2:$S$999"), 12, 0)} -> 66000 | F5: =IFERROR(E5/D5,0) -> 110000 | G5: =((E17-G4)/E17)*100 -> 20.780882
A6: Dmd < 0.12 | D6: {=VLOOKUP($B$2,INDIRECT("'"&A1&"'!$A$2:$S$999"), 6, 0)} | E6: {=VLOOKUP($B$2,INDIRECT("'"&A1&"'!$A$2:$S$999"), 13, 0)} -> 0 | F6: =IFERROR(E6/D6,0) -> 0
A7: Dmd < 0.17 | D7: {=VLOOKUP($B$2,INDIRECT("'"&A1&"'!$A$2:$S$999"), 7, 0)} | E7: {=VLOOKUP($B$2,INDIRECT("'"&A1&"'!$A$2:$S$999"), 14, 0)} -> 0 | F7: =IFERROR(E7/D7,0) -> 0
A8: Dmd Big | D8: {=VLOOKUP($B$2,INDIRECT("'"&A1&"'!$A$2:$S$999"), 8, 0)} | E8: {=VLOOKUP($B$2,INDIRECT("'"&A1&"'!$A$2:$S$999"), 15, 0)} -> 0 | F8: =IFERROR(E8/D8,0) -> 0
A9: Ruby | D9: {=VLOOKUP($B$2,INDIRECT("'"&A1&"'!$A$2:$S$999"), 9, 0)} | E9: {=IF(D9<>0,VLOOKUP($B$2,INDIRECT("'"&A1&"'!$A$2:$S$999"),16,0),0)} -> 0 | F9: =IFERROR(E9/D9,0) -> 0
A10: Emreld | D10: {=VLOOKUP($B$2,INDIRECT("'"&A1&"'!$A$2:$S$999"), 10, 0)} | E10: {=IF(D10<>0,VLOOKUP($B$2,INDIRECT("'"&A1&"'!$A$2:$S$999"),16,0),0)} -> 0 | F10: =IFERROR(E10/D10,0) -> 0
A11: Muga | D11: {=VLOOKUP($B$2,INDIRECT("'"&A1&"'!$A$2:$S$999"), 11, 0)} | E11: {=IF(D11<>0,VLOOKUP($B$2,INDIRECT("'"&A1&"'!$A$2:$S$999"),16,0),0)} -> 0 | F11: =IFERROR(E11/D11,0) -> 0
D12: Gold Total | E12: {=VLOOKUP($B$2,INDIRECT("'"&A1&"'!$A$2:$S$999"), 17, 0)} -> 92373.75
D13: Diamond Total | E13: {=VLOOKUP($B$2,INDIRECT("'"&A1&"'!$A$2:$S$999"), 18, 0)} -> 66000
D14: Stone Total | E14: {=VLOOKUP($B$2,INDIRECT("'"&A1&"'!$A$2:$S$999"), 16, 0)} -> 0
D15: Total | E15: =E14+E12+E13 -> 158373.75
D16: Discount | E16: =E13*E2% -> 24750
D17: Net Total | E17: =E15-E16 -> 133623.75
D18: 2% Luxury Tax | E18: =E12*0.02 -> 1847.475
D19: Grand Total | E19: =E15-E16+E18 -> 135471.23

Sheet Bill Maker 1
C1: Discount | D1: 42 | E1: Gold Rate | F1: 296800 | G1: 1100 | K1: 14k | L1: =L12 -> 17850
A2: SN | B2: Description | C2: Net Wt | D2: Wastage | E2: Total Wt | F2: Rate | G2: Labour | H2: Taxable Amount | I2: Amount | L2: Rate
A3: AJ1 | B3: DJ Price | C3: {=VLOOKUP($A$3,INDIRECT("'"&B3&"'!$A$2:$S$999"), 2, 0)} -> 1.278 | D3: {=VLOOKUP($A$3,INDIRECT("'"&B3&"'!$A$2:$S$999"), 3, 0)} -> 0.3195 | E3: {=VLOOKUP($A$3,INDIRECT("'"&B3&"'!$A$2:$S$999"), 4, 0)} -> 1.5975 | F3: =ROUNDDOWN((F1/11.664)*0.6,0) -> 15267 | G3: =L4*E3 -> 1757.25 | H3: =(F3*E3)+G3 -> 26146.283 | K3: Gold | L3: =ROUNDDOWN((F1/11.664)*0.6,0) -> 15267
B4: Dmd < 0.06 | E4: {=VLOOKUP($A$3,INDIRECT("'"&B3&"'!$A$2:$S$999"), 5, 0)} -> 0.26 | F4: =P5 -> 73094.132 | I4: =F4*E4 -> 19004.474 | K4: Labour Rate | L4: 1100 | M4: =L12-L3 -> 2583 | P4: Rate | R4: =COUNTIF(E4:E7, ">0") -> 1
B5: Dmd < 0.12 | E5: {=VLOOKUP($A$3,INDIRECT("'"&B3&"'!$A$2:$S$999"), 6, 0)} | F5: =P6 -> 0 | I5: =F5*E5 -> 0 | K5: Dmd < 0.06 | L5: =IFERROR(M5/E4,0) -> 110000 | M5: {=VLOOKUP($A$3,INDIRECT("'"&B3&"'!$A$2:$S$999"), 12, 0)} -> 28600 | N5: =L5-(L5*$D$1%) -> 63800 | O5: Dmd < 0.06 | P5: =IFERROR(Q5/E4,0) -> 73094.132 | Q5: =IF(E4<>0,(N5*E4)+R5,0) -> 19004.474 | R5: =$R$15/$R$4 -> 2416.4743
B6: Dmd < 0.17 | E6: {=VLOOKUP($A$3,INDIRECT("'"&B3&"'!$A$2:$S$999"), 7, 0)} | F6: =P7 -> 0 | I6: =F6*E6 -> 0 | K6: Dmd < 0.12 | L6: =IFERROR(M6/E5,0) -> 0 | M6: {=VLOOKUP($A$3,INDIRECT("'"&B3&"'!$A$2:$S$999"), 13, 0)} -> 0 | N6: =L6-(L6*$D$1%) -> 0 | O6: Dmd < 0.12 | P6: =IFERROR(Q6/E5,0) -> 0 | Q6: =IF(E5<>0,(N6*E5)+R6,0) -> 0 | R6: =$R$15/$R$4 -> 2416.4743
B7: Dmd Big | E7: {=VLOOKUP($A$3,INDIRECT("'"&B3&"'!$A$2:$S$999"), 8, 0)} | F7: =P8 -> 0 | I7: =F7*E7 -> 0 | K7: Dmd < 0.17 | L7: =IFERROR(M7/E6,0) -> 0 | M7: {=VLOOKUP($A$3,INDIRECT("'"&B3&"'!$A$2:$S$999"), 14, 0)} -> 0 | N7: =L7-(L7*$D$1%) -> 0 | O7: Dmd < 0.17 | P7: =IFERROR(Q7/E6,0) -> 0 | Q7: =IF(E6<>0,(N7*E6)+R7,0) -> 0 | R7: =$R$15/$R$4 -> 2416.4743
B8: Ruby | E8: {=VLOOKUP($A$3,INDIRECT("'"&B3&"'!$A$2:$S$999"), 9, 0)} | F8: =IFERROR(I8/E8,0) -> 0 | I8: {=IF(E8<>0,VLOOKUP($A$3,INDIRECT("'"&B3&"'!$A$2:$S$999"),16,0),0)} -> 0 | K8: Dmd Big | L8: =IFERROR(M8/E7,0) -> 0 | M8: {=VLOOKUP($A$3,INDIRECT("'"&B3&"'!$A$2:$S$999"), 15, 0)} -> 0 | N8: =L8-(L8*$D$1%) -> 0 | O8: Dmd Big | P8: =IFERROR(Q8/E7,0) -> 0 | Q8: =IF(E7<>0,(N8*E7)+R8,0) -> 0 | R8: =$R$15/$R$4 -> 2416.4743
B9: Emreld | E9: {=VLOOKUP($A$3,INDIRECT("'"&B3&"'!$A$2:$S$999"), 10, 0)} | F9: =IFERROR(I9/E9,0) -> 0 | I9: {=IF(E9<>0,VLOOKUP($A$3,INDIRECT("'"&B3&"'!$A$2:$S$999"),16,0),0)} -> 0 | K9: Ruby | L9: =IFERROR(M9/E8,0) -> 0 | M9: {=IF(I8<>0,VLOOKUP($A$3,INDIRECT("'"&B3&"'!$A$2:$S$999"),16,0),0)} -> 0 | O9: Ruby | P9: =IFERROR(Q9/E8,0) -> 0 | Q9: {=IF(I8<>0,VLOOKUP($A$3,INDIRECT("'"&B3&"'!$A$2:$S$999"),16,0),0)} -> 0
B10: Muga | E10: {=VLOOKUP($A$3,INDIRECT("'"&B3&"'!$A$2:$S$999"), 11, 0)} | F10: =IFERROR(I10/E10,0) -> 0 | I10: {=IF(E10<>0,VLOOKUP($A$3,INDIRECT("'"&B3&"'!$A$2:$S$999"),16,0),0)} -> 0 | K10: Emreld | L10: =IFERROR(M10/E9,0) -> 0 | M10: {=IF(I9<>0,VLOOKUP($A$3,INDIRECT("'"&B3&"'!$A$2:$S$999"),16,0),0)} -> 0 | O10: Emreld | P10: =IFERROR(Q10/E9,0) -> 0 | Q10: {=IF(I9<>0,VLOOKUP($A$3,INDIRECT("'"&B3&"'!$A$2:$S$999"),16,0),0)} -> 0
G11: Discount | I11: 288 | K11: Muga | L11: =IFERROR(M11/E10,0) -> 0 | M11: {=IF(I10<>0,VLOOKUP($A$3,INDIRECT("'"&B3&"'!$A$2:$S$999"),16,0),0)} -> 0 | O11: Muga | P11: =IFERROR(Q11/E10,0) -> 0 | Q11: {=IF(I10<>0,VLOOKUP($A$3,INDIRECT("'"&B3&"'!$A$2:$S$999"),16,0),0)} -> 0
E12: Amount Before TAX | H12: =H3 -> 26146.283 | I12: =I4-I11+I10+I9+I7+I8+I6+I5 -> 18716.474 | K12: Gold | L12: =M12/E3 -> 17850 | M12: {=VLOOKUP($A$3,INDIRECT("'"&$B$3&"'!$A$2:$S$999"), 17, 0)} -> 28515.375 | O12: Gold | P12: =ROUNDDOWN((F1/11.664)*0.6,0) -> 15267 | Q12: =E3*P12 -> 24389.033
E13: 2% TAX | H13: =H12*0.02 -> 522.92565 | K13: Tax | M13: =M12*0.02 -> 570.3075 | O13: Labour | P13: 1100 | Q13: =E3*P13 -> 1757.25
E14: Grand Total | H14: =H12+I12+H13 -> 45385.683 | K14: Diamond | L14: =M14/(E4+E5+E6+E7) -> 110000 | M14: {=VLOOKUP($A$3,INDIRECT("'"&$B$3&"'!$A$2:$S$999"), 18, 0)} -> 28600 | O14: Tax | Q14: =(Q12+Q13)*0.02 -> 522.92565
K15: net | M15: =M14+M13+M12+M11+M10+M9 -> 57685.683 | O15: Diamond | Q15: =Q18-Q9-Q10-Q11-Q12-Q13-Q14 -> 19004.474 | R15: =Q15-M17 -> 2416.4743
K16: Discount | M16: =M14*D1% -> 12012 | O16: net
K17: Diamond Aft Disc | M17: =M14-M16 -> 16588 | O17: Discount
K18: Grand Total | M18: =M9+M10+M11+M12+M13+M14-M16 -> 45673.683 | O18: Grand Total | Q18: =M18 -> 45673.683

Sheet Bill Maker
F1: Gold Rate | G1: 238000 | H1: 14k Rate | I1: =IFERROR(H3/E3,0) -> 17850 | J1: =I1-F3 -> 5608
A2: SN | B2: Description | C2: Net Wt | D2: Wastage | E2: Total Wt | F2: Rate | G2: Labour | H2: Taxable Amount | I2: Amount | L2: Rate
A3: 337 | B3: Ladies Ring | C3: {=VLOOKUP($A$3,INDIRECT("'"&B3&"'!$A$2:$S$999"), 2, 0)} -> 3.442 | D3: {=VLOOKUP($A$3,INDIRECT("'"&B3&"'!$A$2:$S$999"), 3, 0)} -> 0.8605 | E3: {=VLOOKUP($A$3,INDIRECT("'"&B3&"'!$A$2:$S$999"), 4, 0)} -> 4.3025 | F3: =ROUNDDOWN((G1/11.664)*0.6,0) -> 12242 | G3: =J1*E3 -> 24128.42 | H3: {=VLOOKUP($A$3,INDIRECT("'"&B3&"'!$A$2:$S$999"), 17, 0)} -> 76799.625 | K3: Gold | L3: =ROUNDDOWN((G1/11.664)*0.6,0) -> 12242
B4: Dmd < 0.06 | E4: {=VLOOKUP($A$3,INDIRECT("'"&B3&"'!$A$2:$S$999"), 5, 0)} -> 0.54 | F4: =L4-(L4*E11%) -> 68200 | I4: =F4*E4 -> 36828 | K4: Dmd < 0.06 | L4: =IFERROR(M4/E4,0) -> 110000 | M4: {=VLOOKUP($A$3,INDIRECT("'"&B3&"'!$A$2:$S$999"), 12, 0)} -> 59400
B5: Dmd < 0.12 | E5: {=VLOOKUP($A$3,INDIRECT("'"&B3&"'!$A$2:$S$999"), 6, 0)} | F5: =IFERROR(I5/E5,0) -> 0 | I5: {=VLOOKUP($A$3,INDIRECT("'"&B3&"'!$A$2:$S$999"), 13, 0)} -> 0 | K5: Dmd < 0.12 | L5: =IFERROR(M5/E5,0) -> 0 | M5: {=VLOOKUP($A$3,INDIRECT("'"&B3&"'!$A$2:$S$999"), 13, 0)} -> 0
B6: Dmd < 0.17 | E6: {=VLOOKUP($A$3,INDIRECT("'"&B3&"'!$A$2:$S$999"), 7, 0)} | F6: =IFERROR(I6/E6,0) -> 0 | I6: {=VLOOKUP($A$3,INDIRECT("'"&B3&"'!$A$2:$S$999"), 14, 0)} -> 0 | K6: Dmd < 0.17 | L6: =IFERROR(M6/E6,0) -> 0 | M6: {=VLOOKUP($A$3,INDIRECT("'"&B3&"'!$A$2:$S$999"), 14, 0)} -> 0
B7: Dmd Big | E7: {=VLOOKUP($A$3,INDIRECT("'"&B3&"'!$A$2:$S$999"), 8, 0)} | F7: =IFERROR(I7/E7,0) -> 0 | I7: {=VLOOKUP($A$3,INDIRECT("'"&B3&"'!$A$2:$S$999"), 15, 0)} -> 0 | K7: Dmd Big | L7: =IFERROR(M7/E7,0) -> 0 | M7: {=VLOOKUP($A$3,INDIRECT("'"&B3&"'!$A$2:$S$999"), 15, 0)} -> 0
B8: Ruby | E8: {=VLOOKUP($A$3,INDIRECT("'"&B3&"'!$A$2:$S$999"), 9, 0)} | F8: =IFERROR(I8/E8,0) -> 0 | I8: {=IF(E8<>0,VLOOKUP($A$3,INDIRECT("'"&B3&"'!$A$2:$S$999"),16,0),0)} -> 0 | K8: Ruby | L8: =IFERROR(M8/E8,0) -> 0 | M8: {=IF(I8<>0,VLOOKUP($A$3,INDIRECT("'"&B3&"'!$A$2:$S$999"),16,0),0)} -> 0
B9: Emreld | E9: {=VLOOKUP($A$3,INDIRECT("'"&B3&"'!$A$2:$S$999"), 10, 0)} | F9: =IFERROR(I9/E9,0) -> 0 | I9: {=IF(E9<>0,VLOOKUP($A$3,INDIRECT("'"&B3&"'!$A$2:$S$999"),16,0),0)} -> 0 | K9: Emreld | L9: =IFERROR(M9/E9,0) -> 0 | M9: {=IF(I9<>0,VLOOKUP($A$3,INDIRECT("'"&B3&"'!$A$2:$S$999"),16,0),0)} -> 0
B10: Muga | E10: {=VLOOKUP($A$3,INDIRECT("'"&B3&"'!$A$2:$S$999"), 11, 0)} | F10: =IFERROR(I10/E10,0) -> 0 | I10: {=IF(E10<>0,VLOOKUP($A$3,INDIRECT("'"&B3&"'!$A$2:$S$999"),16,0),0)} -> 0 | K10: Muga | L10: =IFERROR(M10/E10,0) -> 0 | M10: {=IF(I10<>0,VLOOKUP($A$3,INDIRECT("'"&B3&"'!$A$2:$S$999"),16,0),0)} -> 0
E11: 38 | F11: % | G11: Discount | I11: 696
E12: Amount Before TAX | H12: {=VLOOKUP($A$3,INDIRECT("'"&B3&"'!$A$2:$S$999"), 17, 0)} -> 76799.625 | I12: =SUM(I4:I10)-I11 -> 36132
E13: 2% TAX | H13: =H12*0.02 -> 1535.9925
E14: Grand Total | H14: =H12+I12+H13 -> 114467.62

Sheet Gold Prices
A1: Gold | C1: 18K | F1: Gold | H1: 14K | K1: Conversion
A2: Weight | B2: 27 | C2: 0.12 | D2: % | F2: Weight | G2: 3.021 | H2: 0.2 | K2: =B2 -> 27 | L2: lal | M2: = | N2: =B2*0.1164 -> 3.1428 | O2: gm
A3: Jarti | B3: =B2*(C2) -> 3.24 | C3: =IF(A1="Gold",IF(C1="24K",B15,IF(C1="22K",B16,IF(C1="18K",B17,B18))),C15) -> 245200 | F3: Jarti | G3: =G2*(H2) -> 0.6042 | H3: =IF(F1="Gold",IF(H1="24K",G15,IF(H1="22K",G16,IF(H1="18K",G17,G18))),H15) -> 15766.461 | K3: =B3 -> 3.24 | L3: lal | M3: = | N3: =B3*0.1164 -> 0.377136 | O3: gm
A4: Total Weight | B4: =B2+B3 -> 30.24 | F4: Total Weight | G4: =G2+G3 -> 3.6252 | K4: =B4 -> 30.24 | L4: lal | M4: = | N4: =B4*0.1164 -> 3.519936 | O4: gm
A5: Jyala/pc | B5: 1500 | F5: Jyala/pc
A6: Jyala % | F6: Jyala % | G6: 5
A7: Jyala/tola | F7: Jyala/gm
A8: Total Price | B8: =IF($A$1="Gold",B4*(C3/100),B4*(C15)) -> 74148.48 | F8: Total Price | G8: =IF($A$1="Gold",G4*(H3),G4*(H15)) -> 57156.574
A9: Jyala | B9: =IF(B6<>0,((B4*B6%)*(C3/100)),IF(B7<>0,B7*B4,B5)) -> 1500 | F9: Jyala | G9: =IF(G6<>0,((G4*G6%)*(H3)),IF(G7<>0,G7*G4,G5)) -> 2857.8287
A10: Stone | F10: Stone
A11: Tax | B11: =IF(A1="Gold",SUM(B8:B9)*0.02,0) -> 1512.9696 | F11: Tax | G11: =IF(F1="Gold",SUM(G8:G9)*0.02,0) -> 1200.2881
A12: Grand Total | B12: =SUM(B8:B11) -> 77161.45 | F12: Grand Total | G12: =SUM(G8:G11) -> 61214.691
B14: Gold | C14: Silver | G14: Gold | H14: Silver
A15: 24K | B15: 306500 | C15: 4080 | F15: 24K | G15: =B15/11.664 -> 26277.435 | H15: 4080
A16: 22K | B16: =ROUNDUP(B15*91.6%, -1) -> 280760 | F16: 22K | G16: =ROUNDUP(G15*91.6%, -1) -> 24080
A17: 18K | B17: =B15*0.8 -> 245200 | F17: 18K | G17: =G15*0.8 -> 21021.948
A18: 14k | B18: =B15*0.6 -> 183900 | F18: 14K | G18: =G15*0.6 -> 15766.461

Sheet Look Up
A1: Ring Lookup | F1: =TODAY() -> 46179 | Q1: Discount % | R1: 40
A2: Sn | B2: Net Weight | C2: Wstg + MC | D2: Gross Weight | E2: Dmd <0.06 | F2: Dmd < 0.12 | G2: Dmd <0.17 | H2: Dmd Big | I2: Ruby | J2: Emreld | K2: Muga | L2: Dmd Price | M2: Dmd Price | N2: Dmd Price | O2: Dmd Price | P2: Stn Price | Q2: Gold Price | R2: Ttl dmd Price | S2: Total Price | T2: Tax | W2: =(((D3*0.6)/11.664)*Prices!A4)+E3*38000+F3*51900+G3*60900+H3*140000+I3*1000+J3*3000+K3*300 -> 250769.14
A3: 232 | B3: =VLOOKUP($A$3,'Ladies Ring'!$A$2:$S$998, 2, 0) -> 9.382 | C3: =VLOOKUP($A$3,'Ladies Ring'!$A$2:$S$998, 3, 0) -> 2.3455 | D3: =VLOOKUP($A$3,'Ladies Ring'!$A$2:$S$998, 4, 0) -> 11.7275 | E3: =VLOOKUP($A$3,'Ladies Ring'!$A$2:$S$998, 5, 0) -> 1.59 | F3: =VLOOKUP($A$3,'Ladies Ring'!$A$2:$S$998, 6, 0) | G3: =VLOOKUP($A$3,'Ladies Ring'!$A$2:$S$998, 7, 0) | H3: =VLOOKUP($A$3,'Ladies Ring'!$A$2:$S$998, 8, 0) | I3: =VLOOKUP($A$3,'Ladies Ring'!$A$2:$S$998, 9, 0) | J3: =VLOOKUP($A$3,'Ladies Ring'!$A$2:$S$998, 10, 0) | K3: =VLOOKUP($A$3,'Ladies Ring'!$A$2:$S$998, 11, 0) -> 7.1 | L3: =VLOOKUP($A$3,'Ladies Ring'!$A$2:$S$998, 12, 0) -> 174900 | M3: =VLOOKUP($A$3,'Ladies Ring'!$A$2:$S$998, 13, 0) -> 0 | N3: =VLOOKUP($A$3,'Ladies Ring'!$A$2:$S$998, 14, 0) -> 0 | O3: =VLOOKUP($A$3,'Ladies Ring'!$A$2:$S$998, 15, 0) -> 0 | P3: =VLOOKUP($A$3,'Ladies Ring'!$A$2:$S$998, 16, 0) -> 12780 | Q3: =VLOOKUP($A$3,'Ladies Ring'!$A$2:$S$998, 17, 0) -> 209335.88 | R3: =VLOOKUP($A$3,'Ladies Ring'!$A$2:$S$998, 18, 0) -> 174900 | S3: =VLOOKUP($A$3,'Ladies Ring'!$A$2:$S$998, 19, 0) -> 397015.88 | T3: =Q3*0.02 -> 4186.7175 | W3: =((S4-W2)/S4)*100 -> 24.294417
L4: =IFERROR(L3/E3,0) -> 110000 | M4: =IFERROR(M3/F3,0) -> 0 | N4: =IFERROR(N3/G3,0) -> 0 | O4: =IFERROR(O3/H3,0) -> 0 | P4: =IFERROR(P3/(K3+J3+I3),0) -> 1800 | Q4: =IFERROR(Q3/D3,0) -> 17850 | R4: =R3-(R3*(R1/100)) -> 104940 | S4: =R4+Q3+P3+T3 -> 331242.59 | T4: =IF(W3>30,"G",IF(AND(W3>25,W3<30),"A",IF(AND(W3>20,W3<25),"B","C"))) -> B
R5: =R3-R4 -> 69960
A6: Gents Ring
A7: Sn | B7: Net Weight | C7: Wstg + MC | D7: Gross Weight | E7: Dmd <0.06 | F7: Dmd < 0.12 | G7: Dmd <0.17 | H7: Dmd Big | I7: Ruby | J7: Emreld | K7: Muga | L7: Dmd Price | M7: Dmd Price | N7: Dmd Price | O7: Dmd Price | P7: Stn Price | Q7: Gold Price | R7: Ttl dmd Price | S7: Total Price | T7: Tax | W7: =(((D8*0.6)/11.664)*Prices!A4)+E8*38000+F8*51900+G8*60900+H8*140000+I8*1000+J8*3000+K8*300 -> 131610.68
A8: 40 | B8: =VLOOKUP($A$8,'Gents Ring'!A2:S999, 2, 0) -> 3.98 | C8: =VLOOKUP($A$8,'Gents Ring'!A2:S999, 3, 0) -> 0.995 | D8: =VLOOKUP($A$8,'Gents Ring'!A2:S999, 4, 0) -> 4.975 | E8: =VLOOKUP($A$8,'Gents Ring'!A2:S999, 5, 0) | F8: =VLOOKUP($A$8,'Gents Ring'!A2:S999, 6, 0) | G8: =VLOOKUP($A$8,'Gents Ring'!A2:S999, 7, 0) -> 0.85 | H8: =VLOOKUP($A$8,'Gents Ring'!A2:S999, 8, 0) | I8: =VLOOKUP($A$8,'Gents Ring'!A2:S999, 9, 0) | J8: =VLOOKUP($A$8,'Gents Ring'!A2:S999, 10, 0) | K8: =VLOOKUP($A$8,'Gents Ring'!A2:S999, 11, 0) | L8: =VLOOKUP($A$8,'Gents Ring'!A2:S999, 12, 0) -> 0 | M8: =VLOOKUP($A$8,'Gents Ring'!A2:S999, 13, 0) -> 0 | N8: =VLOOKUP($A$8,'Gents Ring'!A2:S999, 14, 0) -> 165750 | O8: =VLOOKUP($A$8,'Gents Ring'!A2:S999, 15, 0) -> 0 | P8: =VLOOKUP($A$8,'Gents Ring'!A2:S999, 16, 0) -> 0 | Q8: =VLOOKUP($A$8,'Gents Ring'!A2:S999, 17, 0) -> 88803.75 | R8: =VLOOKUP($A$8,'Gents Ring'!A2:S999, 18, 0) -> 165750 | S8: =VLOOKUP($A$8,'Gents Ring'!A2:S999, 19, 0) -> 254553.75 | T8: =Q8*0.02 -> 1776.075 | W8: =((S9-W7)/S9)*100 -> 30.742093
L9: =IFERROR(L8/E8,0) -> 0 | M9: =IFERROR(M8/F8,0) -> 0 | N9: =IFERROR(N8/G8,0) -> 195000 | O9: =IFERROR(O8/H8,0) -> 0 | P9: =IFERROR(P8/(K8+J8+I8),0) -> 0 | Q9: =IFERROR(Q8/D8,0) -> 17850 | R9: =R8-(R8*(R1/100)) -> 99450 | S9: =R9+Q8+P8+T8 -> 190029.83 | T9: =IF(W8>30,"G",IF(AND(W8>25,W8<30),"A",IF(AND(W8>20,W8<25),"B","C"))) -> G
R10: =R8-R9 -> 66300
A11: Top Lookup
A12: Sn | B12: Net Weight | C12: Wstg + MC | D12: Gross weight | E12: Dmd <0.06 | F12: Dmd < 0.12 | G12: Dmd <0.17 | H12: Dmd Big | I12: Ruby | J12: Emreld | K12: Muga | L12: Dmd Price | M12: Dmd Price | N12: Dmd Price | O12: Dmd Price | P12: Stn Price | Q12: Gold Price | R12: Ttl dmd Price | S12: Total Price | T12: Tax | W12: =(((D13*0.6)/11.664)*Prices!A4)+E13*38000+F13*55000+G13*60900+H13*140000+I13*1000+J13*3000+K13*300 -> 200806.79
A13: 93 | B13: =VLOOKUP($A$13,Top!A2:S1000, 2, 0) -> 8.21 | C13: =VLOOKUP($A$13,Top!A2:S1000, 3, 0) -> 2.0525 | D13: =VLOOKUP($A$13,Top!A2:S1000, 4, 0) -> 10.2625 | E13: =VLOOKUP($A$13,Top!A2:S1000, 5, 0) -> 0.95 | F13: =VLOOKUP($A$13,Top!A2:S1000, 6, 0) | G13: =VLOOKUP($A$13,Top!A2:S1000, 7, 0) | H13: =VLOOKUP($A$13,Top!A2:S1000, 8, 0) | I13: =VLOOKUP($A$13,Top!A2:S1000, 9, 0) | J13: =VLOOKUP($A$13,Top!A2:S1000, 10, 0) | K13: =VLOOKUP($A$13,Top!A2:S1000, 11, 0) | L13: =VLOOKUP($A$13,Top!A2:S1000, 12, 0) -> 104500 | M13: =VLOOKUP($A$13,Top!A2:S1000, 13, 0) -> 0 | N13: =VLOOKUP($A$13,Top!A2:S1000, 14, 0) -> 0 | O13: =VLOOKUP($A$13,Top!A2:S1000, 15, 0) -> 0 | P13: =VLOOKUP($A$13,Top!A2:S1000, 16, 0) -> 0 | Q13: =VLOOKUP($A$13,Top!A2:S1000, 17, 0) -> 183185.62 | R13: =VLOOKUP($A$13,Top!A2:S1000, 18, 0) -> 104500 | S13: =VLOOKUP($A$13,Top!A2:S1000, 19, 0) -> 287685.62 | T13: =Q13*0.02 -> 3663.7125 | W13: =((S14-W12)/S14)*100 -> 19.532229
L14: =IFERROR(L13/E13,0) -> 110000 | M14: =IFERROR(M13/F13,0) -> 0 | N14: =IFERROR(N13/G13,0) -> 0 | O14: =IFERROR(O13/H13,0) -> 0 | P14: =IFERROR(P13/(K13+J13+I13),0) -> 0 | Q14: =IFERROR(Q13/D13,0) -> 17850 | R14: =R13-(R13*(R1/100)) -> 62700 | S14: =R14+Q13+P13+T13 -> 249549.34 | T14: =IF(W13>30,"G",IF(AND(W13>25,W13<30),"A",IF(AND(W13>20,W13<25),"B","C"))) -> C
R15: =R13-R14 -> 41800
A16: Pendent Lookup
A18: Sn | B18: Net Weight | C18: Wstg + MC | D18: Gross weight | E18: Dmd <0.06 | F18: Dmd < 0.12 | G18: Dmd <0.17 | H18: Dmd Big | I18: Ruby | J18: Emreld | K18: Muga | L18: Dmd Price | M18: Dmd Price | N18: Dmd Price | O18: Dmd Price | P18: Stn Price | Q18: Gold Price | R18: Ttl dmd Price | S18: Total Price | T18: Tax | W18: =(((D19*0.6)/11.664)*Prices!A4)+E19*38000+F19*51900+G19*60900+H19*140000+I19*1000+J19*3000+K19*300 -> #REF!
A19: 1 | B19: =VLOOKUP($A$19,#REF!, 2, 0) -> #REF! | C19: =VLOOKUP($A$19,#REF!, 3, 0) -> #REF! | D19: =VLOOKUP($A$19,#REF!, 4, 0) -> #REF! | E19: =VLOOKUP($A$19,#REF!, 5, 0) -> #REF! | F19: =VLOOKUP($A$19,#REF!, 6, 0) -> #REF! | G19: =VLOOKUP($A$19,#REF!, 7, 0) -> #REF! | H19: =VLOOKUP($A$19,#REF!, 8, 0) -> #REF! | I19: =VLOOKUP($A$19,#REF!, 9, 0) -> #REF! | J19: =VLOOKUP($A$19,#REF!, 10, 0) -> #REF! | K19: =VLOOKUP($A$19,#REF!, 11, 0) -> #REF! | L19: =VLOOKUP($A$19,#REF!, 12, 0) -> #REF! | M19: =VLOOKUP($A$19,#REF!, 13, 0) -> #REF! | N19: =VLOOKUP($A$19,#REF!, 14, 0) -> #REF! | O19: =VLOOKUP($A$19,#REF!, 15, 0) -> #REF! | P19: =VLOOKUP($A$19,#REF!, 16, 0) -> #REF! | Q19: =VLOOKUP($A$19,#REF!, 17, 0) -> #REF! | R19: =VLOOKUP($A$19,#REF!, 18, 0) -> #REF! | S19: =VLOOKUP($A$19,#REF!, 19, 0) -> #REF! | T19: =Q19*0.02 -> #REF! | W19: =((S20-W18)/S20)*100 -> #REF!
L20: =IFERROR(L19/E19,0) -> 0 | M20: =IFERROR(M19/F19,0) -> 0 | N20: =IFERROR(N19/G19,0) -> 0 | O20: =IFERROR(O19/H19,0) -> 0 | P20: =IFERROR(P19/(K19+J19+I19),0) -> 0 | Q20: =IFERROR(Q19/D19,0) -> 0 | R20: =R19-(R19*(R1/100)) -> #REF! | S20: =R20+Q19+P19+T19 -> #REF! | T20: =IF(W19>30,"G",IF(AND(W19>25,W19<30),"A",IF(AND(W19>20,W19<25),"B","C"))) -> #REF!
R21: =R19-R20 -> #REF!
A22: Locket Lookup
A23: Sn | B23: Net Weight | C23: Wstg + MC | D23: Gross Weight | E23: Dmd <0.06 | F23: Dmd < 0.12 | G23: Dmd <0.17 | H23: Dmd Big | I23: Ruby | J23: Emreld | K23: Muga | L23: Dmd Price | M23: Dmd Price | N23: Dmd Price | O23: Dmd Price | P23: Stn Price | Q23: Gold Price | R23: Ttl dmd Price | S23: Total Price | T23: Tax | W23: =(((D24*0.6)/11.664)*Prices!A4)+E24*38000+F24*51900+G24*60900+H24*140000+I24*1000+J24*3000+K24*300 -> 293844.07
A24: 33 | B24: =VLOOKUP($A$24,Locket!A2:S999, 2, 0) -> 11.73 | C24: =VLOOKUP($A$24,Locket!A2:S999, 3, 0) -> 2.9325 | D24: =VLOOKUP($A$24,Locket!A2:S999, 4, 0) -> 14.6625 | E24: =VLOOKUP($A$24,Locket!A2:S999, 5, 0) -> 1.54 | F24: =VLOOKUP($A$24,Locket!A2:S999, 6, 0) | G24: =VLOOKUP($A$24,Locket!A2:S999, 7, 0) | H24: =VLOOKUP($A$24,Locket!A2:S999, 8, 0) | I24: =VLOOKUP($A$24,Locket!A2:S999, 9, 0) | J24: =VLOOKUP($A$24,Locket!A2:S999, 10, 0) | K24: =VLOOKUP($A$24,Locket!A2:S999, 11, 0) | L24: =VLOOKUP($A$24,Locket!A2:S999, 12, 0) -> 169400 | M24: =VLOOKUP($A$24,Locket!A2:S999, 13, 0) -> 0 | N24: =VLOOKUP($A$24,Locket!A2:S999, 14, 0) -> 0 | O24: =VLOOKUP($A$24,Locket!A2:S999, 15, 0) -> 0 | P24: =VLOOKUP($A$24,Locket!A2:S999, 16, 0) -> 0 | Q24: =VLOOKUP($A$24,Locket!A2:S999, 17, 0) -> 261725.62 | R24: =VLOOKUP($A$24,Locket!A2:S999, 18, 0) -> 169400 | S24: =VLOOKUP($A$24,Locket!A2:S999, 19, 0) -> 431125.62 | T24: =Q24*0.02 -> 5234.5125 | W24: =((S25-W23)/S25)*100 -> 20.281073
L25: =IFERROR(L24/E24,0) -> 110000 | M25: =IFERROR(M24/F24,0) -> 0 | N25: =IFERROR(N24/G24,0) -> 0 | O25: =IFERROR(O24/H24,0) -> 0 | P25: =IFERROR(P24/(K24+J24+I24),0) -> 0 | Q25: =IFERROR(Q24/D24,0) -> 17850 | R25: =R24-(R24*(R1/100)) -> 101640 | S25: =R25+Q24+P24+T24 -> 368600.14 | T25: =IF(W24>30,"G",IF(AND(W24>25,W24<30),"A",IF(AND(W24>20,W24<25),"B","C"))) -> B
R26: =R24-R25 -> 67760
A27: Jagganath Lookup
A28: Sn | B28: Net Weight | C28: Wstg + MC | D28: Gross weight | E28: Dmd <0.06 | F28: Dmd < 0.12 | G28: Dmd <0.17 | H28: Dmd Big | I28: Ruby | J28: Emreld | K28: Muga | L28: Dmd Price | M28: Dmd Price | N28: Dmd Price | O28: Dmd Price | P28: Stn Price | Q28: Gold Price | R28: Ttl dmd Price | S28: Total Price | T28: Tax | W28: =(((D29*0.6)/11.664)*Prices!A4)+E29*38000+F29*51900+G29*60900+H29*140000+I29*1000+J29*3000+K29*300 -> 45155.679
A29: 21 | B29: =VLOOKUP($A$29,Jagganath!A2:S996, 2, 0) -> 1.55 | C29: =VLOOKUP($A$29,Jagganath!A2:S996, 3, 0) -> 0.3875 | D29: =VLOOKUP($A$29,Jagganath!A2:S996, 4, 0) -> 1.9375 | E29: =VLOOKUP($A$29,Jagganath!A2:S996, 5, 0) -> 0.37 | F29: =VLOOKUP($A$29,Jagganath!A2:S996, 6, 0) | G29: =VLOOKUP($A$29,Jagganath!A2:S996, 7, 0) | H29: =VLOOKUP($A$29,Jagganath!A2:S996, 8, 0) | I29: =VLOOKUP($A$29,Jagganath!A2:S996, 9, 0) | J29: =VLOOKUP($A$29,Jagganath!A2:S996, 10, 0) | K29: =VLOOKUP($A$29,Jagganath!A2:S996, 11, 0) | L29: =VLOOKUP($A$29,Jagganath!A2:S996, 12, 0) -> 40700 | M29: =VLOOKUP($A$29,Jagganath!A2:S996, 13, 0) -> 0 | N29: =VLOOKUP($A$29,Jagganath!A2:S996, 14, 0) -> 0 | O29: =VLOOKUP($A$29,Jagganath!A2:S996, 15, 0) -> 0 | P29: =VLOOKUP($A$29,Jagganath!A2:S996, 16, 0) -> 0 | Q29: =VLOOKUP($A$29,Jagganath!A2:S996, 17, 0) -> 34584.375 | R29: =VLOOKUP($A$29,Jagganath!A2:S996, 18, 0) -> 40700 | S29: =VLOOKUP($A$29,Jagganath!A2:S996, 19, 0) -> 75284.375 | T29: =Q29*0.02 -> 691.6875 | W29: =((S30-W28)/S30)*100 -> 24.357358
L30: =IFERROR(L29/E29,0) -> 110000 | M30: =IFERROR(M29/F29,0) -> 0 | N30: =IFERROR(N29/G29,0) -> 0 | O30: =IFERROR(O29/H29,0) -> 0 | P30: =IFERROR(P29/(K29+J29+I29),0) -> 0 | Q30: =IFERROR(Q29/D29,0) -> 17850 | R30: =R29-(R29*(R1/100)) -> 24420 | S30: =R30+Q29+P29+T29 -> 59696.062 | T30: =IF(W29>30,"G",IF(AND(W29>25,W29<30),"A",IF(AND(W29>20,W29<25),"B","C"))) -> B
R31: =R29-R30 -> 16280
A32: Jagganath Lookup
A33: Sn | B33: Net Weight | C33: Wstg + MC | D33: Gross weight | E33: Dmd <0.06 | F33: Dmd < 0.12 | G33: Dmd <0.17 | H33: Dmd Big | I33: Ruby | J33: Emreld | K33: Muga | L33: Dmd Price | M33: Dmd Price | N33: Dmd Price | O33: Dmd Price | P33: Stn Price | Q33: Gold Price | R33: Ttl dmd Price | S33: Total Price | T33: Tax | W33: =(((D34*0.6)/11.664)*Prices!A4)+E34*38000+F34*51900+G34*60900+H34*140000+I34*1000+J34*3000+K34*300 -> 51735.926
A34: 85720 | B34: =VLOOKUP($A$34,Prithivi!A2:S995, 2, 0) -> 1.878 | C34: =VLOOKUP($A$34,Prithivi!A2:S995, 3, 0) -> 0.4695 | D34: =VLOOKUP($A$34,Prithivi!A2:S995, 4, 0) -> 2.3475 | E34: =VLOOKUP($A$34,Prithivi!A2:S995, 5, 0) -> 0.37 | F34: =VLOOKUP($A$34,Prithivi!A2:S995, 6, 0) | G34: =VLOOKUP($A$34,Prithivi!A2:S995, 7, 0) | H34: =VLOOKUP($A$34,Prithivi!A2:S995, 8, 0) | I34: =VLOOKUP($A$34,Prithivi!A2:S995, 9, 0) | J34: =VLOOKUP($A$34,Prithivi!A2:S995, 10, 0) | K34: =VLOOKUP($A$34,Prithivi!A2:S995, 11, 0) | L34: =VLOOKUP($A$34,Prithivi!A2:S995, 12, 0) -> 40700 | M34: =VLOOKUP($A$34,Prithivi!A2:S995, 13, 0) -> 0 | N34: =VLOOKUP($A$34,Prithivi!A2:S995, 14, 0) -> 0 | O34: =VLOOKUP($A$34,Prithivi!A2:S995, 15, 0) -> 0 | P34: =VLOOKUP($A$34,Prithivi!A2:S995, 16, 0) -> 0 | Q34: =VLOOKUP($A$34,Prithivi!A2:S995, 17, 0) -> 41902.875 | R34: =VLOOKUP($A$34,Prithivi!A2:S995, 18, 0) -> 40700 | S34: =VLOOKUP($A$34,Prithivi!A2:S995, 19, 0) -> 82602.875 | T34: =Q34*0.02 -> 838.0575 | W34: =((S35-W33)/S35)*100 -> 22.967231
L35: =IFERROR(L34/E34,0) -> 110000 | M35: =IFERROR(M34/F34,0) -> 0 | N35: =IFERROR(N34/G34,0) -> 0 | O35: =IFERROR(O34/H34,0) -> 0 | P35: =IFERROR(P34/(K34+J34+I34),0) -> 0 | Q35: =IFERROR(Q34/D34,0) -> 17850 | R35: =R34-(R34*(R1/100)) -> 24420 | S35: =R35+Q34+P34+T34 -> 67160.932 | T35: =IF(W34>30,"G",IF(AND(W34>25,W34<30),"A",IF(AND(W34>20,W34<25),"B","C"))) -> B
R36: =R34-R35 -> 16280
A37: Necklace Lookup
A38: Sn | B38: Net Weight | C38: Wstg + MC | D38: Gross weight | E38: Dmd <0.06 | F38: Dmd < 0.12 | G38: Dmd <0.17 | H38: Dmd Big | I38: Ruby | J38: Emreld | K38: Muga | L38: Dmd Price | M38: Dmd Price | N38: Dmd Price | O38: Dmd Price | P38: Stn Price | Q38: Gold Price | R38: Ttl dmd Price | S38: Total Price | T38: Tax | W38: =(((D39*0.6)/11.664)*Prices!A4)+E39*38000+F39*51900+G39*60900+H39*140000+I39*1000+J39*3000+K39*300 -> 696704.9
A39: 1 | B39: =VLOOKUP($A$39,Necklace!A1:T999, 2, 0) -> 23.132 | C39: =VLOOKUP($A$39,Necklace!A1:T999, 3, 0) -> 5.783 | D39: =VLOOKUP($A$39,Necklace!A1:T999, 4, 0) -> 28.915 | E39: =VLOOKUP($A$39,Necklace!A1:T999, 5, 0) -> 6.1 | F39: =VLOOKUP($A$39,Necklace!A1:T999, 6, 0) | G39: =VLOOKUP($A$39,Necklace!A1:T999, 7, 0) | H39: =VLOOKUP($A$39,Necklace!A1:T999, 8, 0) | I39: =VLOOKUP($A$39,Necklace!A1:T999, 9, 0) | J39: =VLOOKUP($A$39,Necklace!A1:T999, 10, 0) | K39: =VLOOKUP($A$39,Necklace!A1:T999, 11, 0) -> 2.79 | L39: =VLOOKUP($A$39,Necklace!A1:T999, 12, 0) -> 671000 | M39: =VLOOKUP($A$39,Necklace!A1:T999, 13, 0) -> 0 | N39: =VLOOKUP($A$39,Necklace!A1:T999, 14, 0) -> 0 | O39: =VLOOKUP($A$39,Necklace!A1:T999, 15, 0) -> 0 | P39: =VLOOKUP($A$39,Necklace!A1:T999, 16, 0) -> 1813.5 | Q39: =VLOOKUP($A$39,Necklace!A1:T999, 17, 0) -> 516132.75 | R39: =VLOOKUP($A$39,Necklace!A1:T999, 18, 0) -> 671000 | S39: =VLOOKUP($A$39,Necklace!A1:T999, 19, 0) -> 1188946.2 | T39: =Q39*0.02 -> 10322.655 | W39: =((S40-W38)/S40)*100 -> 25.155422
L40: =IFERROR(L39/E39,0) -> 110000 | M40: =IFERROR(M39/F39,0) -> 0 | N40: =IFERROR(N39/G39,0) -> 0 | O40: =IFERROR(O39/H39,0) -> 0 | P40: =IFERROR(P39/(K39+J39+I39),0) -> 650 | Q40: =IFERROR(Q39/D39,0) -> 17850 | R40: =R39-(R39*(R1/100)) -> 402600 | S40: =R40+Q39+P39+T39 -> 930868.91 | T40: =IF(W34>30,"G",IF(AND(W34>25,W34<30),"A",IF(AND(W34>20,W34<25),"B","C"))) -> B
R41: =R39-R40 -> 268400
A42: Chura Lookup
A43: Sn | B43: Net Weight | C43: Wstg + MC | D43: Gross weight | E43: Dmd <0.06 | F43: Dmd < 0.12 | G43: Dmd <0.17 | H43: Dmd Big | I43: Ruby | J43: Emreld | K43: Muga | L43: Dmd Price | M43: Dmd Price | N43: Dmd Price | O43: Dmd Price | P43: Stn Price | Q43: Gold Price | R43: Ttl dmd Price | S43: Total Price | T43: Tax | W43: =(((D44*0.6)/11.664)*Prices!A4)+E44*38000+F44*51900+G44*60900+H44*140000+I44*1000+J44*3000+K44*300 -> 839867.53
A44: 268 | B44: =VLOOKUP($A$44,Chura!A1:T999, 2, 0) -> 33.17 | C44: =VLOOKUP($A$44,Chura!A1:T999, 3, 0) -> 8.2925 | D44: =VLOOKUP($A$44,Chura!A1:T999, 4, 0) -> 41.4625 | E44: =VLOOKUP($A$44,Chura!A1:T999, 5, 0) -> 4.59 | F44: =VLOOKUP($A$44,Chura!A1:T999, 6, 0) | G44: =VLOOKUP($A$44,Chura!A1:T999, 7, 0) | H44: =VLOOKUP($A$44,Chura!A1:T999, 8, 0) | I44: =VLOOKUP($A$44,Chura!A1:T999, 9, 0) | J44: =VLOOKUP($A$44,Chura!A1:T999, 10, 0) | K44: =VLOOKUP($A$44,Chura!A1:T999, 11, 0) | L44: =VLOOKUP($A$44,Chura!A1:T999, 12, 0) -> 504900 | M44: =VLOOKUP($A$44,Chura!A1:T999, 13, 0) -> 0 | N44: =VLOOKUP($A$44,Chura!A1:T999, 14, 0) -> 0 | O44: =VLOOKUP($A$44,Chura!A1:T999, 15, 0) -> 0 | P44: =VLOOKUP($A$44,Chura!A1:T999, 16, 0) -> 0 | Q44: =VLOOKUP($A$44,Chura!A1:T999, 17, 0) -> 740105.62 | R44: =VLOOKUP($A$44,Chura!A1:T999, 18, 0) -> 504900 | S44: =VLOOKUP($A$44,Chura!A1:T999, 19, 0) -> 1245005.6 | T44: =Q44*0.02 -> 14802.112 | W44: =((S45-W43)/S45)*100 -> 20.60601
L45: =IFERROR(L44/E44,0) -> 110000 | M45: =IFERROR(M44/F44,0) -> 0 | N45: =IFERROR(N44/G44,0) -> 0 | O45: =IFERROR(O44/H44,0) -> 0 | P45: =IFERROR(P44/(K44+J44+I44),0) -> 0 | Q45: =IFERROR(Q44/D44,0) -> 17850 | R45: =R44-(R44*(R1/100)) -> 302940 | S45: =R45+Q44+P44+T44 -> 1057847.7 | T45: =IF(W39>30,"G",IF(AND(W39>25,W39<30),"A",IF(AND(W39>20,W39<25),"B","C"))) -> A
R46: =R44-R45 -> 201960

Sheet Ladies Ring
A1: Sn | B1: Net Weight | C1: Wstg + MC | D1: Gross Weight | E1: Dmd <0.06 | F1: Dmd < 0.12 | G1: Dmd <0.17 | H1: Dmd Big | I1: Ruby | J1: Emreld | K1: Muga | L1: Dmd Price | M1: Dmd Price | N1: Dmd Price | O1: Dmd Price | P1: Stn Price | Q1: Gold Price | R1: Ttl dmd Price | S1: Total Price | T1: Sn
A2: 1 | B2: 6.06 | C2: =B2*(25/100) -> 1.515 | D2: =C2+B2 -> 7.575 | E2: 0.54 | L2: =E2*Prices!B$2 -> 59400 | M2: =F2*Prices!C$2 -> 0 | N2: =G2*Prices!D$2 -> 0 | O2: =H2*Prices!E$2 -> 0 | P2: =I2*2000+J2*10000+K2*1800 -> 0 | Q2: =D2*Prices!A$2 -> 135213.75 | R2: =L2+M2+N2+O2 -> 59400 | S2: =R2+Q2+P2 -> 194613.75 | T2: 1 | U2: Available | V2: A
A3: 2 | B3: 2.986 | C3: =B3*(25/100) -> 0.7465 | D3: =C3+B3 -> 3.7325 | E3: 0.5 | L3: =E3*Prices!B$2 -> 55000 | M3: =F3*Prices!C$2 -> 0 | N3: =G3*Prices!D$2 -> 0 | O3: =H3*Prices!E$2 -> 0 | P3: =I3*2000+J3*10000+K3*1800 -> 0 | Q3: =D3*Prices!A$2 -> 66625.125 | R3: =L3+M3+N3+O3 -> 55000 | S3: =R3+Q3+P3 -> 121625.12 | T3: 2 | U3: Sold
A4: 3 | B4: 5.86 | C4: =B4*(25/100) -> 1.465 | D4: =C4+B4 -> 7.325 | E4: 1.19 | L4: =E4*Prices!B$2 -> 130900 | M4: =F4*Prices!C$2 -> 0 | N4: =G4*Prices!D$2 -> 0 | O4: =H4*Prices!E$2 -> 0 | P4: =I4*2000+J4*10000+K4*1800 -> 0 | Q4: =D4*Prices!A$2 -> 130751.25 | R4: =L4+M4+N4+O4 -> 130900 | S4: =R4+Q4+P4 -> 261651.25 | T4: 3 | U4: Sold
A5: 4 | B5: 1.79 | C5: =B5*(25/100) -> 0.4475 | D5: =C5+B5 -> 2.2375 | E5: 0.18 | L5: =E5*Prices!B$2 -> 19800 | M5: =F5*Prices!C$2 -> 0 | N5: =G5*Prices!D$2 -> 0 | O5: =H5*Prices!E$2 -> 0 | P5: =I5*2000+J5*10000+K5*1800 -> 0 | Q5: =D5*Prices!A$2 -> 39939.375 | R5: =L5+M5+N5+O5 -> 19800 | S5: =R5+Q5+P5 -> 59739.375 | T5: 4 | U5: Sold
A6: 5 | B6: 2.194 | C6: =B6*(25/100) -> 0.5485 | D6: =C6+B6 -> 2.7425 | E6: 0.35 | L6: =E6*Prices!B$2 -> 38500 | M6: =F6*Prices!C$2 -> 0 | N6: =G6*Prices!D$2 -> 0 | O6: =H6*Prices!E$2 -> 0 | P6: =I6*2000+J6*10000+K6*1800 -> 0 | Q6: =D6*Prices!A$2 -> 48953.625 | R6: =L6+M6+N6+O6 -> 38500 | S6: =R6+Q6+P6 -> 87453.625 | T6: 5 | U6: Sold
A7: 6 | B7: 1.95 | C7: =B7*(25/100) -> 0.4875 | D7: =C7+B7 -> 2.4375 | E7: 0.33 | L7: =E7*Prices!B$2 -> 36300 | M7: =F7*Prices!C$2 -> 0 | N7: =G7*Prices!D$2 -> 0 | O7: =H7*Prices!E$2 -> 0 | P7: =I7*2000+J7*10000+K7*1800 -> 0 | Q7: =D7*Prices!A$2 -> 43509.375 | R7: =L7+M7+N7+O7 -> 36300 | S7: =R7+Q7+P7 -> 79809.375 | T7: 6 | U7: Available | V7: A
A8: 7 | B8: 2.75 | C8: =B8*(25/100) -> 0.6875 | D8: =C8+B8 -> 3.4375 | E8: 0.75 | L8: =E8*Prices!B$2 -> 82500 | M8: =F8*Prices!C$2 -> 0 | N8: =G8*Prices!D$2 -> 0 | O8: =H8*Prices!E$2 -> 0 | P8: =I8*2000+J8*10000+K8*1800 -> 0 | Q8: =D8*Prices!A$2 -> 61359.375 | R8: =L8+M8+N8+O8 -> 82500 | S8: =R8+Q8+P8 -> 143859.38 | T8: 7 | U8: Sold
A9: 8 | B9: 3.58 | C9: =B9*(25/100) -> 0.895 | D9: =C9+B9 -> 4.475 | E9: 0.41 | I9: 1.26 | L9: =E9*Prices!B$2 -> 45100 | M9: =F9*Prices!C$2 -> 0 | N9: =G9*Prices!D$2 -> 0 | O9: =H9*Prices!E$2 -> 0 | P9: =I9*2000+J9*10000+K9*1800 -> 2520 | Q9: =D9*Prices!A$2 -> 79878.75 | R9: =L9+M9+N9+O9 -> 45100 | S9: =R9+Q9+P9 -> 127498.75 | T9: 8 | U9: Return
A10: 9 | B10: 2.7 | C10: =B10*(25/100) -> 0.675 | D10: =C10+B10 -> 3.375 | E10: 0.56 | L10: =E10*Prices!B$2 -> 61600 | M10: =F10*Prices!C$2 -> 0 | N10: =G10*Prices!D$2 -> 0 | O10: =H10*Prices!E$2 -> 0 | P10: =I10*2000+J10*10000+K10*1800 -> 0 | Q10: =D10*Prices!A$2 -> 60243.75 | R10: =L10+M10+N10+O10 -> 61600 | S10: =R10+Q10+P10 -> 121843.75 | T10: 9 | U10: Available
A11: 10 | B11: 2.694 | C11: =B11*(25/100) -> 0.6735 | D11: =C11+B11 -> 3.3675 | E11: 0.53 | L11: =E11*Prices!B$2 -> 58300 | M11: =F11*Prices!C$2 -> 0 | N11: =G11*Prices!D$2 -> 0 | O11: =H11*Prices!E$2 -> 0 | P11: =I11*2000+J11*10000+K11*1800 -> 0 | Q11: =D11*Prices!A$2 -> 60109.875 | R11: =L11+M11+N11+O11 -> 58300 | S11: =R11+Q11+P11 -> 118409.88 | T11: 10 | U11: Sold
A12: 11 | B12: 3.66 | C12: =B12*(25/100) -> 0.915 | D12: =C12+B12 -> 4.575 | E12: 0.69 | L12: =E12*Prices!B$2 -> 75900 | M12: =F12*Prices!C$2 -> 0 | N12: =G12*Prices!D$2 -> 0 | O12: =H12*Prices!E$2 -> 0 | P12: =I12*2000+J12*10000+K12*1800 -> 0 | Q12: =D12*Prices!A$2 -> 81663.75 | R12: =L12+M12+N12+O12 -> 75900 | S12: =R12+Q12+P12 -> 157563.75 | T12: 11 | U12: Available | V12: A
A13: 12 | B13: 1.568 | C13: =B13*(25/100) -> 0.392 | D13: =C13+B13 -> 1.96 | E13: 0.36 | L13: =E13*Prices!B$2 -> 39600 | M13: =F13*Prices!C$2 -> 0 | N13: =G13*Prices!D$2 -> 0 | O13: =H13*Prices!E$2 -> 0 | P13: =I13*2000+J13*10000+K13*1800 -> 0 | Q13: =D13*Prices!A$2 -> 34986 | R13: =L13+M13+N13+O13 -> 39600 | S13: =R13+Q13+P13 -> 74586 | T13: 12 | U13: Available | V13: A
A14: 13 | B14: 2.48 | C14: =B14*(25/100) -> 0.62 | D14: =C14+B14 -> 3.1 | E14: 0.49 | L14: =E14*Prices!B$2 -> 53900 | M14: =F14*Prices!C$2 -> 0 | N14: =G14*Prices!D$2 -> 0 | O14: =H14*Prices!E$2 -> 0 | P14: =I14*2000+J14*10000+K14*1800 -> 0 | Q14: =D14*Prices!A$2 -> 55335 | R14: =L14+M14+N14+O14 -> 53900 | S14: =R14+Q14+P14 -> 109235 | T14: 13 | U14: Sold
A15: 14 | B15: 2.92 | C15: =B15*(25/100) -> 0.73 | D15: =C15+B15 -> 3.65 | E15: 0.83 | L15: =E15*Prices!B$2 -> 91300 | M15: =F15*Prices!C$2 -> 0 | N15: =G15*Prices!D$2 -> 0 | O15: =H15*Prices!E$2 -> 0 | P15: =I15*2000+J15*10000+K15*1800 -> 0 | Q15: =D15*Prices!A$2 -> 65152.5 | R15: =L15+M15+N15+O15 -> 91300 | S15: =R15+Q15+P15 -> 156452.5 | T15: 14 | U15: Available | V15: A
A16: 15 | B16: 5.11 | C16: =B16*(25/100) -> 1.2775 | D16: =C16+B16 -> 6.3875 | E16: 1.24 | L16: =E16*Prices!B$2 -> 136400 | M16: =F16*Prices!C$2 -> 0 | N16: =G16*Prices!D$2 -> 0 | O16: =H16*Prices!E$2 -> 0 | P16: =I16*2000+J16*10000+K16*1800 -> 0 | Q16: =D16*Prices!A$2 -> 114016.88 | R16: =L16+M16+N16+O16 -> 136400 | S16: =R16+Q16+P16 -> 250416.88 | T16: 15 | U16: Sold
A17: 16 | B17: 3.182 | C17: =B17*(25/100) -> 0.7955 | D17: =C17+B17 -> 3.9775 | E17: 0.79 | L17: =E17*Prices!B$2 -> 86900 | M17: =F17*Prices!C$2 -> 0 | N17: =G17*Prices!D$2 -> 0 | O17: =H17*Prices!E$2 -> 0 | P17: =I17*2000+J17*10000+K17*1800 -> 0 | Q17: =D17*Prices!A$2 -> 70998.375 | R17: =L17+M17+N17+O17 -> 86900 | S17: =R17+Q17+P17 -> 157898.38 | T17: 16 | U17: Sold
A18: 17 | B18: 2.984 | C18: =B18*(25/100) -> 0.746 | D18: =C18+B18 -> 3.73 | E18: 0.88 | L18: =E18*Prices!B$2 -> 96800 | M18: =F18*Prices!C$2 -> 0 | N18: =G18*Prices!D$2 -> 0 | O18: =H18*Prices!E$2 -> 0 | P18: =I18*2000+J18*10000+K18*1800 -> 0 | Q18: =D18*Prices!A$2 -> 66580.5 | R18: =L18+M18+N18+O18 -> 96800 | S18: =R18+Q18+P18 -> 163380.5 | T18: 17 | U18: Available | V18: A
A19: 18 | B19: 3.174 | C19: =B19*(25/100) -> 0.7935 | D19: =C19+B19 -> 3.9675 | E19: 0.68 | L19: =E19*Prices!B$2 -> 74800 | M19: =F19*Prices!C$2 -> 0 | N19: =G19*Prices!D$2 -> 0 | O19: =H19*Prices!E$2 -> 0 | P19: =I19*2000+J19*10000+K19*1800 -> 0 | Q19: =D19*Prices!A$2 -> 70819.875 | R19: =L19+M19+N19+O19 -> 74800 | S19: =R19+Q19+P19 -> 145619.88 | T19: 18 | U19: Sold
A20: 19 | B20: 3.282 | C20: =B20*(25/100) -> 0.8205 | D20: =C20+B20 -> 4.1025 | E20: 0.89 | L20: =E20*Prices!B$2 -> 97900 | M20: =F20*Prices!C$2 -> 0 | N20: =G20*Prices!D$2 -> 0 | O20: =H20*Prices!E$2 -> 0 | P20: =I20*2000+J20*10000+K20*1800 -> 0 | Q20: =D20*Prices!A$2 -> 73229.625 | R20: =L20+M20+N20+O20 -> 97900 | S20: =R20+Q20+P20 -> 171129.62 | T20: 19 | U20: Sold
A21: 20 | B21: 3.786 | C21: =B21*(25/100) -> 0.9465 | D21: =C21+B21 -> 4.7325 | E21: 0.77 | L21: =E21*Prices!B$2 -> 84700 | M21: =F21*Prices!C$2 -> 0 | N21: =G21*Prices!D$2 -> 0 | O21: =H21*Prices!E$2 -> 0 | P21: =I21*2000+J21*10000+K21*1800 -> 0 | Q21: =D21*Prices!A$2 -> 84475.125 | R21: =L21+M21+N21+O21 -> 84700 | S21: =R21+Q21+P21 -> 169175.12 | T21: 20 | U21: Sold
A22: 21 | B22: 1.324 | C22: =B22*(25/100) -> 0.331 | D22: =C22+B22 -> 1.655 | E22: 0.13 | L22: =E22*Prices!B$2 -> 14300 | M22: =F22*Prices!C$2 -> 0 | N22: =G22*Prices!D$2 -> 0 | O22: =H22*Prices!E$2 -> 0 | P22: =I22*2000+J22*10000+K22*1800 -> 0 | Q22: =D22*Prices!A$2 -> 29541.75 | R22: =L22+M22+N22+O22 -> 14300 | S22: =R22+Q22+P22 -> 43841.75 | T22: 21 | U22: Sold
A23: 22 | B23: 3.664 | C23: =B23*(25/100) -> 0.916 | D23: =C23+B23 -> 4.58 | E23: 0.2774 | L23: =E23*Prices!B$2 -> 30514 | M23: =F23*Prices!C$2 -> 0 | N23: =G23*Prices!D$2 -> 0 | O23: =H23*Prices!E$2 -> 0 | P23: =I23*2000+J23*10000+K23*1800 -> 0 | Q23: =D23*Prices!A$2 -> 81753 | R23: =L23+M23+N23+O23 -> 30514 | S23: =R23+Q23+P23 -> 112267 | T23: 22 | U23: Sold
A24: 23 | B24: 2.65 | C24: =B24*(25/100) -> 0.6625 | D24: =C24+B24 -> 3.3125 | E24: 0.46 | L24: =E24*Prices!B$2 -> 50600 | M24: =F24*Prices!C$2 -> 0 | N24: =G24*Prices!D$2 -> 0 | O24: =H24*Prices!E$2 -> 0 | P24: =I24*2000+J24*10000+K24*1800 -> 0 | Q24: =D24*Prices!A$2 -> 59128.125 | R24: =L24+M24+N24+O24 -> 50600 | S24: =R24+Q24+P24 -> 109728.12 | T24: 23 | U24: Sold
A25: 24 | B25: 2.83 | C25: =B25*(25/100) -> 0.7075 | D25: =C25+B25 -> 3.5375 | E25: 0.35 | L25: =E25*Prices!B$2 -> 38500 | M25: =F25*Prices!C$2 -> 0 | N25: =G25*Prices!D$2 -> 0 | O25: =H25*Prices!E$2 -> 0 | P25: =I25*2000+J25*10000+K25*1800 -> 0 | Q25: =D25*Prices!A$2 -> 63144.375 | R25: =L25+M25+N25+O25 -> 38500 | S25: =R25+Q25+P25 -> 101644.38 | T25: 24 | U25: Sold
A26: 25 | B26: 2.564 | C26: =B26*(25/100) -> 0.641 | D26: =C26+B26 -> 3.205 | E26: 0.38 | L26: =E26*Prices!B$2 -> 41800 | M26: =F26*Prices!C$2 -> 0 | N26: =G26*Prices!D$2 -> 0 | O26: =H26*Prices!E$2 -> 0 | P26: =I26*2000+J26*10000+K26*1800 -> 0 | Q26: =D26*Prices!A$2 -> 57209.25 | R26: =L26+M26+N26+O26 -> 41800 | S26: =R26+Q26+P26 -> 99009.25 | T26: 25 | U26: Sold
A27: 26 | B27: 2.706 | C27: =B27*(25/100) -> 0.6765 | D27: =C27+B27 -> 3.3825 | E27: 0.52 | L27: =E27*Prices!B$2 -> 57200 | M27: =F27*Prices!C$2 -> 0 | N27: =G27*Prices!D$2 -> 0 | O27: =H27*Prices!E$2 -> 0 | P27: =I27*2000+J27*10000+K27*1800 -> 0 | Q27: =D27*Prices!A$2 -> 60377.625 | R27: =L27+M27+N27+O27 -> 57200 | S27: =R27+Q27+P27 -> 117577.62 | T27: 26 | U27: Sold
A28: 27 | B28: 2.76 | C28: =B28*(25/100) -> 0.69 | D28: =C28+B28 -> 3.45 | E28: 0.33 | L28: =E28*Prices!B$2 -> 36300 | M28: =F28*Prices!C$2 -> 0 | N28: =G28*Prices!D$2 -> 0 | O28: =H28*Prices!E$2 -> 0 | P28: =I28*2000+J28*10000+K28*1800 -> 0 | Q28: =D28*Prices!A$2 -> 61582.5 | R28: =L28+M28+N28+O28 -> 36300 | S28: =R28+Q28+P28 -> 97882.5 | T28: 27 | U28: Available | V28: A
A29: 28 | B29: 1.904 | C29: =B29*(25/100) -> 0.476 | D29: =C29+B29 -> 2.38 | E29: 0.28 | L29: =E29*Prices!B$2 -> 30800 | M29: =F29*Prices!C$2 -> 0 | N29: =G29*Prices!D$2 -> 0 | O29: =H29*Prices!E$2 -> 0 | P29: =I29*2000+J29*10000+K29*1800 -> 0 | Q29: =D29*Prices!A$2 -> 42483 | R29: =L29+M29+N29+O29 -> 30800 | S29: =R29+Q29+P29 -> 73283 | T29: 28 | U29: Sold
A30: 29 | B30: 9.384 | C30: =B30*(25/100) -> 2.346 | D30: =C30+B30 -> 11.73 | E30: 1.38 | K30: 8 | L30: =E30*Prices!B$2 -> 151800 | M30: =F30*Prices!C$2 -> 0 | N30: =G30*Prices!D$2 -> 0 | O30: =H30*Prices!E$2 -> 0 | P30: =I30*2000+J30*10000+K30*1800 -> 14400 | Q30: =D30*Prices!A$2 -> 209380.5 | R30: =L30+M30+N30+O30 -> 151800 | S30: =R30+Q30+P30 -> 375580.5 | T30: 29 | U30: Available | V30: A
A31: 30 | B31: 7.69 | C31: =B31*(25/100) -> 1.9225 | D31: =C31+B31 -> 9.6125 | E31: 0.98 | K31: 6.42 | L31: =E31*Prices!B$2 -> 107800 | M31: =F31*Prices!C$2 -> 0 | N31: =G31*Prices!D$2 -> 0 | O31: =H31*Prices!E$2 -> 0 | P31: =I31*2000+J31*10000+K31*1800 -> 11556 | Q31: =D31*Prices!A$2 -> 171583.12 | R31: =L31+M31+N31+O31 -> 107800 | S31: =R31+Q31+P31 -> 290939.12 | T31: 30 | U31: Sold
A32: 31 | B32: 4.37 | C32: =B32*(25/100) -> 1.0925 | D32: =C32+B32 -> 5.4625 | E32: 0.54 | K32: 9.96 | L32: =E32*Prices!B$2 -> 59400 | M32: =F32*Prices!C$2 -> 0 | N32: =G32*Prices!D$2 -> 0 | O32: =H32*Prices!E$2 -> 0 | P32: =I32*2000+J32*10000+K32*1800 -> 17928 | Q32: =D32*Prices!A$2 -> 97505.625 | R32: =L32+M32+N32+O32 -> 59400 | S32: =R32+Q32+P32 -> 174833.62 | T32: 31 | U32: Sold
A33: 32 | B33: 6.42 | C33: =B33*(25/100) -> 1.605 | D33: =C33+B33 -> 8.025 | E33: 0.95 | L33: =E33*Prices!B$2 -> 104500 | M33: =F33*Prices!C$2 -> 0 | N33: =G33*Prices!D$2 -> 0 | O33: =H33*Prices!E$2 -> 0 | P33: =I33*2000+J33*10000+K33*1800 -> 0 | Q33: =D33*Prices!A$2 -> 143246.25 | R33: =L33+M33+N33+O33 -> 104500 | S33: =R33+Q33+P33 -> 247746.25 | T33: 32 | U33: Sold
A34: 33 | B34: 3.194 | C34: =B34*(25/100) -> 0.7985 | D34: =C34+B34 -> 3.9925 | E34: 0.7 | F34: 0.08 | L34: =E34*Prices!B$2 -> 77000 | M34: =F34*Prices!C$2 -> 12800 | N34: =G34*Prices!D$2 -> 0 | O34: =H34*Prices!E$2 -> 0 | P34: =I34*2000+J34*10000+K34*1800 -> 0 | Q34: =D34*Prices!A$2 -> 71266.125 | R34: =L34+M34+N34+O34 -> 89800 | S34: =R34+Q34+P34 -> 161066.12 | T34: 33 | U34: Sold
A35: 34 | B35: 4.4 | C35: =B35*(25/100) -> 1.1 | D35: =C35+B35 -> 5.5 | E35: 1.22 | L35: =E35*Prices!B$2 -> 134200 | M35: =F35*Prices!C$2 -> 0 | N35: =G35*Prices!D$2 -> 0 | O35: =H35*Prices!E$2 -> 0 | P35: =I35*2000+J35*10000+K35*1800 -> 0 | Q35: =D35*Prices!A$2 -> 98175 | R35: =L35+M35+N35+O35 -> 134200 | S35: =R35+Q35+P35 -> 232375 | T35: 34 | U35: Available | V35: A
A36: 35 | B36: 4.31 | C36: =B36*(25/100) -> 1.0775 | D36: =C36+B36 -> 5.3875 | E36: 0.6 | J36: 0.7 | L36: =E36*Prices!B$2 -> 66000 | M36: =F36*Prices!C$2 -> 0 | N36: =G36*Prices!D$2 -> 0 | O36: =H36*Prices!E$2 -> 0 | P36: =I36*2000+J36*10000+K36*1800 -> 7000 | Q36: =D36*Prices!A$2 -> 96166.875 | R36: =L36+M36+N36+O36 -> 66000 | S36: =R36+Q36+P36 -> 169166.88 | T36: 35 | U36: Available | V36: A
A37: 36 | B37: 8.02 | C37: =B37*(25/100) -> 2.005 | D37: =C37+B37 -> 10.025 | E37: 0.96 | J37: 2.68 | L37: =E37*Prices!B$2 -> 105600 | M37: =F37*Prices!C$2 -> 0 | N37: =G37*Prices!D$2 -> 0 | O37: =H37*Prices!E$2 -> 0 | P37: =I37*2000+J37*10000+K37*1800 -> 26800 | Q37: =D37*Prices!A$2 -> 178946.25 | R37: =L37+M37+N37+O37 -> 105600 | S37: =R37+Q37+P37 -> 311346.25 | T37: 36 | U37: Sold
A38: 37 | B38: 3.8 | C38: =B38*(25/100) -> 0.95 | D38: =C38+B38 -> 4.75 | E38: 0.33 | J38: 1.1 | L38: =E38*Prices!B$2 -> 36300 | M38: =F38*Prices!C$2 -> 0 | N38: =G38*Prices!D$2 -> 0 | O38: =H38*Prices!E$2 -> 0 | P38: =I38*2000+J38*10000+K38*1800 -> 11000 | Q38: =D38*Prices!A$2 -> 84787.5 | R38: =L38+M38+N38+O38 -> 36300 | S38: =R38+Q38+P38 -> 132087.5 | T38: 37 | U38: Available | V38: A
A39: 38 | B39: 5.562 | C39: =B39*(25/100) -> 1.3905 | D39: =C39+B39 -> 6.9525 | E39: 1.16 | J39: 1.63 | L39: =E39*Prices!B$2 -> 127600 | M39: =F39*Prices!C$2 -> 0 | N39: =G39*Prices!D$2 -> 0 | O39: =H39*Prices!E$2 -> 0 | P39: =I39*2000+J39*10000+K39*1800 -> 16300 | Q39: =D39*Prices!A$2 -> 124102.12 | R39: =L39+M39+N39+O39 -> 127600 | S39: =R39+Q39+P39 -> 268002.12 | T39: 38 | U39: Sold
A40: 39 | B40: 2.66 | C40: =B40*(25/100) -> 0.665 | D40: =C40+B40 -> 3.325 | H40: 0.71 | L40: =E40*Prices!B$2 -> 0 | M40: =F40*Prices!C$2 -> 0 | N40: =G40*Prices!D$2 -> 0 | O40: =H40*360000 -> 255600 | P40: =I40*2000+J40*10000+K40*1800 -> 0 | Q40: =D40*Prices!A$2 -> 59351.25 | R40: =L40+M40+N40+O40 -> 255600 | S40: =R40+Q40+P40 -> 314951.25 | T40: 39 | U40: Available | V40: A
A41: 40 | B41: 3.204 | C41: =B41*(25/100) -> 0.801 | D41: =C41+B41 -> 4.005 | E41: 0.5 | H41: 0.28 | L41: =E41*Prices!B$2 -> 55000 | M41: =F41*Prices!C$2 -> 0 | N41: =G41*Prices!D$2 -> 0 | O41: =H41*200000 -> 56000 | P41: =I41*2000+J41*10000+K41*1800 -> 0 | Q41: =D41*Prices!A$2 -> 71489.25 | R41: =L41+M41+N41+O41 -> 111000 | S41: =R41+Q41+P41 -> 182489.25 | T41: 40 | U41: Available | V41: A
A42: 41 | B42: 3.91 | C42: =B42*(25/100) -> 0.9775 | D42: =C42+B42 -> 4.8875 | H42: 0.7 | L42: =E42*Prices!B$2 -> 0 | M42: =F42*Prices!C$2 -> 0 | N42: =G42*Prices!D$2 -> 0 | O42: =H42*360000 -> 252000 | P42: =I42*2000+J42*10000+K42*1800 -> 0 | Q42: =D42*Prices!A$2 -> 87241.875 | R42: =L42+M42+N42+O42 -> 252000 | S42: =R42+Q42+P42 -> 339241.88 | T42: 41 | U42: Sold
A43: 42 | B43: 3.688 | C43: =B43*(25/100) -> 0.922 | D43: =C43+B43 -> 4.61 | H43: 0.56 | L43: =E43*Prices!B$2 -> 0 | M43: =F43*Prices!C$2 -> 0 | N43: =G43*Prices!D$2 -> 0 | O43: =H43*290000 -> 162400 | P43: =I43*2000+J43*10000+K43*1800 -> 0 | Q43: =D43*Prices!A$2 -> 82288.5 | R43: =L43+M43+N43+O43 -> 162400 | S43: =R43+Q43+P43 -> 244688.5 | T43: 42 | U43: Available | V43: A
A44: 43 | B44: 4.006 | C44: =B44*(25/100) -> 1.0015 | D44: =C44+B44 -> 5.0075 | E44: 0.72 | L44: =E44*Prices!B$2 -> 79200 | M44: =F44*Prices!C$2 -> 0 | N44: =G44*Prices!D$2 -> 0 | O44: =H44*Prices!E$2 -> 0 | P44: =I44*2000+J44*10000+K44*1800 -> 0 | Q44: =D44*Prices!A$2 -> 89383.875 | R44: =L44+M44+N44+O44 -> 79200 | S44: =R44+Q44+P44 -> 168583.88 | T44: 43 | U44: Available | V44: A
A45: 44 | B45: 6.64 | C45: =B45*(25/100) -> 1.66 | D45: =C45+B45 -> 8.3 | E45: =0.52+0.3 -> 0.82 | L45: =E45*Prices!B$2 -> 90200 | M45: =F45*Prices!C$2 -> 0 | N45: =G45*Prices!D$2 -> 0 | O45: =H45*Prices!E$2 -> 0 | P45: =I45*2000+J45*10000+K45*1800 -> 0 | Q45: =D45*Prices!A$2 -> 148155 | R45: =L45+M45+N45+O45 -> 90200 | S45: =R45+Q45+P45 -> 238355 | T45: 44 | U45: Available | V45: A
A46: 45 | B46: 5.934 | C46: =B46*(25/100) -> 1.4835 | D46: =C46+B46 -> 7.4175 | E46: 1.13 | K46: 7.8 | L46: =E46*Prices!B$2 -> 124300 | M46: =F46*Prices!C$2 -> 0 | N46: =G46*Prices!D$2 -> 0 | O46: =H46*Prices!E$2 -> 0 | P46: =I46*2000+J46*10000+K46*1800 -> 14040 | Q46: =D46*Prices!A$2 -> 132402.38 | R46: =L46+M46+N46+O46 -> 124300 | S46: =R46+Q46+P46 -> 270742.38 | T46: 45 | U46: Sold
A47: 46 | B47: 10.44 | C47: =B47*(25/100) -> 2.61 | D47: =C47+B47 -> 13.05 | E47: 1.97 | K47: 6.3 | L47: =E47*Prices!B$2 -> 216700 | M47: =F47*Prices!C$2 -> 0 | N47: =G47*Prices!D$2 -> 0 | O47: =H47*Prices!E$2 -> 0 | P47: =I47*2000+J47*10000+K47*1800 -> 11340 | Q47: =D47*Prices!A$2 -> 232942.5 | R47: =L47+M47+N47+O47 -> 216700 | S47: =R47+Q47+P47 -> 460982.5 | T47: 46 | U47: Available | V47: A
A48: 47 | B48: 5.174 | C48: =B48*(25/100) -> 1.2935 | D48: =C48+B48 -> 6.4675 | E48: 0.77 | K48: 6.36 | L48: =E48*Prices!B$2 -> 84700 | M48: =F48*Prices!C$2 -> 0 | N48: =G48*Prices!D$2 -> 0 | O48: =H48*Prices!E$2 -> 0 | P48: =I48*2000+J48*10000+K48*1800 -> 11448 | Q48: =D48*Prices!A$2 -> 115444.88 | R48: =L48+M48+N48+O48 -> 84700 | S48: =R48+Q48+P48 -> 211592.88 | T48: 47 | U48: Sold
A49: 48 | B49: 4.932 | C49: =B49*(25/100) -> 1.233 | D49: =C49+B49 -> 6.165 | E49: 0.39 | L49: =E49*Prices!B$2 -> 42900 | M49: =F49*Prices!C$2 -> 0 | N49: =G49*Prices!D$2 -> 0 | O49: =H49*Prices!E$2 -> 0 | P49: =I49*2000+J49*10000+K49*1800 -> 0 | Q49: =D49*Prices!A$2 -> 110045.25 | R49: =L49+M49+N49+O49 -> 42900 | S49: =R49+Q49+P49 -> 152945.25 | T49: 48 | U49: Sold
A50: 49 | B50: 5.852 | C50: =B50*(25/100) -> 1.463 | D50: =C50+B50 -> 7.315 | E50: 1.67 | K50: 5.32 | L50: =E50*Prices!B$2 -> 183700 | M50: =F50*Prices!C$2 -> 0 | N50: =G50*Prices!D$2 -> 0 | O50: =H50*Prices!E$2 -> 0 | P50: =I50*2000+J50*10000+K50*1800 -> 9576 | Q50: =D50*Prices!A$2 -> 130572.75 | R50: =L50+M50+N50+O50 -> 183700 | S50: =R50+Q50+P50 -> 323848.75 | T50: 49 | U50: Sold
A51: 50 | B51: 4.95 | C51: =B51*(25/100) -> 1.2375 | D51: =C51+B51 -> 6.1875 | E51: 1.1 | L51: =E51*Prices!B$2 -> 121000 | M51: =F51*Prices!C$2 -> 0 | N51: =G51*Prices!D$2 -> 0 | O51: =H51*Prices!E$2 -> 0 | P51: =I51*2000+J51*10000+K51*1800 -> 0 | Q51: =D51*Prices!A$2 -> 110446.88 | R51: =L51+M51+N51+O51 -> 121000 | S51: =R51+Q51+P51 -> 231446.88 | T51: 50 | U51: Available | V51: A
A52: 51 | B52: 5.614 | C52: =B52*(25/100) -> 1.4035 | D52: =C52+B52 -> 7.0175 | E52: =0.23+0.18 -> 0.41 | K52: 2.52 | L52: =E52*Prices!B$2 -> 45100 | M52: =F52*Prices!C$2 -> 0 | N52: =G52*Prices!D$2 -> 0 | O52: =H52*Prices!E$2 -> 0 | P52: =I52*2000+J52*10000+K52*1800 -> 4536 | Q52: =D52*Prices!A$2 -> 125262.38 | R52: =L52+M52+N52+O52 -> 45100 | S52: =R52+Q52+P52 -> 174898.38 | T52: 51 | U52: Return
A53: 52 | B53: 3.318 | C53: =B53*(25/100) -> 0.8295 | D53: =C53+B53 -> 4.1475 | E53: 0.65 | L53: =E53*Prices!B$2 -> 71500 | M53: =F53*Prices!C$2 -> 0 | N53: =G53*Prices!D$2 -> 0 | O53: =H53*Prices!E$2 -> 0 | P53: =I53*2000+J53*10000+K53*1800 -> 0 | Q53: =D53*Prices!A$2 -> 74032.875 | R53: =L53+M53+N53+O53 -> 71500 | S53: =R53+Q53+P53 -> 145532.88 | T53: 52 | U53: Sold
A54: 53 | B54: 5.804 | C54: =B54*(25/100) -> 1.451 | D54: =C54+B54 -> 7.255 | E54: 0.86 | K54: 4.92 | L54: =E54*Prices!B$2 -> 94600 | M54: =F54*Prices!C$2 -> 0 | N54: =G54*Prices!D$2 -> 0 | O54: =H54*Prices!E$2 -> 0 | P54: =I54*2000+J54*10000+K54*1800 -> 8856 | Q54: =D54*Prices!A$2 -> 129501.75 | R54: =L54+M54+N54+O54 -> 94600 | S54: =R54+Q54+P54 -> 232957.75 | T54: 53 | U54: Return
A55: 54 | B55: 7.378 | C55: =B55*(25/100) -> 1.8445 | D55: =C55+B55 -> 9.2225 | E55: 0.92 | K55: 4.84 | L55: =E55*Prices!B$2 -> 101200 | M55: =F55*Prices!C$2 -> 0 | N55: =G55*Prices!D$2 -> 0 | O55: =H55*Prices!E$2 -> 0 | P55: =I55*2000+J55*10000+K55*1800 -> 8712 | Q55: =D55*Prices!A$2 -> 164621.62 | R55: =L55+M55+N55+O55 -> 101200 | S55: =R55+Q55+P55 -> 274533.62 | T55: 54 | U55: Return
A56: 55 | B56: 3.702 | C56: =B56*(25/100) -> 0.9255 | D56: =C56+B56 -> 4.6275 | E56: 0.54 | L56: =E56*Prices!B$2 -> 59400 | M56: =F56*Prices!C$2 -> 0 | N56: =G56*Prices!D$2 -> 0 | O56: =H56*Prices!E$2 -> 0 | P56: =I56*2000+J56*10000+K56*1800 -> 0 | Q56: =D56*Prices!A$2 -> 82600.875 | R56: =L56+M56+N56+O56 -> 59400 | S56: =R56+Q56+P56 -> 142000.88 | T56: 55 | U56: Available | V56: A
A57: 56 | B57: 2.8 | C57: =B57*(25/100) -> 0.7 | D57: =C57+B57 -> 3.5 | E57: 0.35 | L57: =E57*Prices!B$2 -> 38500 | M57: =F57*Prices!C$2 -> 0 | N57: =G57*Prices!D$2 -> 0 | O57: =H57*Prices!E$2 -> 0 | P57: =I57*2000+J57*10000+K57*1800 -> 0 | Q57: =D57*Prices!A$2 -> 62475 | R57: =L57+M57+N57+O57 -> 38500 | S57: =R57+Q57+P57 -> 100975 | T57: 56 | U57: Sold
A58: 57 | B58: 3.126 | C58: =B58*(25/100) -> 0.7815 | D58: =C58+B58 -> 3.9075 | E58: 0.42 | F58: 0.65 | L58: =E58*Prices!B$2 -> 46200 | M58: =F58*Prices!C$2 -> 104000 | N58: =G58*Prices!D$2 -> 0 | O58: =H58*Prices!E$2 -> 0 | P58: =I58*2000+J58*10000+K58*1800 -> 0 | Q58: =D58*Prices!A$2 -> 69748.875 | R58: =L58+M58+N58+O58 -> 150200 | S58: =R58+Q58+P58 -> 219948.88 | T58: 57 | U58: Available | V58: A
A59: 58 | B59: 8.74 | C59: =B59*(25/100) -> 2.185 | D59: =C59+B59 -> 10.925 | E59: 1.47 | K59: 15.98 | L59: =E59*Prices!B$2 -> 161700 | M59: =F59*Prices!C$2 -> 0 | N59: =G59*Prices!D$2 -> 0 | O59: =H59*Prices!E$2 -> 0 | P59: =I59*2000+J59*10000+K59*1800 -> 28764 | Q59: =D59*Prices!A$2 -> 195011.25 | R59: =L59+M59+N59+O59 -> 161700 | S59: =R59+Q59+P59 -> 385475.25 | T59: 58 | U59: Sold
A60: 59 | B60: 3.81 | C60: =B60*(25/100) -> 0.9525 | D60: =C60+B60 -> 4.7625 | E60: 0.9 | L60: =E60*Prices!B$2 -> 99000 | M60: =F60*Prices!C$2 -> 0 | N60: =G60*Prices!D$2 -> 0 | O60: =H60*Prices!E$2 -> 0 | P60: =I60*2000+J60*10000+K60*1800 -> 0 | Q60: =D60*Prices!A$2 -> 85010.625 | R60: =L60+M60+N60+O60 -> 99000 | S60: =R60+Q60+P60 -> 184010.62 | T60: 59 | U60: Sold
A61: 60 | B61: 3.524 | C61: =B61*(25/100) -> 0.881 | D61: =C61+B61 -> 4.405 | F61: 1.88 | L61: =E61*Prices!B$2 -> 0 | M61: =F61*Prices!C$2 -> 300800 | N61: =G61*Prices!D$2 -> 0 | O61: =H61*Prices!E$2 -> 0 | P61: =I61*2000+J61*10000+K61*1800 -> 0 | Q61: =D61*Prices!A$2 -> 78629.25 | R61: =L61+M61+N61+O61 -> 300800 | S61: =R61+Q61+P61 -> 379429.25 | T61: 60 | U61: Sold
A62: 61 | B62: 3.537 | C62: =B62*(25/100) -> 0.88425 | D62: =C62+B62 -> 4.42125 | E62: 0.49 | L62: =E62*Prices!B$2 -> 53900 | M62: =F62*Prices!C$2 -> 0 | N62: =G62*Prices!D$2 -> 0 | O62: =H62*Prices!E$2 -> 0 | P62: =I62*2000+J62*10000+K62*1800 -> 0 | Q62: =D62*Prices!A$2 -> 78919.312 | R62: =L62+M62+N62+O62 -> 53900 | S62: =R62+Q62+P62 -> 132819.31 | T62: 61 | U62: Return
A63: 62 | B63: 4.78 | C63: =B63*(25/100) -> 1.195 | D63: =C63+B63 -> 5.975 | E63: 1.18 | L63: =E63*Prices!B$2 -> 129800 | M63: =F63*Prices!C$2 -> 0 | N63: =G63*Prices!D$2 -> 0 | O63: =H63*Prices!E$2 -> 0 | P63: =I63*2000+J63*10000+K63*1800 -> 0 | Q63: =D63*Prices!A$2 -> 106653.75 | R63: =L63+M63+N63+O63 -> 129800 | S63: =R63+Q63+P63 -> 236453.75 | T63: 62 | U63: Available | V63: A
A64: 63 | B64: 1.588 | C64: =B64*(25/100) -> 0.397 | D64: =C64+B64 -> 1.985 | E64: 0.46 | L64: =E64*Prices!B$2 -> 50600 | M64: =F64*Prices!C$2 -> 0 | N64: =G64*Prices!D$2 -> 0 | O64: =H64*Prices!E$2 -> 0 | P64: =I64*2000+J64*10000+K64*1800 -> 0 | Q64: =D64*Prices!A$2 -> 35432.25 | R64: =L64+M64+N64+O64 -> 50600 | S64: =R64+Q64+P64 -> 86032.25 | T64: 63 | U64: Sold
A65: 64 | B65: 2.16 | C65: =B65*(25/100) -> 0.54 | D65: =C65+B65 -> 2.7 | E65: 0.35 | L65: =E65*Prices!B$2 -> 38500 | M65: =F65*Prices!C$2 -> 0 | N65: =G65*Prices!D$2 -> 0 | O65: =H65*Prices!E$2 -> 0 | P65: =I65*2000+J65*10000+K65*1800 -> 0 | Q65: =D65*Prices!A$2 -> 48195 | R65: =L65+M65+N65+O65 -> 38500 | S65: =R65+Q65+P65 -> 86695 | T65: 64 | U65: Sold
A66: 65 | B66: 1.518 | C66: =B66*(25/100) -> 0.3795 | D66: =C66+B66 -> 1.8975 | E66: 0.26 | L66: =E66*Prices!B$2 -> 28600 | M66: =F66*Prices!C$2 -> 0 | N66: =G66*Prices!D$2 -> 0 | O66: =H66*Prices!E$2 -> 0 | P66: =I66*2000+J66*10000+K66*1800 -> 0 | Q66: =D66*Prices!A$2 -> 33870.375 | R66: =L66+M66+N66+O66 -> 28600 | S66: =R66+Q66+P66 -> 62470.375 | T66: 65 | U66: Sold
A67: 66 | B67: 2.148 | C67: =B67*(25/100) -> 0.537 | D67: =C67+B67 -> 2.685 | E67: 0.36 | L67: =E67*Prices!B$2 -> 39600 | M67: =F67*Prices!C$2 -> 0 | N67: =G67*Prices!D$2 -> 0 | O67: =H67*Prices!E$2 -> 0 | P67: =I67*2000+J67*10000+K67*1800 -> 0 | Q67: =D67*Prices!A$2 -> 47927.25 | R67: =L67+M67+N67+O67 -> 39600 | S67: =R67+Q67+P67 -> 87527.25 | T67: 66 | U67: Sold
A68: 67 | B68: 1.482 | C68: =B68*(25/100) -> 0.3705 | D68: =C68+B68 -> 1.8525 | E68: 0.49 | L68: =E68*Prices!B$2 -> 53900 | M68: =F68*Prices!C$2 -> 0 | N68: =G68*Prices!D$2 -> 0 | O68: =H68*Prices!E$2 -> 0 | P68: =I68*2000+J68*10000+K68*1800 -> 0 | Q68: =D68*Prices!A$2 -> 33067.125 | R68: =L68+M68+N68+O68 -> 53900 | S68: =R68+Q68+P68 -> 86967.125 | T68: 67 | U68: Sold
A69: 68 | B69: 1.92 | C69: =B69*(25/100) -> 0.48 | D69: =C69+B69 -> 2.4 | E69: 0.3 | L69: =E69*Prices!B$2 -> 33000 | M69: =F69*Prices!C$2 -> 0 | N69: =G69*Prices!D$2 -> 0 | O69: =H69*Prices!E$2 -> 0 | P69: =I69*2000+J69*10000+K69*1800 -> 0 | Q69: =D69*Prices!A$2 -> 42840 | R69: =L69+M69+N69+O69 -> 33000 | S69: =R69+Q69+P69 -> 75840 | T69: 68 | U69: Available | V69: A
A70: 69 | B70: 1.394 | C70: =B70*(25/100) -> 0.3485 | D70: =C70+B70 -> 1.7425 | E70: 0.48 | L70: =E70*Prices!B$2 -> 52800 | M70: =F70*Prices!C$2 -> 0 | N70: =G70*Prices!D$2 -> 0 | O70: =H70*Prices!E$2 -> 0 | P70: =I70*2000+J70*10000+K70*1800 -> 0 | Q70: =D70*Prices!A$2 -> 31103.625 | R70: =L70+M70+N70+O70 -> 52800 | S70: =R70+Q70+P70 -> 83903.625 | T70: 69 | U70: Sold
A71: 70 | B71: 2.4 | C71: =B71*(25/100) -> 0.6 | D71: =C71+B71 -> 3 | E71: 0.21 | L71: =E71*Prices!B$2 -> 23100 | M71: =F71*Prices!C$2 -> 0 | N71: =G71*Prices!D$2 -> 0 | O71: =H71*Prices!E$2 -> 0 | P71: =I71*2000+J71*10000+K71*1800 -> 0 | Q71: =D71*Prices!A$2 -> 53550 | R71: =L71+M71+N71+O71 -> 23100 | S71: =R71+Q71+P71 -> 76650 | T71: 70 | U71: Available | V71: A
A72: 71 | B72: 2.77 | C72: =B72*(25/100) -> 0.6925 | D72: =C72+B72 -> 3.4625 | G72: 0.54 | L72: =E72*Prices!B$2 -> 0 | M72: =F72*Prices!C$2 -> 0 | N72: =G72*Prices!D$2 -> 105300 | O72: =H72*Prices!E$2 -> 0 | P72: =I72*2000+J72*10000+K72*1800 -> 0 | Q72: =D72*Prices!A$2 -> 61805.625 | R72: =L72+M72+N72+O72 -> 105300 | S72: =R72+Q72+P72 -> 167105.62 | T72: 71 | U72: Sold
A73: 72 | B73: 3.488 | C73: =B73*(25/100) -> 0.872 | D73: =C73+B73 -> 4.36 | F73: 0.81 | L73: =E73*Prices!B$2 -> 0 | M73: =F73*Prices!C$2 -> 129600 | N73: =G73*Prices!D$2 -> 0 | O73: =H73*Prices!E$2 -> 0 | P73: =I73*2000+J73*10000+K73*1800 -> 0 | Q73: =D73*Prices!A$2 -> 77826 | R73: =L73+M73+N73+O73 -> 129600 | S73: =R73+Q73+P73 -> 207426 | T73: 72 | U73: Available | V73: A
A74: 73 | B74: 2.344 | C74: =B74*(25/100) -> 0.586 | D74: =C74+B74 -> 2.93 | F74: 0.63 | L74: =E74*Prices!B$2 -> 0 | M74: =F74*Prices!C$2 -> 100800 | N74: =G74*Prices!D$2 -> 0 | O74: =H74*Prices!E$2 -> 0 | P74: =I74*2000+J74*10000+K74*1800 -> 0 | Q74: =D74*Prices!A$2 -> 52300.5 | R74: =L74+M74+N74+O74 -> 100800 | S74: =R74+Q74+P74 -> 153100.5 | T74: 73 | U74: Sold
A75: 74 | B75: 1.824 | C75: =B75*(25/100) -> 0.456 | D75: =C75+B75 -> 2.28 | E75: 0.28 | L75: =E75*Prices!B$2 -> 30800 | M75: =F75*Prices!C$2 -> 0 | N75: =G75*Prices!D$2 -> 0 | O75: =H75*Prices!E$2 -> 0 | P75: =I75*2000+J75*10000+K75*1800 -> 0 | Q75: =D75*Prices!A$2 -> 40698 | R75: =L75+M75+N75+O75 -> 30800 | S75: =R75+Q75+P75 -> 71498 | T75: 74 | U75: Sold
A76: 75 | B76: 2.398 | C76: =B76*(25/100) -> 0.5995 | D76: =C76+B76 -> 2.9975 | E76: 0.26 | L76: =E76*Prices!B$2 -> 28600 | M76: =F76*Prices!C$2 -> 0 | N76: =G76*Prices!D$2 -> 0 | O76: =H76*Prices!E$2 -> 0 | P76: =I76*2000+J76*10000+K76*1800 -> 0 | Q76: =D76*Prices!A$2 -> 53505.375 | R76: =L76+M76+N76+O76 -> 28600 | S76: =R76+Q76+P76 -> 82105.375 | T76: 75 | U76: Sold
A77: 76 | B77: 2.55 | C77: =B77*(25/100) -> 0.6375 | D77: =C77+B77 -> 3.1875 | E77: 0.31 | F77: 0.08 | L77: =E77*Prices!B$2 -> 34100 | M77: =F77*Prices!C$2 -> 12800 | N77: =G77*Prices!D$2 -> 0 | O77: =H77*Prices!E$2 -> 0 | P77: =I77*2000+J77*10000+K77*1800 -> 0 | Q77: =D77*Prices!A$2 -> 56896.875 | R77: =L77+M77+N77+O77 -> 46900 | S77: =R77+Q77+P77 -> 103796.88 | T77: 76 | U77: Sold
A78: 77 | B78: 3.5 | C78: =B78*(25/100) -> 0.875 | D78: =C78+B78 -> 4.375 | E78: 0.32 | L78: =E78*Prices!B$2 -> 35200 | M78: =F78*Prices!C$2 -> 0 | N78: =G78*Prices!D$2 -> 0 | O78: =H78*Prices!E$2 -> 0 | P78: =I78*2000+J78*10000+K78*1800 -> 0 | Q78: =D78*Prices!A$2 -> 78093.75 | R78: =L78+M78+N78+O78 -> 35200 | S78: =R78+Q78+P78 -> 113293.75 | T78: 77 | U78: Return
A79: 78 | B79: 3.13 | C79: =B79*(25/100) -> 0.7825 | D79: =C79+B79 -> 3.9125 | E79: 0.25 | L79: =E79*Prices!B$2 -> 27500 | M79: =F79*Prices!C$2 -> 0 | N79: =G79*Prices!D$2 -> 0 | O79: =H79*Prices!E$2 -> 0 | P79: =I79*2000+J79*10000+K79*1800 -> 0 | Q79: =D79*Prices!A$2 -> 69838.125 | R79: =L79+M79+N79+O79 -> 27500 | S79: =R79+Q79+P79 -> 97338.125 | T79: 78 | U79: Available | V79: A
A80: 79 | B80: 2.844 | C80: =B80*(25/100) -> 0.711 | D80: =C80+B80 -> 3.555 | E80: 0.18 | L80: =E80*Prices!B$2 -> 19800 | M80: =F80*Prices!C$2 -> 0 | N80: =G80*Prices!D$2 -> 0 | O80: =H80*Prices!E$2 -> 0 | P80: =I80*2000+J80*10000+K80*1800 -> 0 | Q80: =D80*Prices!A$2 -> 63456.75 | R80: =L80+M80+N80+O80 -> 19800 | S80: =R80+Q80+P80 -> 83256.75 | T80: 79 | U80: Sold
A81: 80 | B81: 2.84 | C81: =B81*(25/100) -> 0.71 | D81: =C81+B81 -> 3.55 | E81: 0.65 | L81: =E81*Prices!B$2 -> 71500 | M81: =F81*Prices!C$2 -> 0 | N81: =G81*Prices!D$2 -> 0 | O81: =H81*Prices!E$2 -> 0 | P81: =I81*2000+J81*10000+K81*1800 -> 0 | Q81: =D81*Prices!A$2 -> 63367.5 | R81: =L81+M81+N81+O81 -> 71500 | S81: =R81+Q81+P81 -> 134867.5 | T81: 80 | U81: Sold
A82: 81 | B82: 3.468 | C82: =B82*(25/100) -> 0.867 | D82: =C82+B82 -> 4.335 | E82: 0.46 | L82: =E82*Prices!B$2 -> 50600 | M82: =F82*Prices!C$2 -> 0 | N82: =G82*Prices!D$2 -> 0 | O82: =H82*Prices!E$2 -> 0 | P82: =I82*2000+J82*10000+K82*1800 -> 0 | Q82: =D82*Prices!A$2 -> 77379.75 | R82: =L82+M82+N82+O82 -> 50600 | S82: =R82+Q82+P82 -> 127979.75 | T82: 81 | U82: Sold
A83: 82 | B83: 2.456 | C83: =B83*(25/100) -> 0.614 | D83: =C83+B83 -> 3.07 | E83: 0.42 | L83: =E83*Prices!B$2 -> 46200 | M83: =F83*Prices!C$2 -> 0 | N83: =G83*Prices!D$2 -> 0 | O83: =H83*Prices!E$2 -> 0 | P83: =I83*2000+J83*10000+K83*1800 -> 0 | Q83: =D83*Prices!A$2 -> 54799.5 | R83: =L83+M83+N83+O83 -> 46200 | S83: =R83+Q83+P83 -> 100999.5 | T83: 82 | U83: Sold
A84: 83 | B84: 5.21 | C84: =B84*(25/100) -> 1.3025 | D84: =C84+B84 -> 6.5125 | E84: 0.53 | L84: =E84*Prices!B$2 -> 58300 | M84: =F84*Prices!C$2 -> 0 | N84: =G84*Prices!D$2 -> 0 | O84: =H84*Prices!E$2 -> 0 | P84: =I84*2000+J84*10000+K84*1800 -> 0 | Q84: =D84*Prices!A$2 -> 116248.12 | R84: =L84+M84+N84+O84 -> 58300 | S84: =R84+Q84+P84 -> 174548.12 | T84: 83 | U84: Return
A85: 84 | B85: 2.86 | C85: =B85*(25/100) -> 0.715 | D85: =C85+B85 -> 3.575 | E85: 0.4 | L85: =E85*Prices!B$2 -> 44000 | M85: =F85*Prices!C$2 -> 0 | N85: =G85*Prices!D$2 -> 0 | O85: =H85*Prices!E$2 -> 0 | P85: =I85*2000+J85*10000+K85*1800 -> 0 | Q85: =D85*Prices!A$2 -> 63813.75 | R85: =L85+M85+N85+O85 -> 44000 | S85: =R85+Q85+P85 -> 107813.75 | T85: 84 | U85: Sold
A86: 85 | B86: 3.038 | C86: =B86*(25/100) -> 0.7595 | D86: =C86+B86 -> 3.7975 | E86: 0.51 | L86: =E86*Prices!B$2 -> 56100 | M86: =F86*Prices!C$2 -> 0 | N86: =G86*Prices!D$2 -> 0 | O86: =H86*Prices!E$2 -> 0 | P86: =I86*2000+J86*10000+K86*1800 -> 0 | Q86: =D86*Prices!A$2 -> 67785.375 | R86: =L86+M86+N86+O86 -> 56100 | S86: =R86+Q86+P86 -> 123885.38 | T86: 85 | U86: Sold
A87: 86 | B87: 4.08 | C87: =B87*(25/100) -> 1.02 | D87: =C87+B87 -> 5.1 | E87: 0.95 | L87: =E87*Prices!B$2 -> 104500 | M87: =F87*Prices!C$2 -> 0 | N87: =G87*Prices!D$2 -> 0 | O87: =H87*Prices!E$2 -> 0 | P87: =I87*2000+J87*10000+K87*1800 -> 0 | Q87: =D87*Prices!A$2 -> 91035 | R87: =L87+M87+N87+O87 -> 104500 | S87: =R87+Q87+P87 -> 195535 | T87: 86 | U87: Sold
A88: 87 | B88: 3.122 | C88: =B88*(25/100) -> 0.7805 | D88: =C88+B88 -> 3.9025 | E88: 0.42 | F88: 0.07 | L88: =E88*Prices!B$2 -> 46200 | M88: =F88*Prices!C$2 -> 11200 | N88: =G88*Prices!D$2 -> 0 | O88: =H88*Prices!E$2 -> 0 | P88: =I88*2000+J88*10000+K88*1800 -> 0 | Q88: =D88*Prices!A$2 -> 69659.625 | R88: =L88+M88+N88+O88 -> 57400 | S88: =R88+Q88+P88 -> 127059.62 | T88: 87 | U88: Sold
A89: 88 | B89: 2.634 | C89: =B89*(25/100) -> 0.6585 | D89: =C89+B89 -> 3.2925 | E89: 0.23 | L89: =E89*Prices!B$2 -> 25300 | M89: =F89*Prices!C$2 -> 0 | N89: =G89*Prices!D$2 -> 0 | O89: =H89*Prices!E$2 -> 0 | P89: =I89*2000+J89*10000+K89*1800 -> 0 | Q89: =D89*Prices!A$2 -> 58771.125 | R89: =L89+M89+N89+O89 -> 25300 | S89: =R89+Q89+P89 -> 84071.125 | T89: 88 | U89: Sold
A90: 89 | B90: 2.408 | C90: =B90*(25/100) -> 0.602 | D90: =C90+B90 -> 3.01 | E90: 0.21 | L90: =E90*Prices!B$2 -> 23100 | M90: =F90*Prices!C$2 -> 0 | N90: =G90*Prices!D$2 -> 0 | O90: =H90*Prices!E$2 -> 0 | P90: =I90*2000+J90*10000+K90*1800 -> 0 | Q90: =D90*Prices!A$2 -> 53728.5 | R90: =L90+M90+N90+O90 -> 23100 | S90: =R90+Q90+P90 -> 76828.5 | T90: 89 | U90: Sold
A91: 90 | B91: 2.514 | C91: =B91*(25/100) -> 0.6285 | D91: =C91+B91 -> 3.1425 | E91: 0.28 | L91: =E91*Prices!B$2 -> 30800 | M91: =F91*Prices!C$2 -> 0 | N91: =G91*Prices!D$2 -> 0 | O91: =H91*Prices!E$2 -> 0 | P91: =I91*2000+J91*10000+K91*1800 -> 0 | Q91: =D91*Prices!A$2 -> 56093.625 | R91: =L91+M91+N91+O91 -> 30800 | S91: =R91+Q91+P91 -> 86893.625 | T91: 90 | U91: Sold
A92: 91 | B92: 2.734 | C92: =B92*(25/100) -> 0.6835 | D92: =C92+B92 -> 3.4175 | E92: 0.28 | L92: =E92*Prices!B$2 -> 30800 | M92: =F92*Prices!C$2 -> 0 | N92: =G92*Prices!D$2 -> 0 | O92: =H92*Prices!E$2 -> 0 | P92: =I92*2000+J92*10000+K92*1800 -> 0 | Q92: =D92*Prices!A$2 -> 61002.375 | R92: =L92+M92+N92+O92 -> 30800 | S92: =R92+Q92+P92 -> 91802.375 | T92: 91 | U92: Sold
A93: 92 | B93: 2.736 | C93: =B93*(25/100) -> 0.684 | D93: =C93+B93 -> 3.42 | E93: 0.42 | L93: =E93*Prices!B$2 -> 46200 | M93: =F93*Prices!C$2 -> 0 | N93: =G93*Prices!D$2 -> 0 | O93: =H93*Prices!E$2 -> 0 | P93: =I93*2000+J93*10000+K93*1800 -> 0 | Q93: =D93*Prices!A$2 -> 61047 | R93: =L93+M93+N93+O93 -> 46200 | S93: =R93+Q93+P93 -> 107247 | T93: 92 | U93: Sold
A94: 93 | B94: 2.914 | C94: =B94*(25/100) -> 0.7285 | D94: =C94+B94 -> 3.6425 | E94: 0.63 | L94: =E94*Prices!B$2 -> 69300 | M94: =F94*Prices!C$2 -> 0 | N94: =G94*Prices!D$2 -> 0 | O94: =H94*Prices!E$2 -> 0 | P94: =I94*2000+J94*10000+K94*1800 -> 0 | Q94: =D94*Prices!A$2 -> 65018.625 | R94: =L94+M94+N94+O94 -> 69300 | S94: =R94+Q94+P94 -> 134318.62 | T94: 93 | U94: Sold
A95: 94 | B95: 3.124 | C95: =B95*(25/100) -> 0.781 | D95: =C95+B95 -> 3.905 | E95: 0.73 | L95: =E95*Prices!B$2 -> 80300 | M95: =F95*Prices!C$2 -> 0 | N95: =G95*Prices!D$2 -> 0 | O95: =H95*Prices!E$2 -> 0 | P95: =I95*2000+J95*10000+K95*1800 -> 0 | Q95: =D95*Prices!A$2 -> 69704.25 | R95: =L95+M95+N95+O95 -> 80300 | S95: =R95+Q95+P95 -> 150004.25 | T95: 94 | U95: Sold
A96: 95 | B96: 1.568 | C96: =B96*(25/100) -> 0.392 | D96: =C96+B96 -> 1.96 | E96: 0.26 | L96: =E96*Prices!B$2 -> 28600 | M96: =F96*Prices!C$2 -> 0 | N96: =G96*Prices!D$2 -> 0 | O96: =H96*Prices!E$2 -> 0 | P96: =I96*2000+J96*10000+K96*1800 -> 0 | Q96: =D96*Prices!A$2 -> 34986 | R96: =L96+M96+N96+O96 -> 28600 | S96: =R96+Q96+P96 -> 63586 | T96: 95 | U96: Sold
A97: 96 | B97: 6.804 | C97: =B97*(25/100) -> 1.701 | D97: =C97+B97 -> 8.505 | E97: 1.48 | L97: =E97*Prices!B$2 -> 162800 | M97: =F97*Prices!C$2 -> 0 | N97: =G97*Prices!D$2 -> 0 | O97: =H97*Prices!E$2 -> 0 | P97: =I97*2000+J97*10000+K97*1800 -> 0 | Q97: =D97*Prices!A$2 -> 151814.25 | R97: =L97+M97+N97+O97 -> 162800 | S97: =R97+Q97+P97 -> 314614.25 | T97: 96 | U97: Sold
A98: 97 | B98: 5.308 | C98: =B98*(25/100) -> 1.327 | D98: =C98+B98 -> 6.635 | E98: 0.96 | L98: =E98*Prices!B$2 -> 105600 | M98: =F98*Prices!C$2 -> 0 | N98: =G98*Prices!D$2 -> 0 | O98: =H98*Prices!E$2 -> 0 | P98: =I98*2000+J98*10000+K98*1800 -> 0 | Q98: =D98*Prices!A$2 -> 118434.75 | R98: =L98+M98+N98+O98 -> 105600 | S98: =R98+Q98+P98 -> 224034.75 | T98: 97 | U98: Sold
A99: 98 | B99: 5.168 | C99: =B99*(25/100) -> 1.292 | D99: =C99+B99 -> 6.46 | E99: 1.21 | L99: =E99*Prices!B$2 -> 133100 | M99: =F99*Prices!C$2 -> 0 | N99: =G99*Prices!D$2 -> 0 | O99: =H99*Prices!E$2 -> 0 | P99: =I99*2000+J99*10000+K99*1800 -> 0 | Q99: =D99*Prices!A$2 -> 115311 | R99: =L99+M99+N99+O99 -> 133100 | S99: =R99+Q99+P99 -> 248411 | T99: 98 | U99: Sold
A100: 99 | B100: 3.242 | C100: =B100*(25/100) -> 0.8105 | D100: =C100+B100 -> 4.0525 | E100: 1.17 | F100: 0.07 | L100: =E100*Prices!B$2 -> 128700 | M100: =F100*Prices!C$2 -> 11200 | N100: =G100*Prices!D$2 -> 0 | O100: =H100*Prices!E$2 -> 0 | P100: =I100*2000+J100*10000+K100*1800 -> 0 | Q100: =D100*Prices!A$2 -> 72337.125 | R100: =L100+M100+N100+O100 -> 139900 | S100: =R100+Q100+P100 -> 212237.12 | T100: 99 | U100: Available | V100: A
...

Sheet Gents Ring
A1: Sn | B1: Net Weight | C1: Wstg + MC | D1: Gross Weight | E1: Dmd <0.06 | F1: Dmd < 0.12 | G1: Dmd <0.17 | H1: Dmd Big | I1: Ruby | J1: Emreld | K1: Muga | L1: Dmd Price | M1: Dmd Price | N1: Dmd Price | O1: Dmd Price | P1: Stn Price | Q1: Gold Price | R1: Ttl dmd Price | S1: Total Price | T1: Sn
A2: 1 | B2: 5.478 | C2: =B2*(25/100) -> 1.3695 | D2: =C2+B2 -> 6.8475 | E2: =0.63+0.08 -> 0.71 | L2: =E2*60000 -> 42600 | M2: =F2*70000 -> 0 | N2: =G2*90000 -> 0 | O2: =H2*200000 -> 0 | P2: =I2*2000+J2*4000+K2*650 -> 0 | Q2: =D2*6700 -> 45878.25 | R2: =L2+M2+N2+O2 -> 42600 | S2: =R2+Q2+P2 -> 88478.25 | T2: 1 | U2: Return
A3: 2 | B3: 6.094 | C3: =B3*(25/100) -> 1.5235 | D3: =C3+B3 -> 7.6175 | H3: 0.53 | L3: =E3*Prices!B$2 -> 0 | M3: =F3*Prices!C$2 -> 0 | N3: =G3*Prices!D$2 -> 0 | O3: =H3*Prices!E$2 -> 185500 | P3: =I3*2000+J3*4000+K3*650 -> 0 | Q3: =D3*Prices!A$2 -> 135972.38 | R3: =L3+M3+N3+O3 -> 185500 | S3: =R3+Q3+P3 -> 321472.38 | T3: 2 | U3: Available | V3: A
A4: 3 | B4: 6.94 | C4: =B4*(25/100) -> 1.735 | D4: =C4+B4 -> 8.675 | H4: 0.27 | L4: =E4*Prices!B$2 -> 0 | M4: =F4*Prices!C$2 -> 0 | N4: =G4*Prices!D$2 -> 0 | O4: =H4*200000 -> 54000 | P4: =I4*2000+J4*4000+K4*650 -> 0 | Q4: =D4*Prices!A$2 -> 154848.75 | R4: =L4+M4+N4+O4 -> 54000 | S4: =R4+Q4+P4 -> 208848.75 | T4: 3 | U4: Sold
A5: 4 | B5: 3.694 | C5: =B5*(25/100) -> 0.9235 | D5: =C5+B5 -> 4.6175 | E5: 0.46 | L5: =E5*Prices!B$2 -> 50600 | M5: =F5*Prices!C$2 -> 0 | N5: =G5*Prices!D$2 -> 0 | O5: =H5*Prices!E$2 -> 0 | P5: =I5*2000+J5*4000+K5*650 -> 0 | Q5: =D5*Prices!A$2 -> 82422.375 | R5: =L5+M5+N5+O5 -> 50600 | S5: =R5+Q5+P5 -> 133022.38 | T5: 4 | U5: Sold
A6: 5 | B6: 4.15 | C6: =B6*(25/100) -> 1.0375 | D6: =C6+B6 -> 5.1875 | F6: 0.7 | L6: =E6*Prices!B$2 -> 0 | M6: =F6*Prices!C$2 -> 112000 | N6: =G6*Prices!D$2 -> 0 | O6: =H6*Prices!E$2 -> 0 | P6: =I6*2000+J6*4000+K6*650 -> 0 | Q6: =D6*Prices!A$2 -> 92596.875 | R6: =L6+M6+N6+O6 -> 112000 | S6: =R6+Q6+P6 -> 204596.88 | T6: 5 | U6: Available | V6: A
A7: 6 | B7: 3.284 | C7: =B7*(25/100) -> 0.821 | D7: =C7+B7 -> 4.105 | E7: 0.58 | L7: =E7*Prices!B$2 -> 63800 | M7: =F7*Prices!C$2 -> 0 | N7: =G7*Prices!D$2 -> 0 | O7: =H7*Prices!E$2 -> 0 | P7: =I7*2000+J7*4000+K7*650 -> 0 | Q7: =D7*Prices!A$2 -> 73274.25 | R7: =L7+M7+N7+O7 -> 63800 | S7: =R7+Q7+P7 -> 137074.25 | T7: 6 | U7: Available | V7: A
A8: 7 | B8: 5.862 | C8: =B8*(25/100) -> 1.4655 | D8: =C8+B8 -> 7.3275 | H8: 0.39 | L8: =E8*Prices!B$2 -> 0 | M8: =F8*Prices!C$2 -> 0 | N8: =G8*Prices!D$2 -> 0 | O8: =H8*Prices!E$2 -> 136500 | P8: =I8*2000+J8*4000+K8*650 -> 0 | Q8: =D8*Prices!A$2 -> 130795.88 | R8: =L8+M8+N8+O8 -> 136500 | S8: =R8+Q8+P8 -> 267295.88 | T8: 7 | U8: Available | V8: A
A9: 8 | B9: 5.638 | C9: =B9*(25/100) -> 1.4095 | D9: =C9+B9 -> 7.0475 | H9: 0.56 | L9: =E9*Prices!B$2 -> 0 | M9: =F9*Prices!C$2 -> 0 | N9: =G9*Prices!D$2 -> 0 | O9: =H9*180000 -> 100800 | P9: =I9*2000+J9*4000+K9*650 -> 0 | Q9: =D9*Prices!A$2 -> 125797.88 | R9: =L9+M9+N9+O9 -> 100800 | S9: =R9+Q9+P9 -> 226597.88 | T9: 8 | U9: Available | V9: A
A10: 9 | B10: 4.424 | C10: =B10*(25/100) -> 1.106 | D10: =C10+B10 -> 5.53 | E10: 0.48 | L10: =E10*Prices!B$2 -> 52800 | M10: =F10*Prices!C$2 -> 0 | N10: =G10*Prices!D$2 -> 0 | O10: =H10*Prices!E$2 -> 0 | P10: =I10*2000+J10*4000+K10*650 -> 0 | Q10: =D10*Prices!A$2 -> 98710.5 | R10: =L10+M10+N10+O10 -> 52800 | S10: =R10+Q10+P10 -> 151510.5 | T10: 9 | U10: Sold
A11: 10 | B11: 3.408 | C11: =B11*(25/100) -> 0.852 | D11: =C11+B11 -> 4.26 | E11: 0.51 | L11: =E11*Prices!B$2 -> 56100 | M11: =F11*Prices!C$2 -> 0 | N11: =G11*Prices!D$2 -> 0 | O11: =H11*Prices!E$2 -> 0 | P11: =I11*2000+J11*4000+K11*650 -> 0 | Q11: =D11*Prices!A$2 -> 76041 | R11: =L11+M11+N11+O11 -> 56100 | S11: =R11+Q11+P11 -> 132141 | T11: 10 | U11: Sold
A12: 11 | B12: 3.066 | C12: =B12*(25/100) -> 0.7665 | D12: =C12+B12 -> 3.8325 | E12: 0.47 | L12: =E12*Prices!B$2 -> 51700 | M12: =F12*Prices!C$2 -> 0 | N12: =G12*Prices!D$2 -> 0 | O12: =H12*Prices!E$2 -> 0 | P12: =I12*2000+J12*4000+K12*650 -> 0 | Q12: =D12*Prices!A$2 -> 68410.125 | R12: =L12+M12+N12+O12 -> 51700 | S12: =R12+Q12+P12 -> 120110.12 | T12: 11 | U12: Available | V12: A
A13: 12 | B13: 4.904 | C13: =B13*(25/100) -> 1.226 | D13: =C13+B13 -> 6.13 | E13: 0.28 | L13: =E13*Prices!B$2 -> 30800 | M13: =F13*Prices!C$2 -> 0 | N13: =G13*Prices!D$2 -> 0 | O13: =H13*Prices!E$2 -> 0 | P13: =I13*2000+J13*4000+K13*650 -> 0 | Q13: =D13*Prices!A$2 -> 109420.5 | R13: =L13+M13+N13+O13 -> 30800 | S13: =R13+Q13+P13 -> 140220.5 | T13: 12 | U13: Sold
A14: 13 | B14: 5.922 | C14: =B14*(25/100) -> 1.4805 | D14: =C14+B14 -> 7.4025 | G14: 0.79 | L14: =E14*Prices!B$2 -> 0 | M14: =F14*Prices!C$2 -> 0 | N14: =G14*Prices!D$2 -> 154050 | O14: =H14*Prices!E$2 -> 0 | P14: =I14*2000+J14*4000+K14*650 -> 0 | Q14: =D14*Prices!A$2 -> 132134.62 | R14: =L14+M14+N14+O14 -> 154050 | S14: =R14+Q14+P14 -> 286184.62 | T14: 13 | U14: Sold
A15: 14 | B15: 6.126 | C15: =B15*(25/100) -> 1.5315 | D15: =C15+B15 -> 7.6575 | G15: 0.77 | L15: =E15*Prices!B$2 -> 0 | M15: =F15*Prices!C$2 -> 0 | N15: =G15*Prices!D$2 -> 150150 | O15: =H15*Prices!E$2 -> 0 | P15: =I15*2000+J15*4000+K15*650 -> 0 | Q15: =D15*Prices!A$2 -> 136686.38 | R15: =L15+M15+N15+O15 -> 150150 | S15: =R15+Q15+P15 -> 286836.38 | T15: 14 | U15: Sold
A16: 15 | B16: 6.334 | C16: =B16*(25/100) -> 1.5835 | D16: =C16+B16 -> 7.9175 | E16: 0.48 | L16: =E16*Prices!B$2 -> 52800 | M16: =F16*Prices!C$2 -> 0 | N16: =G16*Prices!D$2 -> 0 | O16: =H16*Prices!E$2 -> 0 | P16: =I16*2000+J16*4000+K16*650 -> 0 | Q16: =D16*Prices!A$2 -> 141327.38 | R16: =L16+M16+N16+O16 -> 52800 | S16: =R16+Q16+P16 -> 194127.38 | T16: 15 | U16: Sold
A17: 16 | B17: 6.466 | C17: =B17*(25/100) -> 1.6165 | D17: =C17+B17 -> 8.0825 | E17: 0.47 | L17: =E17*Prices!B$2 -> 51700 | M17: =F17*Prices!C$2 -> 0 | N17: =G17*Prices!D$2 -> 0 | O17: =H17*Prices!E$2 -> 0 | P17: =I17*2000+J17*4000+K17*650 -> 0 | Q17: =D17*Prices!A$2 -> 144272.62 | R17: =L17+M17+N17+O17 -> 51700 | S17: =R17+Q17+P17 -> 195972.62 | T17: 16 | U17: Sold
A18: 17 | B18: 4.352 | C18: =B18*(25/100) -> 1.088 | D18: =C18+B18 -> 5.44 | E18: 0.34 | L18: =E18*Prices!B$2 -> 37400 | M18: =F18*Prices!C$2 -> 0 | N18: =G18*Prices!D$2 -> 0 | O18: =H18*Prices!E$2 -> 0 | P18: =I18*2000+J18*4000+K18*650 -> 0 | Q18: =D18*Prices!A$2 -> 97104 | R18: =L18+M18+N18+O18 -> 37400 | S18: =R18+Q18+P18 -> 134504 | T18: 17 | U18: Available | V18: A
A19: 18 | B19: 6.66 | C19: =B19*(25/100) -> 1.665 | D19: =C19+B19 -> 8.325 | F19: 0.68 | L19: =E19*Prices!B$2 -> 0 | M19: =F19*Prices!C$2 -> 108800 | N19: =G19*Prices!D$2 -> 0 | O19: =H19*Prices!E$2 -> 0 | P19: =I19*2000+J19*4000+K19*650 -> 0 | Q19: =D19*Prices!A$2 -> 148601.25 | R19: =L19+M19+N19+O19 -> 108800 | S19: =R19+Q19+P19 -> 257401.25 | T19: 18 | U19: Available | V19: A
A20: 19 | B20: 6.624 | C20: =B20*(25/100) -> 1.656 | D20: =C20+B20 -> 8.28 | E20: 0.48 | L20: =E20*Prices!B$2 -> 52800 | M20: =F20*Prices!C$2 -> 0 | N20: =G20*Prices!D$2 -> 0 | O20: =H20*Prices!E$2 -> 0 | P20: =I20*2000+J20*4000+K20*650 -> 0 | Q20: =D20*Prices!A$2 -> 147798 | R20: =L20+M20+N20+O20 -> 52800 | S20: =R20+Q20+P20 -> 200598 | T20: 19 | U20: Sold
A21: 20 | B21: 5.492 | C21: =B21*(25/100) -> 1.373 | D21: =C21+B21 -> 6.865 | E21: 0.39 | L21: =E21*Prices!B$2 -> 42900 | M21: =F21*Prices!C$2 -> 0 | N21: =G21*Prices!D$2 -> 0 | O21: =H21*Prices!E$2 -> 0 | P21: =I21*2000+J21*4000+K21*650 -> 0 | Q21: =D21*Prices!A$2 -> 122540.25 | R21: =L21+M21+N21+O21 -> 42900 | S21: =R21+Q21+P21 -> 165440.25 | T21: 20 | U21: Sold
A22: 21 | B22: 5.552 | C22: =B22*(25/100) -> 1.388 | D22: =C22+B22 -> 6.94 | E22: 0.39 | L22: =E22*Prices!B$2 -> 42900 | M22: =F22*Prices!C$2 -> 0 | N22: =G22*Prices!D$2 -> 0 | O22: =H22*Prices!E$2 -> 0 | P22: =I22*2000+J22*4000+K22*650 -> 0 | Q22: =D22*Prices!A$2 -> 123879 | R22: =L22+M22+N22+O22 -> 42900 | S22: =R22+Q22+P22 -> 166779 | T22: 21 | U22: Sold
A23: 22 | B23: 6.114 | C23: =B23*(25/100) -> 1.5285 | D23: =C23+B23 -> 7.6425 | G23: 0.58 | L23: =E23*Prices!B$2 -> 0 | M23: =F23*Prices!C$2 -> 0 | N23: =G23*Prices!D$2 -> 113100 | O23: =H23*Prices!E$2 -> 0 | P23: =I23*2000+J23*4000+K23*650 -> 0 | Q23: =D23*Prices!A$2 -> 136418.62 | R23: =L23+M23+N23+O23 -> 113100 | S23: =R23+Q23+P23 -> 249518.62 | T23: 22 | U23: Available | V23: A
A24: 23 | B24: 5.052 | C24: =B24*(25/100) -> 1.263 | D24: =C24+B24 -> 6.315 | H24: 0.69 | L24: =E24*Prices!B$2 -> 0 | M24: =F24*Prices!C$2 -> 0 | N24: =G24*Prices!D$2 -> 0 | O24: =H24*180000 -> 124200 | P24: =I24*2000+J24*4000+K24*650 -> 0 | Q24: =D24*Prices!A$2 -> 112722.75 | R24: =L24+M24+N24+O24 -> 124200 | S24: =R24+Q24+P24 -> 236922.75 | T24: 23 | U24: Available | V24: A
A25: 24 | B25: 4.84 | C25: =B25*(25/100) -> 1.21 | D25: =C25+B25 -> 6.05 | G25: 0.85 | L25: =E25*Prices!B$2 -> 0 | M25: =F25*Prices!C$2 -> 0 | N25: =G25*Prices!D$2 -> 165750 | O25: =H25*Prices!E$2 -> 0 | P25: =I25*2000+J25*4000+K25*650 -> 0 | Q25: =D25*Prices!A$2 -> 107992.5 | R25: =L25+M25+N25+O25 -> 165750 | S25: =R25+Q25+P25 -> 273742.5 | T25: 24 | U25: Available | V25: A
A26: 25 | B26: 5.75 | C26: =B26*(25/100) -> 1.4375 | D26: =C26+B26 -> 7.1875 | E26: 0.69 | L26: =E26*Prices!B$2 -> 75900 | M26: =F26*Prices!C$2 -> 0 | N26: =G26*Prices!D$2 -> 0 | O26: =H26*Prices!E$2 -> 0 | P26: =I26*2000+J26*4000+K26*650 -> 0 | Q26: =D26*Prices!A$2 -> 128296.88 | R26: =L26+M26+N26+O26 -> 75900 | S26: =R26+Q26+P26 -> 204196.88 | T26: 25 | U26: Sold
A27: 26 | B27: 7.27 | C27: =B27*(25/100) -> 1.8175 | D27: =C27+B27 -> 9.0875 | E27: 0.2 | L27: =E27*Prices!B$2 -> 22000 | M27: =F27*Prices!C$2 -> 0 | N27: =G27*Prices!D$2 -> 0 | O27: =H27*Prices!E$2 -> 0 | P27: =I27*2000+J27*4000+K27*650 -> 0 | Q27: =D27*(Prices!A$2+2200) -> 182204.38 | R27: =L27+M27+N27+O27 -> 22000 | S27: =R27+Q27+P27 -> 204204.38 | T27: 26 | U27: Available | V27: A
A28: 27 | B28: 6.94 | C28: =B28*(25/100) -> 1.735 | D28: =C28+B28 -> 8.675 | H28: 0.54 | L28: =E28*Prices!B$2 -> 0 | M28: =F28*Prices!C$2 -> 0 | N28: =G28*Prices!D$2 -> 0 | O28: =H28*Prices!E$2 -> 189000 | P28: =I28*2000+J28*4000+K28*650 -> 0 | Q28: =D28*Prices!A$2 -> 154848.75 | R28: =L28+M28+N28+O28 -> 189000 | S28: =R28+Q28+P28 -> 343848.75 | T28: 27 | U28: Available | V28: A
A29: 28 | B29: 6.1 | C29: =B29*(25/100) -> 1.525 | D29: =C29+B29 -> 7.625 | E29: 0.3 | L29: =E29*Prices!B$2 -> 33000 | M29: =F29*Prices!C$2 -> 0 | N29: =G29*Prices!D$2 -> 0 | O29: =H29*Prices!E$2 -> 0 | P29: =I29*2000+J29*4000+K29*650 -> 0 | Q29: =D29*Prices!A$2 -> 136106.25 | R29: =L29+M29+N29+O29 -> 33000 | S29: =R29+Q29+P29 -> 169106.25 | T29: 28 | U29: Sold
A30: 29 | B30: 4.556 | C30: =B30*(25/100) -> 1.139 | D30: =C30+B30 -> 5.695 | E30: 0.58 | L30: =E30*Prices!B$2 -> 63800 | M30: =F30*Prices!C$2 -> 0 | N30: =G30*Prices!D$2 -> 0 | O30: =H30*Prices!E$2 -> 0 | P30: =I30*2000+J30*4000+K30*650 -> 0 | Q30: =D30*Prices!A$2 -> 101655.75 | R30: =L30+M30+N30+O30 -> 63800 | S30: =R30+Q30+P30 -> 165455.75 | T30: 29 | U30: Sold
A31: 30 | B31: 4.218 | C31: =B31*(25/100) -> 1.0545 | D31: =C31+B31 -> 5.2725 | E31: 0.42 | L31: =E31*Prices!B$2 -> 46200 | M31: =F31*Prices!C$2 -> 0 | N31: =G31*Prices!D$2 -> 0 | O31: =H31*Prices!E$2 -> 0 | P31: =I31*2000+J31*4000+K31*650 -> 0 | Q31: =D31*Prices!A$2 -> 94114.125 | R31: =L31+M31+N31+O31 -> 46200 | S31: =R31+Q31+P31 -> 140314.12 | T31: 30 | U31: Available | V31: A
A32: 31 | B32: 4.428 | C32: =B32*(25/100) -> 1.107 | D32: =C32+B32 -> 5.535 | E32: 0.57 | L32: =E32*Prices!B$2 -> 62700 | M32: =F32*Prices!C$2 -> 0 | N32: =G32*Prices!D$2 -> 0 | O32: =H32*Prices!E$2 -> 0 | P32: =I32*2000+J32*4000+K32*650 -> 0 | Q32: =D32*Prices!A$2 -> 98799.75 | R32: =L32+M32+N32+O32 -> 62700 | S32: =R32+Q32+P32 -> 161499.75 | T32: 31 | U32: Sold
A33: 32 | B33: 4.928 | C33: =B33*(25/100) -> 1.232 | D33: =C33+B33 -> 6.16 | E33: 0.67 | L33: =E33*Prices!B$2 -> 73700 | M33: =F33*Prices!C$2 -> 0 | N33: =G33*Prices!D$2 -> 0 | O33: =H33*Prices!E$2 -> 0 | P33: =I33*2000+J33*4000+K33*650 -> 0 | Q33: =D33*Prices!A$2 -> 109956 | R33: =L33+M33+N33+O33 -> 73700 | S33: =R33+Q33+P33 -> 183656 | T33: 32 | U33: Sold
A34: 33 | B34: 4.62 | C34: =B34*(25/100) -> 1.155 | D34: =C34+B34 -> 5.775 | E34: 0.56 | L34: =E34*Prices!B$2 -> 61600 | M34: =F34*Prices!C$2 -> 0 | N34: =G34*Prices!D$2 -> 0 | O34: =H34*Prices!E$2 -> 0 | P34: =I34*2000+J34*4000+K34*650 -> 0 | Q34: =D34*Prices!A$2 -> 103083.75 | R34: =L34+M34+N34+O34 -> 61600 | S34: =R34+Q34+P34 -> 164683.75 | T34: 33 | U34: Available | V34: A
A35: 34 | B35: 5.448 | C35: =B35*(25/100) -> 1.362 | D35: =C35+B35 -> 6.81 | E35: 0.57 | L35: =E35*Prices!B$2 -> 62700 | M35: =F35*Prices!C$2 -> 0 | N35: =G35*Prices!D$2 -> 0 | O35: =H35*Prices!E$2 -> 0 | P35: =I35*2000+J35*4000+K35*650 -> 0 | Q35: =D35*Prices!A$2 -> 121558.5 | R35: =L35+M35+N35+O35 -> 62700 | S35: =R35+Q35+P35 -> 184258.5 | T35: 34 | U35: Sold
A36: 35 | B36: 5.298 | C36: =B36*(25/100) -> 1.3245 | D36: =C36+B36 -> 6.6225 | E36: 0.72 | L36: =E36*Prices!B$2 -> 79200 | M36: =F36*Prices!C$2 -> 0 | N36: =G36*Prices!D$2 -> 0 | O36: =H36*Prices!E$2 -> 0 | P36: =I36*2000+J36*4000+K36*650 -> 0 | Q36: =D36*Prices!A$2 -> 118211.62 | R36: =L36+M36+N36+O36 -> 79200 | S36: =R36+Q36+P36 -> 197411.62 | T36: 35 | U36: Available | V36: A
A37: 36 | B37: 5.208 | C37: =B37*(25/100) -> 1.302 | D37: =C37+B37 -> 6.51 | E37: 0.57 | L37: =E37*Prices!B$2 -> 62700 | M37: =F37*Prices!C$2 -> 0 | N37: =G37*Prices!D$2 -> 0 | O37: =H37*Prices!E$2 -> 0 | P37: =I37*2000+J37*4000+K37*650 -> 0 | Q37: =D37*Prices!A$2 -> 116203.5 | R37: =L37+M37+N37+O37 -> 62700 | S37: =R37+Q37+P37 -> 178903.5 | T37: 36 | U37: Sold
A38: 37 | B38: 4.738 | C38: =B38*(25/100) -> 1.1845 | D38: =C38+B38 -> 5.9225 | E38: 0.52 | L38: =E38*Prices!B$2 -> 57200 | M38: =F38*Prices!C$2 -> 0 | N38: =G38*Prices!D$2 -> 0 | O38: =H38*Prices!E$2 -> 0 | P38: =I38*2000+J38*4000+K38*650 -> 0 | Q38: =D38*Prices!A$2 -> 105716.62 | R38: =L38+M38+N38+O38 -> 57200 | S38: =R38+Q38+P38 -> 162916.62 | T38: 37 | U38: Sold
A39: 38 | B39: 5.168 | C39: =B39*(25/100) -> 1.292 | D39: =C39+B39 -> 6.46 | E39: 0.62 | L39: =E39*Prices!B$2 -> 68200 | M39: =F39*Prices!C$2 -> 0 | N39: =G39*Prices!D$2 -> 0 | O39: =H39*Prices!E$2 -> 0 | P39: =I39*2000+J39*4000+K39*650 -> 0 | Q39: =D39*Prices!A$2 -> 115311 | R39: =L39+M39+N39+O39 -> 68200 | S39: =R39+Q39+P39 -> 183511 | T39: 38 | U39: Sold
A40: 39 | B40: 3.692 | C40: =B40*(25/100) -> 0.923 | D40: =C40+B40 -> 4.615 | G40: 0.69 | L40: =E40*Prices!B$2 -> 0 | M40: =F40*Prices!C$2 -> 0 | N40: =G40*Prices!D$2 -> 134550 | O40: =H40*Prices!E$2 -> 0 | P40: =I40*2000+J40*4000+K40*650 -> 0 | Q40: =D40*Prices!A$2 -> 82377.75 | R40: =L40+M40+N40+O40 -> 134550 | S40: =R40+Q40+P40 -> 216927.75 | T40: 39 | U40: Available | V40: A
A41: 40 | B41: 3.98 | C41: =B41*(25/100) -> 0.995 | D41: =C41+B41 -> 4.975 | G41: 0.85 | L41: =E41*Prices!B$2 -> 0 | M41: =F41*Prices!C$2 -> 0 | N41: =G41*Prices!D$2 -> 165750 | O41: =H41*Prices!E$2 -> 0 | P41: =I41*2000+J41*4000+K41*650 -> 0 | Q41: =D41*Prices!A$2 -> 88803.75 | R41: =L41+M41+N41+O41 -> 165750 | S41: =R41+Q41+P41 -> 254553.75 | T41: 40 | U41: Sold
A42: 41 | B42: 7.936 | C42: =B42*(25/100) -> 1.984 | D42: =C42+B42 -> 9.92 | F42: 0.52 | L42: =E42*Prices!B$2 -> 0 | M42: =F42*Prices!C$2 -> 83200 | N42: =G42*Prices!D$2 -> 0 | O42: =H42*Prices!E$2 -> 0 | P42: =I42*2000+J42*4000+K42*650 -> 0 | Q42: =D42*Prices!A$2 -> 177072 | R42: =L42+M42+N42+O42 -> 83200 | S42: =R42+Q42+P42 -> 260272 | T42: 41 | U42: Sold
A43: 42 | B43: 8.105 | C43: =B43*(25/100) -> 2.02625 | D43: =C43+B43 -> 10.13125 | E43: 0.73 | L43: =E43*Prices!B$2 -> 80300 | M43: =F43*Prices!C$2 -> 0 | N43: =G43*Prices!D$2 -> 0 | O43: =H43*Prices!E$2 -> 0 | P43: =I43*2000+J43*4000+K43*650 -> 0 | Q43: =D43*Prices!A$2 -> 180842.81 | R43: =L43+M43+N43+O43 -> 80300 | S43: =R43+Q43+P43 -> 261142.81 | T43: 42 | U43: Sold
A44: 43 | B44: 5.866 | C44: =B44*(25/100) -> 1.4665 | D44: =C44+B44 -> 7.3325 | E44: 0.57 | L44: =E44*Prices!B$2 -> 62700 | M44: =F44*Prices!C$2 -> 0 | N44: =G44*Prices!D$2 -> 0 | O44: =H44*Prices!E$2 -> 0 | P44: =I44*2000+J44*4000+K44*650 -> 0 | Q44: =D44*Prices!A$2 -> 130885.12 | R44: =L44+M44+N44+O44 -> 62700 | S44: =R44+Q44+P44 -> 193585.12 | T44: 43 | U44: Sold
A45: 44 | B45: 4.262 | C45: =B45*(25/100) -> 1.0655 | D45: =C45+B45 -> 5.3275 | H45: 0.89 | L45: =E45*Prices!B$2 -> 0 | M45: =F45*Prices!C$2 -> 0 | N45: =G45*Prices!D$2 -> 0 | O45: =H45*180000 -> 160200 | P45: =I45*2000+J45*4000+K45*650 -> 0 | Q45: =D45*Prices!A$2 -> 95095.875 | R45: =L45+M45+N45+O45 -> 160200 | S45: =R45+Q45+P45 -> 255295.88 | T45: 44 | U45: Sold
A46: 45 | B46: 4.242 | C46: =B46*(25/100) -> 1.0605 | D46: =C46+B46 -> 5.3025 | E46: 0.29 | L46: =E46*Prices!B$2 -> 31900 | M46: =F46*Prices!C$2 -> 0 | N46: =G46*Prices!D$2 -> 0 | O46: =H46*180000 -> 0 | P46: =I46*2000+J46*4000+K46*650 -> 0 | Q46: =D46*Prices!A$2 -> 94649.625 | R46: =L46+M46+N46+O46 -> 31900 | S46: =R46+Q46+P46 -> 126549.62 | T46: 45 | U46: Sold
A47: 46 | B47: 5.865 | C47: =B47*(25/100) -> 1.46625 | D47: =C47+B47 -> 7.33125 | F47: 0.79 | L47: =E47*Prices!B$2 -> 0 | M47: =F47*Prices!C$2 -> 126400 | N47: =G47*Prices!D$2 -> 0 | O47: =H47*180000 -> 0 | P47: =I47*2000+J47*4000+K47*650 -> 0 | Q47: =D47*Prices!A$2 -> 130862.81 | R47: =L47+M47+N47+O47 -> 126400 | S47: =R47+Q47+P47 -> 257262.81 | T47: 46 | U47: Available | V47: A
A48: 47 | B48: 4.86 | C48: =B48*(25/100) -> 1.215 | D48: =C48+B48 -> 6.075 | E48: 0.75 | L48: =E48*Prices!B$2 -> 82500 | M48: =F48*Prices!C$2 -> 0 | N48: =G48*Prices!D$2 -> 0 | O48: =H48*180000 -> 0 | P48: =I48*2000+J48*4000+K48*650 -> 0 | Q48: =D48*Prices!A$2 -> 108438.75 | R48: =L48+M48+N48+O48 -> 82500 | S48: =R48+Q48+P48 -> 190938.75 | T48: 47 | U48: Available | V48: A
A49: 48 | B49: 7.45 | C49: =B49*(25/100) -> 1.8625 | D49: =C49+B49 -> 9.3125 | E49: 0.75 | L49: =E49*Prices!B$2 -> 82500 | M49: =F49*Prices!C$2 -> 0 | N49: =G49*Prices!D$2 -> 0 | O49: =H49*180000 -> 0 | P49: =I49*2000+J49*4000+K49*650 -> 0 | Q49: =D49*Prices!A$2 -> 166228.12 | R49: =L49+M49+N49+O49 -> 82500 | S49: =R49+Q49+P49 -> 248728.12 | T49: 48 | U49: Available | V49: A
A50: 49 | B50: 5.61 | C50: =B50*(25/100) -> 1.4025 | D50: =C50+B50 -> 7.0125 | E50: 0.5 | L50: =E50*Prices!B$2 -> 55000 | M50: =F50*Prices!C$2 -> 0 | N50: =G50*Prices!D$2 -> 0 | O50: =H50*180000 -> 0 | P50: =I50*2000+J50*4000+K50*650 -> 0 | Q50: =D50*Prices!A$2 -> 125173.12 | R50: =L50+M50+N50+O50 -> 55000 | S50: =R50+Q50+P50 -> 180173.12 | T50: 49 | U50: Available | V50: A
A51: 50 | B51: 3.624 | C51: =B51*(25/100) -> 0.906 | D51: =C51+B51 -> 4.53 | E51: 0.83 | L51: =E51*Prices!B$2 -> 91300 | M51: =F51*Prices!C$2 -> 0 | N51: =G51*Prices!D$2 -> 0 | O51: =H51*180000 -> 0 | P51: =I51*2000+J51*4000+K51*650 -> 0 | Q51: =D51*Prices!A$2 -> 80860.5 | R51: =L51+M51+N51+O51 -> 91300 | S51: =R51+Q51+P51 -> 172160.5 | T51: 50 | U51: Sold
A52: 51 | B52: 7.23 | C52: =B52*(25/100) -> 1.8075 | D52: =C52+B52 -> 9.0375 | E52: 0.23 | L52: =E52*Prices!B$2 -> 25300 | M52: =F52*Prices!C$2 -> 0 | N52: =G52*Prices!D$2 -> 0 | O52: =H52*180000 -> 0 | P52: =I52*2000+J52*4000+K52*650 -> 0 | Q52: =D52*(Prices!A$2+2200) -> 181201.88 | R52: =L52+M52+N52+O52 -> 25300 | S52: =R52+Q52+P52 -> 206501.88 | T52: 51 | U52: Available | V52: A
A53: 52 | B53: 2.33 | C53: =B53*(25/100) -> 0.5825 | D53: =C53+B53 -> 2.9125 | E53: 0.45 | L53: =E53*Prices!B$2 -> 49500 | M53: =F53*Prices!C$2 -> 0 | N53: =G53*Prices!D$2 -> 0 | O53: =H53*180000 -> 0 | P53: =I53*2000+J53*4000+K53*650 -> 0 | Q53: =D53*Prices!A$2 -> 51988.125 | R53: =L53+M53+N53+O53 -> 49500 | S53: =R53+Q53+P53 -> 101488.12 | T53: 52 | U53: Sold
A54: 53 | B54: 4.68 | C54: =B54*(25/100) -> 1.17 | D54: =C54+B54 -> 5.85 | E54: 0.3 | L54: =E54*Prices!B$2 -> 33000 | M54: =F54*Prices!C$2 -> 0 | N54: =G54*Prices!D$2 -> 0 | O54: =H54*180000 -> 0 | P54: =I54*2000+J54*4000+K54*650 -> 0 | Q54: =D54*Prices!A$2 -> 104422.5 | R54: =L54+M54+N54+O54 -> 33000 | S54: =R54+Q54+P54 -> 137422.5 | T54: 53 | U54: Available | V54: A
A55: 54 | B55: 3.69 | C55: =B55*(25/100) -> 0.9225 | D55: =C55+B55 -> 4.6125 | E55: 0.35 | L55: =E55*Prices!B$2 -> 38500 | M55: =F55*Prices!C$2 -> 0 | N55: =G55*Prices!D$2 -> 0 | O55: =H55*180000 -> 0 | P55: =I55*2000+J55*4000+K55*650 -> 0 | Q55: =D55*Prices!A$2 -> 82333.125 | R55: =L55+M55+N55+O55 -> 38500 | S55: =R55+Q55+P55 -> 120833.12 | T55: 54 | U55: Available | V55: A
A56: 55 | B56: 4.65 | C56: =B56*(25/100) -> 1.1625 | D56: =C56+B56 -> 5.8125 | E56: 0.4 | L56: =E56*Prices!B$2 -> 44000 | M56: =F56*Prices!C$2 -> 0 | N56: =G56*Prices!D$2 -> 0 | O56: =H56*180000 -> 0 | P56: =I56*2000+J56*4000+K56*650 -> 0 | Q56: =D56*Prices!A$2 -> 103753.12 | R56: =L56+M56+N56+O56 -> 44000 | S56: =R56+Q56+P56 -> 147753.12 | T56: 55 | U56: Available | V56: A
A57: 56 | B57: 3.936 | C57: =B57*(25/100) -> 0.984 | D57: =C57+B57 -> 4.92 | E57: 0.47 | L57: =E57*Prices!B$2 -> 51700 | M57: =F57*Prices!C$2 -> 0 | N57: =G57*Prices!D$2 -> 0 | O57: =H57*180000 -> 0 | P57: =I57*2000+J57*4000+K57*650 -> 0 | Q57: =D57*Prices!A$2 -> 87822 | R57: =L57+M57+N57+O57 -> 51700 | S57: =R57+Q57+P57 -> 139522 | T57: 56 | U57: Available | V57: A
A58: 57 | B58: 6.254 | C58: =B58*(25/100) -> 1.5635 | D58: =C58+B58 -> 7.8175 | H58: 0.38 | L58: =E58*Prices!B$2 -> 0 | M58: =F58*Prices!C$2 -> 0 | N58: =G58*Prices!D$2 -> 0 | O58: =H58*270000 -> 102600 | P58: =I58*2000+J58*4000+K58*650 -> 0 | Q58: =D58*Prices!A$2 -> 139542.38 | R58: =L58+M58+N58+O58 -> 102600 | S58: =R58+Q58+P58 -> 242142.38 | T58: 57 | U58: Sold
A59: 58 | B59: 9.348 | C59: =B59*(25/100) -> 2.337 | D59: =C59+B59 -> 11.685 | E59: 1.16 | L59: =E59*Prices!B$2 -> 127600 | M59: =F59*Prices!C$2 -> 0 | N59: =G59*Prices!D$2 -> 0 | O59: =H59*270000 -> 0 | P59: =I59*2000+J59*4000+K59*650 -> 0 | Q59: =D59*(Prices!A$2+2200) -> 234284.25 | R59: =L59+M59+N59+O59 -> 127600 | S59: =R59+Q59+P59 -> 361884.25 | T59: 58 | U59: Available | V59: A
A60: 59 | B60: 4.258 | C60: =B60*(25/100) -> 1.0645 | D60: =C60+B60 -> 5.3225 | E60: 0.41 | L60: =E60*Prices!B$2 -> 45100 | M60: =F60*Prices!C$2 -> 0 | N60: =G60*Prices!D$2 -> 0 | O60: =H60*270000 -> 0 | P60: =I60*2000+J60*4000+K60*650 -> 0 | Q60: =D60*Prices!A$2 -> 95006.625 | R60: =L60+M60+N60+O60 -> 45100 | S60: =R60+Q60+P60 -> 140106.62 | T60: 59 | U60: Sold
A61: 60 | B61: 3.708 | C61: =B61*(25/100) -> 0.927 | D61: =C61+B61 -> 4.635 | E61: 0.26 | L61: =E61*Prices!B$2 -> 28600 | M61: =F61*Prices!C$2 -> 0 | N61: =G61*Prices!D$2 -> 0 | O61: =H61*270000 -> 0 | P61: =I61*2000+J61*4000+K61*650 -> 0 | Q61: =D61*Prices!A$2 -> 82734.75 | R61: =L61+M61+N61+O61 -> 28600 | S61: =R61+Q61+P61 -> 111334.75 | T61: 60 | U61: Sold
A62: 61 | B62: 4.43 | C62: =B62*(25/100) -> 1.1075 | D62: =C62+B62 -> 5.5375 | E62: 0.25 | L62: =E62*Prices!B$2 -> 27500 | M62: =F62*Prices!C$2 -> 0 | N62: =G62*Prices!D$2 -> 0 | O62: =H62*270000 -> 0 | P62: =I62*2000+J62*4000+K62*650 -> 0 | Q62: =D62*Prices!A$2 -> 98844.375 | R62: =L62+M62+N62+O62 -> 27500 | S62: =R62+Q62+P62 -> 126344.38 | T62: 61 | U62: Sold
A63: 62 | B63: 3.842 | C63: =B63*(25/100) -> 0.9605 | D63: =C63+B63 -> 4.8025 | E63: 0.24 | L63: =E63*Prices!B$2 -> 26400 | M63: =F63*Prices!C$2 -> 0 | N63: =G63*Prices!D$2 -> 0 | O63: =H63*270000 -> 0 | P63: =I63*2000+J63*4000+K63*650 -> 0 | Q63: =D63*Prices!A$2 -> 85724.625 | R63: =L63+M63+N63+O63 -> 26400 | S63: =R63+Q63+P63 -> 112124.62 | T63: 62 | U63: Available | V63: A
A64: 63 | B64: 4.706 | C64: =B64*(25/100) -> 1.1765 | D64: =C64+B64 -> 5.8825 | E64: 0.37 | L64: =E64*Prices!B$2 -> 40700 | M64: =F64*Prices!C$2 -> 0 | N64: =G64*Prices!D$2 -> 0 | O64: =H64*270000 -> 0 | P64: =I64*2000+J64*4000+K64*650 -> 0 | Q64: =D64*Prices!A$2 -> 105002.62 | R64: =L64+M64+N64+O64 -> 40700 | S64: =R64+Q64+P64 -> 145702.62 | T64: 63 | U64: Available | V64: A
A65: 64 | B65: 3.408 | C65: =B65*(25/100) -> 0.852 | D65: =C65+B65 -> 4.26 | E65: 0.41 | L65: =E65*Prices!B$2 -> 45100 | M65: =F65*Prices!C$2 -> 0 | N65: =G65*Prices!D$2 -> 0 | O65: =H65*270000 -> 0 | P65: =I65*2000+J65*4000+K65*650 -> 0 | Q65: =D65*Prices!A$2 -> 76041 | R65: =L65+M65+N65+O65 -> 45100 | S65: =R65+Q65+P65 -> 121141 | T65: 64 | U65: Available | V65: A
A66: 65 | B66: 3.668 | C66: =B66*(25/100) -> 0.917 | D66: =C66+B66 -> 4.585 | E66: 0.31 | L66: =E66*Prices!B$2 -> 34100 | M66: =F66*Prices!C$2 -> 0 | N66: =G66*Prices!D$2 -> 0 | O66: =H66*270000 -> 0 | P66: =I66*2000+J66*4000+K66*650 -> 0 | Q66: =D66*Prices!A$2 -> 81842.25 | R66: =L66+M66+N66+O66 -> 34100 | S66: =R66+Q66+P66 -> 115942.25 | T66: 65 | U66: Available | V66: A
A67: 66 | B67: 7.818 | C67: =B67*(25/100) -> 1.9545 | D67: =C67+B67 -> 9.7725 | H67: 1.06 | L67: =E67*Prices!B$2 -> 0 | M67: =F67*Prices!C$2 -> 0 | N67: =G67*Prices!D$2 -> 0 | O67: =H67*675000 -> 715500 | P67: =I67*2000+J67*4000+K67*650 -> 0 | Q67: =D67*Prices!A$2 -> 174439.12 | R67: =L67+M67+N67+O67 -> 715500 | S67: =R67+Q67+P67 -> 889939.12 | T67: 66 | U67: Available | V67: A
A68: 67 | B68: 4.256 | C68: =B68*(25/100) -> 1.064 | D68: =C68+B68 -> 5.32 | E68: 0.32 | L68: =E68*Prices!B$2 -> 35200 | M68: =F68*Prices!C$2 -> 0 | N68: =G68*Prices!D$2 -> 0 | O68: =H68*600000 -> 0 | P68: =I68*2000+J68*4000+K68*650 -> 0 | Q68: =D68*Prices!A$2 -> 94962 | R68: =L68+M68+N68+O68 -> 35200 | S68: =R68+Q68+P68 -> 130162 | T68: 67 | U68: Sold
A69: 68 | B69: 3.524 | C69: =B69*(25/100) -> 0.881 | D69: =C69+B69 -> 4.405 | E69: 0.18 | L69: =E69*Prices!B$2 -> 19800 | M69: =F69*Prices!C$2 -> 0 | N69: =G69*Prices!D$2 -> 0 | O69: =H69*600000 -> 0 | P69: =I69*2000+J69*4000+K69*650 -> 0 | Q69: =D69*Prices!A$2 -> 78629.25 | R69: =L69+M69+N69+O69 -> 19800 | S69: =R69+Q69+P69 -> 98429.25 | T69: 68 | U69: Sold
A70: 69 | B70: 3.252 | C70: =B70*(25/100) -> 0.813 | D70: =C70+B70 -> 4.065 | E70: 0.34 | L70: =E70*Prices!B$2 -> 37400 | M70: =F70*Prices!C$2 -> 0 | N70: =G70*Prices!D$2 -> 0 | O70: =H70*600000 -> 0 | P70: =I70*2000+J70*4000+K70*650 -> 0 | Q70: =D70*Prices!A$2 -> 72560.25 | R70: =L70+M70+N70+O70 -> 37400 | S70: =R70+Q70+P70 -> 109960.25 | T70: 69 | U70: Sold

Sheet Top
A1: Sn | B1: Net Weightt | C1: Wstg + MC | D1: Gross weight | E1: Dmd <0.06 | F1: Dmd < 0.12 | G1: Dmd <0.17 | H1: Dmd Big | I1: Ruby | J1: Emreld | K1: Muga | L1: Dmd Price | M1: Dmd Price | N1: Dmd Price | O1: Dmd Price | P1: Stn Price | Q1: Gold Price | R1: Ttl dmd Price | S1: Total Price | T1: Sn
A2: 1 | B2: 6.558 | C2: =B2*(25/100) -> 1.6395 | D2: =C2+B2 -> 8.1975 | E2: 0.96 | K2: 6.1 | L2: =E2*Prices!B$2 -> 105600 | M2: =F2*Prices!C$2 -> 0 | N2: =G2*Prices!D$2 -> 0 | O2: =H2*Prices!E$2 -> 0 | P2: =I2*2000+J2*10000+K2*1800 -> 10980 | Q2: =D2*Prices!A$2 -> 146325.38 | R2: =L2+M2+N2+O2 -> 105600 | S2: =R2+Q2+P2 -> 262905.38 | T2: 1 | U2: Return
A3: 2 | B3: 5.89 | C3: =B3*(25/100) -> 1.4725 | D3: =C3+B3 -> 7.3625 | E3: 0.84 | K3: 4.19 | L3: =E3*Prices!B$2 -> 92400 | M3: =F3*Prices!C$2 -> 0 | N3: =G3*Prices!D$2 -> 0 | O3: =H3*Prices!E$2 -> 0 | P3: =I3*2000+J3*10000+K3*1800 -> 7542 | Q3: =D3*Prices!A$2 -> 131420.62 | R3: =L3+M3+N3+O3 -> 92400 | S3: =R3+Q3+P3 -> 231362.62 | T3: 2 | U3: Return
A4: 3 | B4: 2.902 | C4: =B4*(25/100) -> 0.7255 | D4: =C4+B4 -> 3.6275 | E4: 0.64 | L4: =E4*Prices!B$2 -> 70400 | M4: =F4*Prices!C$2 -> 0 | N4: =G4*Prices!D$2 -> 0 | O4: =H4*Prices!E$2 -> 0 | P4: =I4*2000+J4*10000+K4*1800 -> 0 | Q4: =D4*Prices!A$2 -> 64750.875 | R4: =L4+M4+N4+O4 -> 70400 | S4: =R4+Q4+P4 -> 135150.88 | T4: 3 | U4: Available | V4: A
A5: 4 | B5: 3.04 | C5: =B5*(25/100) -> 0.76 | D5: =C5+B5 -> 3.8 | F5: 0.95 | L5: =E5*Prices!B$2 -> 0 | M5: =F5*Prices!C$2 -> 152000 | N5: =G5*Prices!D$2 -> 0 | O5: =H5*Prices!E$2 -> 0 | P5: =I5*2000+J5*10000+K5*1800 -> 0 | Q5: =D5*Prices!A$2 -> 67830 | R5: =L5+M5+N5+O5 -> 152000 | S5: =R5+Q5+P5 -> 219830 | T5: 4 | U5: Available | V5: A
A6: 5 | B6: 3.936 | C6: =B6*(25/100) -> 0.984 | D6: =C6+B6 -> 4.92 | E6: 0.65 | G6: 0.32 | L6: =E6*Prices!B$2 -> 71500 | M6: =F6*Prices!C$2 -> 0 | N6: =G6*Prices!D$2 -> 62400 | O6: =H6*Prices!E$2 -> 0 | P6: =I6*2000+J6*10000+K6*1800 -> 0 | Q6: =D6*Prices!A$2 -> 87822 | R6: =L6+M6+N6+O6 -> 133900 | S6: =R6+Q6+P6 -> 221722 | T6: 5 | U6: Available | V6: A
A7: 6 | B7: 5.382 | C7: =B7*(25/100) -> 1.3455 | D7: =C7+B7 -> 6.7275 | E7: =0.4+0.29 -> 0.69 | L7: =E7*Prices!B$2 -> 75900 | M7: =F7*Prices!C$2 -> 0 | N7: =G7*Prices!D$2 -> 0 | O7: =H7*Prices!E$2 -> 0 | P7: =I7*2000+J7*10000+K7*1800 -> 0 | Q7: =D7*Prices!A$2 -> 120085.88 | R7: =L7+M7+N7+O7 -> 75900 | S7: =R7+Q7+P7 -> 195985.88 | T7: 6 | U7: Sold
A8: 7 | B8: 3.078 | C8: =B8*(25/100) -> 0.7695 | D8: =C8+B8 -> 3.8475 | E8: 0.56 | L8: =E8*Prices!B$2 -> 61600 | M8: =F8*Prices!C$2 -> 0 | N8: =G8*Prices!D$2 -> 0 | O8: =H8*Prices!E$2 -> 0 | P8: =I8*2000+J8*10000+K8*1800 -> 0 | Q8: =D8*Prices!A$2 -> 68677.875 | R8: =L8+M8+N8+O8 -> 61600 | S8: =R8+Q8+P8 -> 130277.88 | T8: 7 | U8: Sold
A9: 8 | B9: 3.996 | C9: =B9*(25/100) -> 0.999 | D9: =C9+B9 -> 4.995 | E9: =0.66+0.21 -> 0.87 | L9: =E9*Prices!B$2 -> 95700 | M9: =F9*Prices!C$2 -> 0 | N9: =G9*Prices!D$2 -> 0 | O9: =H9*Prices!E$2 -> 0 | P9: =I9*2000+J9*10000+K9*1800 -> 0 | Q9: =D9*Prices!A$2 -> 89160.75 | R9: =L9+M9+N9+O9 -> 95700 | S9: =R9+Q9+P9 -> 184860.75 | T9: 8 | U9: Sold
A10: 9 | B10: 2.502 | C10: =B10*(25/100) -> 0.6255 | D10: =C10+B10 -> 3.1275 | E10: 0.44 | L10: =E10*Prices!B$2 -> 48400 | M10: =F10*Prices!C$2 -> 0 | N10: =G10*Prices!D$2 -> 0 | O10: =H10*Prices!E$2 -> 0 | P10: =I10*2000+J10*10000+K10*1800 -> 0 | Q10: =D10*Prices!A$2 -> 55825.875 | R10: =L10+M10+N10+O10 -> 48400 | S10: =R10+Q10+P10 -> 104225.88 | T10: 9 | U10: Sold
A11: 10 | B11: 1.908 | C11: =B11*(25/100) -> 0.477 | D11: =C11+B11 -> 2.385 | E11: 0.36 | L11: =E11*Prices!B$2 -> 39600 | M11: =F11*Prices!C$2 -> 0 | N11: =G11*Prices!D$2 -> 0 | O11: =H11*Prices!E$2 -> 0 | P11: =I11*2000+J11*10000+K11*1800 -> 0 | Q11: =D11*Prices!A$2 -> 42572.25 | R11: =L11+M11+N11+O11 -> 39600 | S11: =R11+Q11+P11 -> 82172.25 | T11: 10 | U11: Available | V11: A
A12: 11 | B12: 2.306 | C12: =B12*(25/100) -> 0.5765 | D12: =C12+B12 -> 2.8825 | E12: 0.27 | L12: =E12*Prices!B$2 -> 29700 | M12: =F12*Prices!C$2 -> 0 | N12: =G12*Prices!D$2 -> 0 | O12: =H12*Prices!E$2 -> 0 | P12: =I12*2000+J12*10000+K12*1800 -> 0 | Q12: =D12*Prices!A$2 -> 51452.625 | R12: =L12+M12+N12+O12 -> 29700 | S12: =R12+Q12+P12 -> 81152.625 | T12: 11 | U12: Sold
A13: 12 | B13: 4.23 | C13: =B13*(25/100) -> 1.0575 | D13: =C13+B13 -> 5.2875 | E13: 0.6 | L13: =E13*Prices!B$2 -> 66000 | M13: =F13*Prices!C$2 -> 0 | N13: =G13*Prices!D$2 -> 0 | O13: =H13*Prices!E$2 -> 0 | P13: =I13*2000+J13*10000+K13*1800 -> 0 | Q13: =D13*Prices!A$2 -> 94381.875 | R13: =L13+M13+N13+O13 -> 66000 | S13: =R13+Q13+P13 -> 160381.88 | T13: 12 | U13: Return
A14: 13 | B14: 4.4 | C14: =B14*(25/100) -> 1.1 | D14: =C14+B14 -> 5.5 | E14: 0.75 | L14: =E14*Prices!B$2 -> 82500 | M14: =F14*Prices!C$2 -> 0 | N14: =G14*Prices!D$2 -> 0 | O14: =H14*Prices!E$2 -> 0 | P14: =I14*2000+J14*10000+K14*1800 -> 0 | Q14: =D14*Prices!A$2 -> 98175 | R14: =L14+M14+N14+O14 -> 82500 | S14: =R14+Q14+P14 -> 180675 | T14: 13 | U14: Available | V14: A
A15: 14 | B15: 4.932 | C15: =B15*(25/100) -> 1.233 | D15: =C15+B15 -> 6.165 | E15: 0.69 | L15: =E15*Prices!B$2 -> 75900 | M15: =F15*Prices!C$2 -> 0 | N15: =G15*Prices!D$2 -> 0 | O15: =H15*Prices!E$2 -> 0 | P15: =I15*2000+J15*10000+K15*1800 -> 0 | Q15: =D15*Prices!A$2 -> 110045.25 | R15: =L15+M15+N15+O15 -> 75900 | S15: =R15+Q15+P15 -> 185945.25 | T15: 14 | U15: Return
A16: 15 | B16: 3.97 | C16: =B16*(25/100) -> 0.9925 | D16: =C16+B16 -> 4.9625 | E16: 1.35 | L16: =E16*Prices!B$2 -> 148500 | M16: =F16*Prices!C$2 -> 0 | N16: =G16*Prices!D$2 -> 0 | O16: =H16*Prices!E$2 -> 0 | P16: =I16*2000+J16*10000+K16*1800 -> 0 | Q16: =D16*Prices!A$2 -> 88580.625 | R16: =L16+M16+N16+O16 -> 148500 | S16: =R16+Q16+P16 -> 237080.62 | T16: 15 | U16: Available | V16: A
A17: 16 | B17: 2.866 | C17: =B17*(25/100) -> 0.7165 | D17: =C17+B17 -> 3.5825 | E17: 0.67 | L17: =E17*Prices!B$2 -> 73700 | M17: =F17*Prices!C$2 -> 0 | N17: =G17*Prices!D$2 -> 0 | O17: =H17*Prices!E$2 -> 0 | P17: =I17*2000+J17*10000+K17*1800 -> 0 | Q17: =D17*Prices!A$2 -> 63947.625 | R17: =L17+M17+N17+O17 -> 73700 | S17: =R17+Q17+P17 -> 137647.62 | T17: 16 | U17: Sold
A18: 17 | B18: 1.548 | C18: =B18*(25/100) -> 0.387 | D18: =C18+B18 -> 1.935 | E18: 0.21 | L18: =E18*Prices!B$2 -> 23100 | M18: =F18*Prices!C$2 -> 0 | N18: =G18*Prices!D$2 -> 0 | O18: =H18*Prices!E$2 -> 0 | P18: =I18*2000+J18*10000+K18*1800 -> 0 | Q18: =D18*Prices!A$2 -> 34539.75 | R18: =L18+M18+N18+O18 -> 23100 | S18: =R18+Q18+P18 -> 57639.75 | T18: 17 | U18: Available | V18: A
A19: 18 | B19: 4.62 | C19: =B19*(25/100) -> 1.155 | D19: =C19+B19 -> 5.775 | E19: 1.12 | L19: =E19*Prices!B$2 -> 123200 | M19: =F19*Prices!C$2 -> 0 | N19: =G19*Prices!D$2 -> 0 | O19: =H19*Prices!E$2 -> 0 | P19: =I19*2000+J19*10000+K19*1800 -> 0 | Q19: =D19*Prices!A$2 -> 103083.75 | R19: =L19+M19+N19+O19 -> 123200 | S19: =R19+Q19+P19 -> 226283.75 | T19: 18 | U19: Sold
A20: 19 | B20: 4.136 | C20: =B20*(25/100) -> 1.034 | D20: =C20+B20 -> 5.17 | E20: 0.42 | L20: =E20*Prices!B$2 -> 46200 | M20: =F20*Prices!C$2 -> 0 | N20: =G20*Prices!D$2 -> 0 | O20: =H20*Prices!E$2 -> 0 | P20: =I20*2000+J20*10000+K20*1800 -> 0 | Q20: =D20*Prices!A$2 -> 92284.5 | R20: =L20+M20+N20+O20 -> 46200 | S20: =R20+Q20+P20 -> 138484.5 | T20: 19 | U20: Sold
A21: 20 | B21: 6.37 | C21: =B21*(25/100) -> 1.5925 | D21: =C21+B21 -> 7.9625 | E21: 1.27 | J21: 4.86 | L21: =E21*Prices!B$2 -> 139700 | M21: =F21*Prices!C$2 -> 0 | N21: =G21*Prices!D$2 -> 0 | O21: =H21*Prices!E$2 -> 0 | P21: =I21*2000+J21*10000+K21*1800 -> 48600 | Q21: =D21*Prices!A$2 -> 142130.62 | R21: =L21+M21+N21+O21 -> 139700 | S21: =R21+Q21+P21 -> 330430.62 | T21: 20 | U21: Available | V21: A
A22: 21 | B22: 4.1 | C22: =B22*(25/100) -> 1.025 | D22: =C22+B22 -> 5.125 | E22: 1.15 | J22: 2.29 | L22: =E22*Prices!B$2 -> 126500 | M22: =F22*Prices!C$2 -> 0 | N22: =G22*Prices!D$2 -> 0 | O22: =H22*Prices!E$2 -> 0 | P22: =I22*2000+J22*10000+K22*1800 -> 22900 | Q22: =D22*Prices!A$2 -> 91481.25 | R22: =L22+M22+N22+O22 -> 126500 | S22: =R22+Q22+P22 -> 240881.25 | T22: 21 | U22: Available | V22: A
A23: 22 | B23: 4.836 | C23: =B23*(25/100) -> 1.209 | D23: =C23+B23 -> 6.045 | E23: 1.13 | J23: 1.39 | L23: =E23*Prices!B$2 -> 124300 | M23: =F23*Prices!C$2 -> 0 | N23: =G23*Prices!D$2 -> 0 | O23: =H23*Prices!E$2 -> 0 | P23: =I23*2000+J23*10000+K23*1800 -> 13900 | Q23: =D23*Prices!A$2 -> 107903.25 | R23: =L23+M23+N23+O23 -> 124300 | S23: =R23+Q23+P23 -> 246103.25 | T23: 22 | U23: Available | V23: A
A24: 23 | B24: 4.21 | C24: =B24*(25/100) -> 1.0525 | D24: =C24+B24 -> 5.2625 | E24: 0.83 | I24: 1.92 | L24: =E24*Prices!B$2 -> 91300 | M24: =F24*Prices!C$2 -> 0 | N24: =G24*Prices!D$2 -> 0 | O24: =H24*Prices!E$2 -> 0 | P24: =I24*2000+J24*10000+K24*1800 -> 3840 | Q24: =D24*Prices!A$2 -> 93935.625 | R24: =L24+M24+N24+O24 -> 91300 | S24: =R24+Q24+P24 -> 189075.62 | T24: 23 | U24: Available | V24: A
A25: 24 | B25: 3.318 | C25: =B25*(25/100) -> 0.8295 | D25: =C25+B25 -> 4.1475 | E25: 0.53 | I25: 2.53 | L25: =E25*Prices!B$2 -> 58300 | M25: =F25*Prices!C$2 -> 0 | N25: =G25*Prices!D$2 -> 0 | O25: =H25*Prices!E$2 -> 0 | P25: =I25*2000+J25*10000+K25*1800 -> 5060 | Q25: =D25*Prices!A$2 -> 74032.875 | R25: =L25+M25+N25+O25 -> 58300 | S25: =R25+Q25+P25 -> 137392.88 | T25: 24 | U25: Sold
A26: 25 | B26: 3.408 | C26: =B26*(25/100) -> 0.852 | D26: =C26+B26 -> 4.26 | F26: 0.66 | L26: =E26*Prices!B$2 -> 0 | M26: =F26*Prices!C$2 -> 105600 | N26: =G26*Prices!D$2 -> 0 | O26: =H26*Prices!E$2 -> 0 | P26: =I26*2000+J26*10000+K26*1800 -> 0 | Q26: =D26*Prices!A$2 -> 76041 | R26: =L26+M26+N26+O26 -> 105600 | S26: =R26+Q26+P26 -> 181641 | T26: 25 | U26: Available | V26: A
A27: 26 | B27: 5.762 | C27: =B27*(25/100) -> 1.4405 | D27: =C27+B27 -> 7.2025 | E27: 1.54 | L27: =E27*Prices!B$2 -> 169400 | M27: =F27*Prices!C$2 -> 0 | N27: =G27*Prices!D$2 -> 0 | O27: =H27*Prices!E$2 -> 0 | P27: =I27*2000+J27*10000+K27*1800 -> 0 | Q27: =D27*Prices!A$2 -> 128564.62 | R27: =L27+M27+N27+O27 -> 169400 | S27: =R27+Q27+P27 -> 297964.62 | T27: 26 | U27: Sold
A28: 27 | B28: 7.34 | C28: =B28*(25/100) -> 1.835 | D28: =C28+B28 -> 9.175 | E28: 2.55 | L28: =E28*Prices!B$2 -> 280500 | M28: =F28*Prices!C$2 -> 0 | N28: =G28*Prices!D$2 -> 0 | O28: =H28*Prices!E$2 -> 0 | P28: =I28*2000+J28*10000+K28*1800 -> 0 | Q28: =D28*Prices!A$2 -> 163773.75 | R28: =L28+M28+N28+O28 -> 280500 | S28: =R28+Q28+P28 -> 444273.75 | T28: 27 | U28: Sold
A29: 28 | B29: 2.966 | C29: =B29*(25/100) -> 0.7415 | D29: =C29+B29 -> 3.7075 | E29: 0.72 | L29: =E29*Prices!B$2 -> 79200 | M29: =F29*Prices!C$2 -> 0 | N29: =G29*Prices!D$2 -> 0 | O29: =H29*Prices!E$2 -> 0 | P29: =I29*2000+J29*10000+K29*1800 -> 0 | Q29: =D29*Prices!A$2 -> 66178.875 | R29: =L29+M29+N29+O29 -> 79200 | S29: =R29+Q29+P29 -> 145378.88 | T29: 28 | U29: Sold
A30: 29 | B30: 4.518 | C30: =B30*(25/100) -> 1.1295 | D30: =C30+B30 -> 5.6475 | E30: 1.58 | G30: 0.33 | L30: =E30*Prices!B$2 -> 173800 | M30: =F30*Prices!C$2 -> 0 | N30: =G30*Prices!D$2 -> 64350 | O30: =H30*Prices!E$2 -> 0 | P30: =I30*2000+J30*10000+K30*1800 -> 0 | Q30: =D30*Prices!A$2 -> 100807.88 | R30: =L30+M30+N30+O30 -> 238150 | S30: =R30+Q30+P30 -> 338957.88 | T30: 29 | U30: Sold
A31: 30 | B31: 3.662 | C31: =B31*(25/100) -> 0.9155 | D31: =C31+B31 -> 4.5775 | E31: 1.64 | L31: =E31*Prices!B$2 -> 180400 | M31: =F31*Prices!C$2 -> 0 | N31: =G31*Prices!D$2 -> 0 | O31: =H31*Prices!E$2 -> 0 | P31: =I31*2000+J31*10000+K31*1800 -> 0 | Q31: =D31*Prices!A$2 -> 81708.375 | R31: =L31+M31+N31+O31 -> 180400 | S31: =R31+Q31+P31 -> 262108.38 | T31: 30 | U31: Sold
A32: 31 | B32: 6.38 | C32: =B32*(25/100) -> 1.595 | D32: =C32+B32 -> 7.975 | E32: 1.55 | L32: =E32*Prices!B$2 -> 170500 | M32: =F32*Prices!C$2 -> 0 | N32: =G32*Prices!D$2 -> 0 | O32: =H32*Prices!E$2 -> 0 | P32: =I32*2000+J32*10000+K32*1800 -> 0 | Q32: =D32*Prices!A$2 -> 142353.75 | R32: =L32+M32+N32+O32 -> 170500 | S32: =R32+Q32+P32 -> 312853.75 | T32: 31 | U32: Sold
A33: 32 | B33: 5.57 | C33: =B33*(25/100) -> 1.3925 | D33: =C33+B33 -> 6.9625 | E33: 0.82 | L33: =E33*Prices!B$2 -> 90200 | M33: =F33*Prices!C$2 -> 0 | N33: =G33*Prices!D$2 -> 0 | O33: =H33*Prices!E$2 -> 0 | P33: =I33*2000+J33*10000+K33*1800 -> 0 | Q33: =D33*Prices!A$2 -> 124280.62 | R33: =L33+M33+N33+O33 -> 90200 | S33: =R33+Q33+P33 -> 214480.62 | T33: 32 | U33: Sold
A34: 33 | B34: 5.05 | C34: =B34*(25/100) -> 1.2625 | D34: =C34+B34 -> 6.3125 | E34: 0.42 | L34: =E34*Prices!B$2 -> 46200 | M34: =F34*Prices!C$2 -> 0 | N34: =G34*Prices!D$2 -> 0 | O34: =H34*Prices!E$2 -> 0 | P34: =I34*2000+J34*10000+K34*1800 -> 0 | Q34: =D34*Prices!A$2 -> 112678.12 | R34: =L34+M34+N34+O34 -> 46200 | S34: =R34+Q34+P34 -> 158878.12 | T34: 33 | U34: Sold
A35: 34 | B35: 3.78 | C35: =B35*(25/100) -> 0.945 | D35: =C35+B35 -> 4.725 | E35: 0.6 | L35: =E35*Prices!B$2 -> 66000 | M35: =F35*Prices!C$2 -> 0 | N35: =G35*Prices!D$2 -> 0 | O35: =H35*Prices!E$2 -> 0 | P35: =I35*2000+J35*10000+K35*1800 -> 0 | Q35: =D35*Prices!A$2 -> 84341.25 | R35: =L35+M35+N35+O35 -> 66000 | S35: =R35+Q35+P35 -> 150341.25 | T35: 34 | U35: Available | V35: A
A36: 35 | B36: 5.34 | C36: =B36*(25/100) -> 1.335 | D36: =C36+B36 -> 6.675 | E36: 1.36 | L36: =E36*Prices!B$2 -> 149600 | M36: =F36*Prices!C$2 -> 0 | N36: =G36*Prices!D$2 -> 0 | O36: =H36*Prices!E$2 -> 0 | P36: =I36*2000+J36*10000+K36*1800 -> 0 | Q36: =D36*Prices!A$2 -> 119148.75 | R36: =L36+M36+N36+O36 -> 149600 | S36: =R36+Q36+P36 -> 268748.75 | T36: 35 | U36: Available | V36: A
A37: 36 | B37: 2.412 | C37: =B37*(25/100) -> 0.603 | D37: =C37+B37 -> 3.015 | E37: 0.64 | L37: =E37*Prices!B$2 -> 70400 | M37: =F37*Prices!C$2 -> 0 | N37: =G37*Prices!D$2 -> 0 | O37: =H37*Prices!E$2 -> 0 | P37: =I37*2000+J37*10000+K37*1800 -> 0 | Q37: =D37*Prices!A$2 -> 53817.75 | R37: =L37+M37+N37+O37 -> 70400 | S37: =R37+Q37+P37 -> 124217.75 | T37: 36 | U37: Sold
A38: 37 | B38: 8.46 | C38: =B38*(25/100) -> 2.115 | D38: =C38+B38 -> 10.575 | E38: =1.3+0.56 -> 1.86 | L38: =E38*Prices!B$2 -> 204600 | M38: =F38*Prices!C$2 -> 0 | N38: =G38*Prices!D$2 -> 0 | O38: =H38*Prices!E$2 -> 0 | P38: =I38*2000+J38*10000+K38*1800 -> 0 | Q38: =D38*Prices!A$2 -> 188763.75 | R38: =L38+M38+N38+O38 -> 204600 | S38: =R38+Q38+P38 -> 393363.75 | T38: 37 | U38: Available | V38: A
A39: 38 | B39: 6.22 | C39: =B39*(25/100) -> 1.555 | D39: =C39+B39 -> 7.775 | E39: 0.97 | L39: =E39*Prices!B$2 -> 106700 | M39: =F39*Prices!C$2 -> 0 | N39: =G39*Prices!D$2 -> 0 | O39: =H39*Prices!E$2 -> 0 | P39: =I39*2000+J39*10000+K39*1800 -> 0 | Q39: =D39*Prices!A$2 -> 138783.75 | R39: =L39+M39+N39+O39 -> 106700 | S39: =R39+Q39+P39 -> 245483.75 | T39: 38 | U39: Sold
A40: 39 | B40: 4.09 | C40: =B40*(25/100) -> 1.0225 | D40: =C40+B40 -> 5.1125 | E40: 0.7 | L40: =E40*Prices!B$2 -> 77000 | M40: =F40*Prices!C$2 -> 0 | N40: =G40*Prices!D$2 -> 0 | O40: =H40*Prices!E$2 -> 0 | P40: =I40*2000+J40*10000+K40*1800 -> 0 | Q40: =D40*Prices!A$2 -> 91258.125 | R40: =L40+M40+N40+O40 -> 77000 | S40: =R40+Q40+P40 -> 168258.12 | T40: 39 | U40: Sold
A41: 40 | B41: 4.632 | C41: =B41*(25/100) -> 1.158 | D41: =C41+B41 -> 5.79 | E41: 1.48 | G41: 0.31 | L41: =E41*Prices!B$2 -> 162800 | M41: =F41*Prices!C$2 -> 0 | N41: =G41*Prices!D$2 -> 60450 | O41: =H41*Prices!E$2 -> 0 | P41: =I41*2000+J41*10000+K41*1800 -> 0 | Q41: =D41*Prices!A$2 -> 103351.5 | R41: =L41+M41+N41+O41 -> 223250 | S41: =R41+Q41+P41 -> 326601.5 | T41: 40 | U41: Sold
A42: 41 | B42: 3.588 | C42: =B42*(25/100) -> 0.897 | D42: =C42+B42 -> 4.485 | E42: =0.66+0.2 -> 0.86 | L42: =E42*Prices!B$2 -> 94600 | M42: =F42*Prices!C$2 -> 0 | N42: =G42*Prices!D$2 -> 0 | O42: =H42*Prices!E$2 -> 0 | P42: =I42*2000+J42*10000+K42*1800 -> 0 | Q42: =D42*Prices!A$2 -> 80057.25 | R42: =L42+M42+N42+O42 -> 94600 | S42: =R42+Q42+P42 -> 174657.25 | T42: 41 | U42: Sold
A43: 42 | B43: 6.412 | C43: =B43*(25/100) -> 1.603 | D43: =C43+B43 -> 8.015 | E43: =0.86+0.38 -> 1.24 | L43: =E43*Prices!B$2 -> 136400 | M43: =F43*Prices!C$2 -> 0 | N43: =G43*Prices!D$2 -> 0 | O43: =H43*Prices!E$2 -> 0 | P43: =I43*2000+J43*10000+K43*1800 -> 0 | Q43: =D43*Prices!A$2 -> 143067.75 | R43: =L43+M43+N43+O43 -> 136400 | S43: =R43+Q43+P43 -> 279467.75 | T43: 42 | U43: Available | V43: A
A44: 43 | B44: 1.942 | C44: =B44*(25/100) -> 0.4855 | D44: =C44+B44 -> 2.4275 | E44: 0.24 | L44: =E44*Prices!B$2 -> 26400 | M44: =F44*Prices!C$2 -> 0 | N44: =G44*Prices!D$2 -> 0 | O44: =H44*Prices!E$2 -> 0 | P44: =I44*2000+J44*10000+K44*1800 -> 0 | Q44: =D44*Prices!A$2 -> 43330.875 | R44: =L44+M44+N44+O44 -> 26400 | S44: =R44+Q44+P44 -> 69730.875 | T44: 43 | U44: Sold
A45: 44 | B45: 1.96 | C45: =B45*(25/100) -> 0.49 | D45: =C45+B45 -> 2.45 | F45: 0.93 | L45: =E45*Prices!B$2 -> 0 | M45: =F45*Prices!C$2 -> 148800 | N45: =G45*Prices!D$2 -> 0 | O45: =H45*Prices!E$2 -> 0 | P45: =I45*2000+J45*10000+K45*1800 -> 0 | Q45: =D45*Prices!A$2 -> 43732.5 | R45: =L45+M45+N45+O45 -> 148800 | S45: =R45+Q45+P45 -> 192532.5 | T45: 44 | U45: Sold
A46: 45 | B46: 1.348 | C46: =B46*(25/100) -> 0.337 | D46: =C46+B46 -> 1.685 | E46: 0.26 | L46: =E46*Prices!B$2 -> 28600 | M46: =F46*Prices!C$2 -> 0 | N46: =G46*Prices!D$2 -> 0 | O46: =H46*Prices!E$2 -> 0 | P46: =I46*2000+J46*10000+K46*1800 -> 0 | Q46: =D46*Prices!A$2 -> 30077.25 | R46: =L46+M46+N46+O46 -> 28600 | S46: =R46+Q46+P46 -> 58677.25 | T46: 45 | U46: Sold
A47: 46 | B47: 1.702 | C47: =B47*(25/100) -> 0.4255 | D47: =C47+B47 -> 2.1275 | E47: 0.34 | L47: =E47*Prices!B$2 -> 37400 | M47: =F47*Prices!C$2 -> 0 | N47: =G47*Prices!D$2 -> 0 | O47: =H47*Prices!E$2 -> 0 | P47: =I47*2000+J47*10000+K47*1800 -> 0 | Q47: =D47*Prices!A$2 -> 37975.875 | R47: =L47+M47+N47+O47 -> 37400 | S47: =R47+Q47+P47 -> 75375.875 | T47: 46 | U47: Sold
A48: 47 | B48: 2.8 | C48: =B48*(25/100) -> 0.7 | D48: =C48+B48 -> 3.5 | E48: 0.55 | F48: 0.15 | L48: =E48*Prices!B$2 -> 60500 | M48: =F48*Prices!C$2 -> 24000 | N48: =G48*Prices!D$2 -> 0 | O48: =H48*Prices!E$2 -> 0 | P48: =I48*2000+J48*10000+K48*1800 -> 0 | Q48: =D48*Prices!A$2 -> 62475 | R48: =L48+M48+N48+O48 -> 84500 | S48: =R48+Q48+P48 -> 146975 | T48: 47 | U48: Sold
A49: 48 | B49: 2.288 | C49: =B49*(25/100) -> 0.572 | D49: =C49+B49 -> 2.86 | E49: 0.31 | L49: =E49*Prices!B$2 -> 34100 | M49: =F49*Prices!C$2 -> 0 | N49: =G49*Prices!D$2 -> 0 | O49: =H49*Prices!E$2 -> 0 | P49: =I49*2000+J49*10000+K49*1800 -> 0 | Q49: =D49*Prices!A$2 -> 51051 | R49: =L49+M49+N49+O49 -> 34100 | S49: =R49+Q49+P49 -> 85151 | T49: 48 | U49: Sold
A50: 49 | B50: 1.386 | C50: =B50*(25/100) -> 0.3465 | D50: =C50+B50 -> 1.7325 | E50: 0.22 | L50: =E50*Prices!B$2 -> 24200 | M50: =F50*Prices!C$2 -> 0 | N50: =G50*Prices!D$2 -> 0 | O50: =H50*Prices!E$2 -> 0 | P50: =I50*2000+J50*10000+K50*1800 -> 0 | Q50: =D50*Prices!A$2 -> 30925.125 | R50: =L50+M50+N50+O50 -> 24200 | S50: =R50+Q50+P50 -> 55125.125 | T50: 49 | U50: Sold
A51: 50 | B51: 2.646 | C51: =B51*(25/100) -> 0.6615 | D51: =C51+B51 -> 3.3075 | E51: 0.22 | L51: =E51*Prices!B$2 -> 24200 | M51: =F51*Prices!C$2 -> 0 | N51: =G51*Prices!D$2 -> 0 | O51: =H51*Prices!E$2 -> 0 | P51: =I51*2000+J51*10000+K51*1800 -> 0 | Q51: =D51*Prices!A$2 -> 59038.875 | R51: =L51+M51+N51+O51 -> 24200 | S51: =R51+Q51+P51 -> 83238.875 | T51: 50 | U51: sold
A52: 51 | B52: 3.486 | C52: =B52*(25/100) -> 0.8715 | D52: =C52+B52 -> 4.3575 | E52: 0.67 | L52: =E52*Prices!B$2 -> 73700 | M52: =F52*Prices!C$2 -> 0 | N52: =G52*Prices!D$2 -> 0 | O52: =H52*Prices!E$2 -> 0 | P52: =I52*2000+J52*10000+K52*1800 -> 0 | Q52: =D52*Prices!A$2 -> 77781.375 | R52: =L52+M52+N52+O52 -> 73700 | S52: =R52+Q52+P52 -> 151481.38 | T52: 51 | U52: Available | V52: A
A53: 52 | B53: 5.48 | C53: =B53*(25/100) -> 1.37 | D53: =C53+B53 -> 6.85 | E53: =1.06+0.42 -> 1.48 | L53: =E53*Prices!B$2 -> 162800 | M53: =F53*Prices!C$2 -> 0 | N53: =G53*Prices!D$2 -> 0 | O53: =H53*Prices!E$2 -> 0 | P53: =I53*2000+J53*10000+K53*1800 -> 0 | Q53: =D53*Prices!A$2 -> 122272.5 | R53: =L53+M53+N53+O53 -> 162800 | S53: =R53+Q53+P53 -> 285072.5 | T53: 52 | U53: Available | V53: A
A54: 53 | B54: 5.66 | C54: =B54*(25/100) -> 1.415 | D54: =C54+B54 -> 7.075 | E54: =0.4+0.42 -> 0.82 | K54: 4.38 | L54: =E54*Prices!B$2 -> 90200 | M54: =F54*Prices!C$2 -> 0 | N54: =G54*Prices!D$2 -> 0 | O54: =H54*Prices!E$2 -> 0 | P54: =I54*2000+J54*10000+K54*1800 -> 7884 | Q54: =D54*Prices!A$2 -> 126288.75 | R54: =L54+M54+N54+O54 -> 90200 | S54: =R54+Q54+P54 -> 224372.75 | T54: 53 | U54: Return
A55: 54 | B55: 8.606 | C55: =B55*(25/100) -> 2.1515 | D55: =C55+B55 -> 10.7575 | E55: 1.34 | K55: 0.38 | L55: =E55*Prices!B$2 -> 147400 | M55: =F55*Prices!C$2 -> 0 | N55: =G55*Prices!D$2 -> 0 | O55: =H55*Prices!E$2 -> 0 | P55: =I55*2000+J55*10000+K55*1800 -> 684 | Q55: =D55*Prices!A$2 -> 192021.38 | R55: =L55+M55+N55+O55 -> 147400 | S55: =R55+Q55+P55 -> 340105.38 | T55: 54 | U55: Available | V55: A
A56: 55 | B56: 3.66 | C56: =B56*(25/100) -> 0.915 | D56: =C56+B56 -> 4.575 | E56: 0.43 | K56: 3.62 | L56: =E56*Prices!B$2 -> 47300 | M56: =F56*Prices!C$2 -> 0 | N56: =G56*Prices!D$2 -> 0 | O56: =H56*Prices!E$2 -> 0 | P56: =I56*2000+J56*10000+K56*1800 -> 6516 | Q56: =D56*Prices!A$2 -> 81663.75 | R56: =L56+M56+N56+O56 -> 47300 | S56: =R56+Q56+P56 -> 135479.75 | T56: 55 | U56: Available | V56: A
A57: 56 | B57: 7.382 | C57: =B57*(25/100) -> 1.8455 | D57: =C57+B57 -> 9.2275 | E57: 1.26 | L57: =E57*Prices!B$2 -> 138600 | M57: =F57*Prices!C$2 -> 0 | N57: =G57*Prices!D$2 -> 0 | O57: =H57*Prices!E$2 -> 0 | P57: =I57*2000+J57*10000+K57*1800 -> 0 | Q57: =D57*Prices!A$2 -> 164710.88 | R57: =L57+M57+N57+O57 -> 138600 | S57: =R57+Q57+P57 -> 303310.88 | T57: 56 | U57: Sold
A58: 57 | B58: 6.514 | C58: =B58*(25/100) -> 1.6285 | D58: =C58+B58 -> 8.1425 | E58: 1.33 | K58: 6.95 | L58: =E58*Prices!B$2 -> 146300 | M58: =F58*Prices!C$2 -> 0 | N58: =G58*Prices!D$2 -> 0 | O58: =H58*Prices!E$2 -> 0 | P58: =I58*2000+J58*10000+K58*6000 -> 41700 | Q58: =D58*Prices!A$2 -> 145343.62 | R58: =L58+M58+N58+O58 -> 146300 | S58: =R58+Q58+P58 -> 333343.62 | T58: 57 | U58: Available | V58: A
A59: 58 | B59: 2.97 | C59: =B59*(25/100) -> 0.7425 | D59: =C59+B59 -> 3.7125 | E59: 0.88 | J59: 0.81 | L59: =E59*Prices!B$2 -> 96800 | M59: =F59*Prices!C$2 -> 0 | N59: =G59*Prices!D$2 -> 0 | O59: =H59*Prices!E$2 -> 0 | P59: =I59*2000+J59*10000+K59*1800 -> 8100 | Q59: =D59*Prices!A$2 -> 66268.125 | R59: =L59+M59+N59+O59 -> 96800 | S59: =R59+Q59+P59 -> 171168.12 | T59: 58 | U59: Sold
A60: 59 | B60: 3.974 | C60: =B60*(25/100) -> 0.9935 | D60: =C60+B60 -> 4.9675 | E60: 0.46 | L60: =E60*Prices!B$2 -> 50600 | M60: =F60*Prices!C$2 -> 0 | N60: =G60*Prices!D$2 -> 0 | O60: =H60*Prices!E$2 -> 0 | P60: =I60*2000+J60*10000+K60*1800 -> 0 | Q60: =D60*Prices!A$2 -> 88669.875 | R60: =L60+M60+N60+O60 -> 50600 | S60: =R60+Q60+P60 -> 139269.88 | T60: 59 | U60: Sold
A61: 60 | B61: 13.774 | C61: =B61*(25/100) -> 3.4435 | D61: =C61+B61 -> 17.2175 | E61: 2.33 | I61: 5.85 | L61: =E61*Prices!B$2 -> 256300 | M61: =F61*Prices!C$2 -> 0 | N61: =G61*Prices!D$2 -> 0 | O61: =H61*Prices!E$2 -> 0 | P61: =I61*2000+J61*10000+K61*1800 -> 11700 | Q61: =D61*Prices!A$2 -> 307332.38 | R61: =L61+M61+N61+O61 -> 256300 | S61: =R61+Q61+P61 -> 575332.38 | T61: 60 | U61: Available | V61: A
A62: 61 | B62: 3.5 | C62: =B62*(25/100) -> 0.875 | D62: =C62+B62 -> 4.375 | E62: 0.6 | L62: =E62*Prices!B$2 -> 66000 | M62: =F62*Prices!C$2 -> 0 | N62: =G62*Prices!D$2 -> 0 | O62: =H62*Prices!E$2 -> 0 | P62: =I62*2000+J62*10000+K62*1800 -> 0 | Q62: =D62*Prices!A$2 -> 78093.75 | R62: =L62+M62+N62+O62 -> 66000 | S62: =R62+Q62+P62 -> 144093.75 | T62: 61 | U62: Sold
A63: 62 | B63: 8.794 | C63: =B63*(25/100) -> 2.1985 | D63: =C63+B63 -> 10.9925 | E63: 1.21 | K63: 4.02 | L63: =E63*Prices!B$2 -> 133100 | M63: =F63*Prices!C$2 -> 0 | N63: =G63*Prices!D$2 -> 0 | O63: =H63*Prices!E$2 -> 0 | P63: =I63*2000+J63*10000+K63*1800 -> 7236 | Q63: =D63*Prices!A$2 -> 196216.12 | R63: =L63+M63+N63+O63 -> 133100 | S63: =R63+Q63+P63 -> 336552.12 | T63: 62 | U63: Sold
A64: 63 | B64: 3.878 | C64: =B64*(25/100) -> 0.9695 | D64: =C64+B64 -> 4.8475 | F64: 0.51 | L64: =E64*Prices!B$2 -> 0 | M64: =F64*Prices!C$2 -> 81600 | N64: =G64*Prices!D$2 -> 0 | O64: =H64*Prices!E$2 -> 0 | P64: =I64*2000+J64*10000+K64*1800 -> 0 | Q64: =D64*Prices!A$2 -> 86527.875 | R64: =L64+M64+N64+O64 -> 81600 | S64: =R64+Q64+P64 -> 168127.88 | T64: 63 | U64: Available | V64: A
A65: 64 | B65: 4.696 | C65: =B65*(25/100) -> 1.174 | D65: =C65+B65 -> 5.87 | E65: 0.82 | L65: =E65*Prices!B$2 -> 90200 | M65: =F65*Prices!C$2 -> 0 | N65: =G65*Prices!D$2 -> 0 | O65: =H65*Prices!E$2 -> 0 | P65: =I65*2000+J65*10000+K65*1800 -> 0 | Q65: =D65*Prices!A$2 -> 104779.5 | R65: =L65+M65+N65+O65 -> 90200 | S65: =R65+Q65+P65 -> 194979.5 | T65: 64 | U65: Sold
A66: 65 | B66: 2.984 | C66: =B66*(25/100) -> 0.746 | D66: =C66+B66 -> 3.73 | F66: 1.23 | L66: =E66*Prices!B$2 -> 0 | M66: =F66*Prices!C$2 -> 196800 | N66: =G66*Prices!D$2 -> 0 | O66: =H66*Prices!E$2 -> 0 | P66: =I66*2000+J66*10000+K66*1800 -> 0 | Q66: =D66*Prices!A$2 -> 66580.5 | R66: =L66+M66+N66+O66 -> 196800 | S66: =R66+Q66+P66 -> 263380.5 | T66: 65 | U66: Available | V66: A
A67: 66 | B67: 4.258 | C67: =B67*(25/100) -> 1.0645 | D67: =C67+B67 -> 5.3225 | E67: 0.96 | L67: =E67*Prices!B$2 -> 105600 | M67: =F67*Prices!C$2 -> 0 | N67: =G67*Prices!D$2 -> 0 | O67: =H67*Prices!E$2 -> 0 | P67: =I67*2000+J67*10000+K67*1800 -> 0 | Q67: =D67*Prices!A$2 -> 95006.625 | R67: =L67+M67+N67+O67 -> 105600 | S67: =R67+Q67+P67 -> 200606.62 | T67: 66 | U67: Sold
A68: 67 | B68: 5.204 | C68: =B68*(25/100) -> 1.301 | D68: =C68+B68 -> 6.505 | E68: 1.03 | L68: =E68*Prices!B$2 -> 113300 | M68: =F68*Prices!C$2 -> 0 | N68: =G68*Prices!D$2 -> 0 | O68: =H68*Prices!E$2 -> 0 | P68: =I68*2000+J68*10000+K68*1800 -> 0 | Q68: =D68*Prices!A$2 -> 116114.25 | R68: =L68+M68+N68+O68 -> 113300 | S68: =R68+Q68+P68 -> 229414.25 | T68: 67 | U68: Sold
A69: 68 | B69: 2.318 | C69: =B69*(25/100) -> 0.5795 | D69: =C69+B69 -> 2.8975 | E69: 0.39 | I69: 1.32 | L69: =E69*Prices!B$2 -> 42900 | M69: =F69*Prices!C$2 -> 0 | N69: =G69*Prices!D$2 -> 0 | O69: =H69*Prices!E$2 -> 0 | P69: =I69*2000+J69*10000+K69*1800 -> 2640 | Q69: =D69*Prices!A$2 -> 51720.375 | R69: =L69+M69+N69+O69 -> 42900 | S69: =R69+Q69+P69 -> 97260.375 | T69: 68 | U69: Available | V69: A
A70: 69 | B70: 4.66 | C70: =B70*(25/100) -> 1.165 | D70: =C70+B70 -> 5.825 | E70: 0.85 | L70: =E70*Prices!B$2 -> 93500 | M70: =F70*Prices!C$2 -> 0 | N70: =G70*Prices!D$2 -> 0 | O70: =H70*Prices!E$2 -> 0 | P70: =I70*2000+J70*10000+K70*1800 -> 0 | Q70: =D70*Prices!A$2 -> 103976.25 | R70: =L70+M70+N70+O70 -> 93500 | S70: =R70+Q70+P70 -> 197476.25 | T70: 69 | U70: Available | V70: A
A71: 70 | B71: 3.618 | C71: =B71*(25/100) -> 0.9045 | D71: =C71+B71 -> 4.5225 | E71: 1.01 | K71: 2.05 | L71: =E71*Prices!B$2 -> 111100 | M71: =F71*Prices!C$2 -> 0 | N71: =G71*Prices!D$2 -> 0 | O71: =H71*Prices!E$2 -> 0 | P71: =I71*2000+J71*10000+K71*1800 -> 3690 | Q71: =D71*Prices!A$2 -> 80726.625 | R71: =L71+M71+N71+O71 -> 111100 | S71: =R71+Q71+P71 -> 195516.62 | T71: 70 | U71: Sold
A72: 71 | B72: 5.906 | C72: =B72*(25/100) -> 1.4765 | D72: =C72+B72 -> 7.3825 | E72: 0.35 | L72: =E72*Prices!B$2 -> 38500 | M72: =F72*Prices!C$2 -> 0 | N72: =G72*Prices!D$2 -> 0 | O72: =H72*Prices!E$2 -> 0 | P72: =I72*2000+J72*10000+K72*1800 -> 0 | Q72: =D72*Prices!A$2 -> 131777.62 | R72: =L72+M72+N72+O72 -> 38500 | S72: =R72+Q72+P72 -> 170277.62 | T72: 71 | U72: Available | V72: A
A73: 72 | B73: 4.562 | C73: =B73*(25/100) -> 1.1405 | D73: =C73+B73 -> 5.7025 | E73: 1.17 | K73: 6.12 | L73: =E73*Prices!B$2 -> 128700 | M73: =F73*Prices!C$2 -> 0 | N73: =G73*Prices!D$2 -> 0 | O73: =H73*Prices!E$2 -> 0 | P73: =I73*2000+J73*10000+K73*500 -> 3060 | Q73: =D73*Prices!A$2 -> 101789.62 | R73: =L73+M73+N73+O73 -> 128700 | S73: =R73+Q73+P73 -> 233549.62 | T73: 72 | U73: Available | V73: A
A74: 73 | B74: 6.608 | C74: =B74*(25/100) -> 1.652 | D74: =C74+B74 -> 8.26 | E74: 1.76 | L74: =E74*Prices!B$2 -> 193600 | M74: =F74*Prices!C$2 -> 0 | N74: =G74*Prices!D$2 -> 0 | O74: =H74*Prices!E$2 -> 0 | P74: =I74*2000+J74*10000+K74*1800 -> 0 | Q74: =D74*Prices!A$2 -> 147441 | R74: =L74+M74+N74+O74 -> 193600 | S74: =R74+Q74+P74 -> 341041 | T74: 73 | U74: Sold
A75: 74 | B75: 3.966 | C75: =B75*(25/100) -> 0.9915 | D75: =C75+B75 -> 4.9575 | E75: 0.92 | L75: =E75*Prices!B$2 -> 101200 | M75: =F75*Prices!C$2 -> 0 | N75: =G75*Prices!D$2 -> 0 | O75: =H75*Prices!E$2 -> 0 | P75: =I75*2000+J75*10000+K75*1800 -> 0 | Q75: =D75*Prices!A$2 -> 88491.375 | R75: =L75+M75+N75+O75 -> 101200 | S75: =R75+Q75+P75 -> 189691.38 | T75: 74 | U75: Available | V75: A
A76: 75 | B76: 4.556 | C76: =B76*(25/100) -> 1.139 | D76: =C76+B76 -> 5.695 | E76: 0.72 | L76: =E76*Prices!B$2 -> 79200 | M76: =F76*Prices!C$2 -> 0 | N76: =G76*Prices!D$2 -> 0 | O76: =H76*Prices!E$2 -> 0 | P76: =I76*2000+J76*10000+K76*1800 -> 0 | Q76: =D76*Prices!A$2 -> 101655.75 | R76: =L76+M76+N76+O76 -> 79200 | S76: =R76+Q76+P76 -> 180855.75 | T76: 75 | U76: Sold
A77: 76 | B77: 4.12 | C77: =B77*(25/100) -> 1.03 | D77: =C77+B77 -> 5.15 | E77: 0.66 | F77: 0.19 | L77: =E77*Prices!B$2 -> 72600 | M77: =F77*Prices!C$2 -> 30400 | N77: =G77*Prices!D$2 -> 0 | O77: =H77*Prices!E$2 -> 0 | P77: =I77*2000+J77*10000+K77*1800 -> 0 | Q77: =D77*Prices!A$2 -> 91927.5 | R77: =L77+M77+N77+O77 -> 103000 | S77: =R77+Q77+P77 -> 194927.5 | T77: 76 | U77: Available | V77: A
A78: 77 | B78: 12.49 | C78: =B78*(25/100) -> 3.1225 | D78: =C78+B78 -> 15.6125 | E78: 2.9 | J78: 10.9 | L78: =E78*Prices!B$2 -> 319000 | M78: =F78*Prices!C$2 -> 0 | N78: =G78*Prices!D$2 -> 0 | O78: =H78*Prices!E$2 -> 0 | P78: =I78*2000+J78*10000+K78*1800 -> 109000 | Q78: =D78*Prices!A$2 -> 278683.12 | R78: =L78+M78+N78+O78 -> 319000 | S78: =R78+Q78+P78 -> 706683.12 | T78: 77 | U78: Available | V78: A
A79: 78 | B79: 2.83 | C79: =B79*(25/100) -> 0.7075 | D79: =C79+B79 -> 3.5375 | F79: 1.5 | L79: =E79*Prices!B$2 -> 0 | M79: =F79*Prices!C$2 -> 240000 | N79: =G79*Prices!D$2 -> 0 | O79: =H79*Prices!E$2 -> 0 | P79: =I79*2000+J79*10000+K79*1800 -> 0 | Q79: =D79*Prices!A$2 -> 63144.375 | R79: =L79+M79+N79+O79 -> 240000 | S79: =R79+Q79+P79 -> 303144.38 | T79: 78 | U79: Sold
A80: 79 | B80: 3.426 | C80: =B80*(25/100) -> 0.8565 | D80: =C80+B80 -> 4.2825 | E80: 0.74 | K80: 2.08 | L80: =E80*Prices!B$2 -> 81400 | M80: =F80*Prices!C$2 -> 0 | N80: =G80*Prices!D$2 -> 0 | O80: =H80*Prices!E$2 -> 0 | P80: =I80*2000+J80*10000+K80*1800 -> 3744 | Q80: =D80*Prices!A$2 -> 76442.625 | R80: =L80+M80+N80+O80 -> 81400 | S80: =R80+Q80+P80 -> 161586.62 | T80: 79 | U80: Sold
A81: 80 | B81: 3.966 | C81: =B81*(25/100) -> 0.9915 | D81: =C81+B81 -> 4.9575 | E81: 0.97 | K81: 1.95 | L81: =E81*Prices!B$2 -> 106700 | M81: =F81*Prices!C$2 -> 0 | N81: =G81*Prices!D$2 -> 0 | O81: =H81*Prices!E$2 -> 0 | P81: =I81*2000+J81*10000+K81*1800 -> 3510 | Q81: =D81*Prices!A$2 -> 88491.375 | R81: =L81+M81+N81+O81 -> 106700 | S81: =R81+Q81+P81 -> 198701.38 | T81: 80 | U81: Available | V81: A
A82: 81 | B82: 3.978 | C82: =B82*(25/100) -> 0.9945 | D82: =C82+B82 -> 4.9725 | E82: 1.16 | L82: =E82*Prices!B$2 -> 127600 | M82: =F82*Prices!C$2 -> 0 | N82: =G82*Prices!D$2 -> 0 | O82: =H82*Prices!E$2 -> 0 | P82: =I82*2000+J82*10000+K82*1800 -> 0 | Q82: =D82*Prices!A$2 -> 88759.125 | R82: =L82+M82+N82+O82 -> 127600 | S82: =R82+Q82+P82 -> 216359.12 | T82: 81 | U82: Sold
A83: 82 | B83: 7.068 | C83: =B83*(25/100) -> 1.767 | D83: =C83+B83 -> 8.835 | F83: 1.83 | I83: 7.33 | L83: =E83*Prices!B$2 -> 0 | M83: =F83*Prices!C$2 -> 292800 | N83: =G83*Prices!D$2 -> 0 | O83: =H83*Prices!E$2 -> 0 | P83: =I83*2000+J83*10000+K83*1800 -> 14660 | Q83: =D83*Prices!A$2 -> 157704.75 | R83: =L83+M83+N83+O83 -> 292800 | S83: =R83+Q83+P83 -> 465164.75 | T83: 82 | U83: Available | V83: A
A84: 83 | B84: 3.754 | C84: =B84*(25/100) -> 0.9385 | D84: =C84+B84 -> 4.6925 | E84: 0.81 | K84: 4.92 | L84: =E84*Prices!B$2 -> 89100 | M84: =F84*Prices!C$2 -> 0 | N84: =G84*Prices!D$2 -> 0 | O84: =H84*Prices!E$2 -> 0 | P84: =I84*2000+J84*10000+K84*1800 -> 8856 | Q84: =D84*Prices!A$2 -> 83761.125 | R84: =L84+M84+N84+O84 -> 89100 | S84: =R84+Q84+P84 -> 181717.12 | T84: 83 | U84: Available | V84: A
A85: 84 | B85: 5.42 | C85: =B85*(25/100) -> 1.355 | D85: =C85+B85 -> 6.775 | E85: 1.64 | L85: =E85*Prices!B$2 -> 180400 | M85: =F85*Prices!C$2 -> 0 | N85: =G85*Prices!D$2 -> 0 | O85: =H85*Prices!E$2 -> 0 | P85: =I85*2000+J85*10000+K85*1800 -> 0 | Q85: =D85*Prices!A$2 -> 120933.75 | R85: =L85+M85+N85+O85 -> 180400 | S85: =R85+Q85+P85 -> 301333.75 | T85: 84 | U85: Available | V85: A
A86: 85 | B86: 6.718 | C86: =B86*(25/100) -> 1.6795 | D86: =C86+B86 -> 8.3975 | E86: 2.47 | J86: 2.89 | L86: =E86*Prices!B$2 -> 271700 | M86: =F86*Prices!C$2 -> 0 | N86: =G86*Prices!D$2 -> 0 | O86: =H86*Prices!E$2 -> 0 | P86: =I86*2000+J86*10000+K86*1800 -> 28900 | Q86: =D86*Prices!A$2 -> 149895.38 | R86: =L86+M86+N86+O86 -> 271700 | S86: =R86+Q86+P86 -> 450495.38 | T86: 85 | U86: Available | V86: A
A87: 86 | B87: 2.784 | C87: =B87*(25/100) -> 0.696 | D87: =C87+B87 -> 3.48 | E87: 0.48 | L87: =E87*Prices!B$2 -> 52800 | M87: =F87*Prices!C$2 -> 0 | N87: =G87*Prices!D$2 -> 0 | O87: =H87*Prices!E$2 -> 0 | P87: =I87*2000+J87*10000+K87*1800 -> 0 | Q87: =D87*Prices!A$2 -> 62118 | R87: =L87+M87+N87+O87 -> 52800 | S87: =R87+Q87+P87 -> 114918 | T87: 86 | U87: Sold
A88: 87 | B88: 4.128 | C88: =B88*(25/100) -> 1.032 | D88: =C88+B88 -> 5.16 | E88: 2.26 | L88: =E88*Prices!B$2 -> 248600 | M88: =F88*Prices!C$2 -> 0 | N88: =G88*Prices!D$2 -> 0 | O88: =H88*Prices!E$2 -> 0 | P88: =I88*2000+J88*10000+K88*1800 -> 0 | Q88: =D88*Prices!A$2 -> 92106 | R88: =L88+M88+N88+O88 -> 248600 | S88: =R88+Q88+P88 -> 340706 | T88: 87 | U88: Available | V88: A
A89: 88 | B89: 4.39 | C89: =B89*(25/100) -> 1.0975 | D89: =C89+B89 -> 5.4875 | F89: 1.17 | L89: =E89*Prices!B$2 -> 0 | M89: =F89*Prices!C$2 -> 187200 | N89: =G89*Prices!D$2 -> 0 | O89: =H89*Prices!E$2 -> 0 | P89: =I89*2000+J89*10000+K89*1800 -> 0 | Q89: =D89*Prices!A$2 -> 97951.875 | R89: =L89+M89+N89+O89 -> 187200 | S89: =R89+Q89+P89 -> 285151.88 | T89: 88 | U89: Available | V89: A
A90: 89 | B90: 6.526 | C90: =B90*(25/100) -> 1.6315 | D90: =C90+B90 -> 8.1575 | F90: 1.69 | I90: 4.43 | L90: =E90*Prices!B$2 -> 0 | M90: =F90*Prices!C$2 -> 270400 | N90: =G90*Prices!D$2 -> 0 | O90: =H90*Prices!E$2 -> 0 | P90: =I90*2000+J90*10000+K90*1800 -> 8860 | Q90: =D90*Prices!A$2 -> 145611.38 | R90: =L90+M90+N90+O90 -> 270400 | S90: =R90+Q90+P90 -> 424871.38 | T90: 89 | U90: Available | V90: A
A91: 90 | B91: 6.02 | C91: =B91*(25/100) -> 1.505 | D91: =C91+B91 -> 7.525 | E91: 0.92 | K91: 7.69 | L91: =E91*Prices!B$2 -> 101200 | M91: =F91*Prices!C$2 -> 0 | N91: =G91*Prices!D$2 -> 0 | O91: =H91*Prices!E$2 -> 0 | P91: =I91*2000+J91*10000+K91*1800 -> 13842 | Q91: =D91*Prices!A$2 -> 134321.25 | R91: =L91+M91+N91+O91 -> 101200 | S91: =R91+Q91+P91 -> 249363.25 | T91: 90 | U91: Available | V91: A
A92: 91 | B92: 4.866 | C92: =B92*(25/100) -> 1.2165 | D92: =C92+B92 -> 6.0825 | E92: 1.17 | L92: =E92*Prices!B$2 -> 128700 | M92: =F92*Prices!C$2 -> 0 | N92: =G92*Prices!D$2 -> 0 | O92: =H92*Prices!E$2 -> 0 | P92: =I92*2000+J92*10000+K92*1800 -> 0 | Q92: =D92*Prices!A$2 -> 108572.62 | R92: =L92+M92+N92+O92 -> 128700 | S92: =R92+Q92+P92 -> 237272.62 | T92: 91 | U92: Sold
A93: 92 | B93: 3.714 | C93: =B93*(25/100) -> 0.9285 | D93: =C93+B93 -> 4.6425 | E93: 1.28 | L93: =E93*Prices!B$2 -> 140800 | M93: =F93*Prices!C$2 -> 0 | N93: =G93*Prices!D$2 -> 0 | O93: =H93*Prices!E$2 -> 0 | P93: =I93*2000+J93*10000+K93*1800 -> 0 | Q93: =D93*Prices!A$2 -> 82868.625 | R93: =L93+M93+N93+O93 -> 140800 | S93: =R93+Q93+P93 -> 223668.62 | T93: 92 | U93: Sold
A94: 93 | B94: 8.21 | C94: =B94*(25/100) -> 2.0525 | D94: =C94+B94 -> 10.2625 | E94: 0.95 | L94: =E94*Prices!B$2 -> 104500 | M94: =F94*Prices!C$2 -> 0 | N94: =G94*Prices!D$2 -> 0 | O94: =H94*Prices!E$2 -> 0 | P94: =I94*2000+J94*10000+K94*1800 -> 0 | Q94: =D94*Prices!A$2 -> 183185.62 | R94: =L94+M94+N94+O94 -> 104500 | S94: =R94+Q94+P94 -> 287685.62 | T94: 93 | U94: Available | V94: A
A95: 94 | B95: 8.56 | C95: =B95*(25/100) -> 2.14 | D95: =C95+B95 -> 10.7 | E95: =1.43+0.38 -> 1.81 | K95: 13.12 | L95: =E95*Prices!B$2 -> 199100 | M95: =F95*Prices!C$2 -> 0 | N95: =G95*Prices!D$2 -> 0 | O95: =H95*Prices!E$2 -> 0 | P95: =I95*2000+J95*10000+K95*500 -> 6560 | Q95: =D95*Prices!A$2 -> 190995 | R95: =L95+M95+N95+O95 -> 199100 | S95: =R95+Q95+P95 -> 396655 | T95: 94 | U95: Available | V95: A
A96: 95 | B96: 10.478 | C96: =B96*(25/100) -> 2.6195 | D96: =C96+B96 -> 13.0975 | E96: 1.99 | K96: 5.4 | L96: =E96*Prices!B$2 -> 218900 | M96: =F96*Prices!C$2 -> 0 | N96: =G96*Prices!D$2 -> 0 | O96: =H96*Prices!E$2 -> 0 | P96: =I96*2000+J96*10000+K96*1800 -> 9720 | Q96: =D96*Prices!A$2 -> 233790.38 | R96: =L96+M96+N96+O96 -> 218900 | S96: =R96+Q96+P96 -> 462410.38 | T96: 95 | U96: Available | V96: A
A97: 96 | B97: 3.51 | C97: =B97*(25/100) -> 0.8775 | D97: =C97+B97 -> 4.3875 | E97: 0.8 | L97: =E97*Prices!B$2 -> 88000 | M97: =F97*Prices!C$2 -> 0 | N97: =G97*Prices!D$2 -> 0 | O97: =H97*Prices!E$2 -> 0 | P97: =I97*2000+J97*10000+K97*1800 -> 0 | Q97: =D97*Prices!A$2 -> 78316.875 | R97: =L97+M97+N97+O97 -> 88000 | S97: =R97+Q97+P97 -> 166316.88 | T97: 96 | U97: Sold
L98: =E98*Prices!B$2 -> 0 | M98: =F98*Prices!C$2 -> 0 | N98: =G98*Prices!D$2 -> 0 | O98: =H98*Prices!E$2 -> 0 | P98: =I98*2000+J98*10000+K98*1800 -> 0 | Q98: =D98*Prices!A$2 -> 0
L99: =E99*Prices!B$2 -> 0 | M99: =F99*Prices!C$2 -> 0 | N99: =G99*Prices!D$2 -> 0 | O99: =H99*Prices!E$2 -> 0 | P99: =I99*2000+J99*10000+K99*1800 -> 0 | Q99: =D99*Prices!A$2 -> 0
A100: 99 | B100: 1.606 | C100: =B100*(25/100) -> 0.4015 | D100: =C100+B100 -> 2.0075 | E100: 0.32 | L100: =E100*Prices!B$2 -> 35200 | M100: =F100*Prices!C$2 -> 0 | N100: =G100*Prices!D$2 -> 0 | O100: =H100*Prices!E$2 -> 0 | P100: =I100*2000+J100*10000+K100*1800 -> 0 | Q100: =D100*Prices!A$2 -> 35833.875 | R100: =L100+M100+N100+O100 -> 35200 | S100: =R100+Q100+P100 -> 71033.875 | T100: 99 | U100: Sold
...

Sheet Locket
A1: Sn | B1: Net Weight | C1: Wstg + MC | D1: Gross Weight | E1: Dmd <0.06 | F1: Dmd < 0.12 | G1: Dmd <0.17 | H1: Dmd Big | I1: Ruby | J1: Emreld | K1: Muga | L1: Dmd Price | M1: Dmd Price | N1: Dmd Price | O1: Dmd Price | P1: Stn Price | Q1: Gold Price | R1: Ttl dmd Price | S1: Total Price | T1: Sn
A2: 1 | B2: 3.168 | C2: =B2*(25/100) -> 0.792 | D2: =C2+B2 -> 3.96 | E2: 0.56 | L2: =E2*Prices!B$2 -> 61600 | M2: =F2*Prices!C$2 -> 0 | N2: =G2*Prices!D$2 -> 0 | O2: =H2*Prices!E$2 -> 0 | P2: =I2*2000+J2*10000+K2*1800 -> 0 | Q2: =D2*Prices!A$2 -> 70686 | R2: =L2+M2+N2+O2 -> 61600 | S2: =R2+Q2+P2 -> 132286 | T2: 1 | U2: Sold
A3: 2 | B3: 3.718 | C3: =B3*(25/100) -> 0.9295 | D3: =C3+B3 -> 4.6475 | E3: 1.36 | L3: =E3*Prices!B$2 -> 149600 | M3: =F3*Prices!C$2 -> 0 | N3: =G3*Prices!D$2 -> 0 | O3: =H3*Prices!E$2 -> 0 | P3: =I3*2000+J3*10000+K3*1800 -> 0 | Q3: =D3*Prices!A$2 -> 82957.875 | R3: =L3+M3+N3+O3 -> 149600 | S3: =R3+Q3+P3 -> 232557.88 | T3: 2 | U3: Available | V3: A
A4: 3 | B4: 2.968 | C4: =B4*(25/100) -> 0.742 | D4: =C4+B4 -> 3.71 | F4: 1.04 | K4: 2.52 | L4: =E4*Prices!B$2 -> 0 | M4: =F4*Prices!C$2 -> 166400 | N4: =G4*Prices!D$2 -> 0 | O4: =H4*Prices!E$2 -> 0 | P4: =I4*2000+J4*10000+K4*500 -> 1260 | Q4: =D4*Prices!A$2 -> 66223.5 | R4: =L4+M4+N4+O4 -> 166400 | S4: =R4+Q4+P4 -> 233883.5 | T4: 3 | U4: Available
A5: 4 | B5: 5.27 | C5: =B5*(25/100) -> 1.3175 | D5: =C5+B5 -> 6.5875 | E5: 0.39 | L5: =E5*Prices!B$2 -> 42900 | M5: =F5*Prices!C$2 -> 0 | N5: =G5*Prices!D$2 -> 0 | O5: =H5*Prices!E$2 -> 0 | P5: =I5*2000+J5*10000+K5*1800 -> 0 | Q5: =D5*Prices!A$2 -> 117586.88 | R5: =L5+M5+N5+O5 -> 42900 | S5: =R5+Q5+P5 -> 160486.88 | T5: 4 | U5: Available | V5: A
A6: 5 | B6: 4.32 | C6: =B6*(25/100) -> 1.08 | D6: =C6+B6 -> 5.4 | E6: 1.31 | L6: =E6*Prices!B$2 -> 144100 | M6: =F6*Prices!C$2 -> 0 | N6: =G6*Prices!D$2 -> 0 | O6: =H6*Prices!E$2 -> 0 | P6: =I6*2000+J6*10000+K6*1800 -> 0 | Q6: =D6*Prices!A$2 -> 96390 | R6: =L6+M6+N6+O6 -> 144100 | S6: =R6+Q6+P6 -> 240490 | T6: 5 | U6: Sold
A7: 6 | B7: 2.21 | C7: =B7*(25/100) -> 0.5525 | D7: =C7+B7 -> 2.7625 | E7: 0.61 | L7: =E7*Prices!B$2 -> 67100 | M7: =F7*Prices!C$2 -> 0 | N7: =G7*Prices!D$2 -> 0 | O7: =H7*Prices!E$2 -> 0 | P7: =I7*2000+J7*10000+K7*1800 -> 0 | Q7: =D7*Prices!A$2 -> 49310.625 | R7: =L7+M7+N7+O7 -> 67100 | S7: =R7+Q7+P7 -> 116410.62 | T7: 6 | U7: Return
A8: 7 | B8: 4.28 | C8: =B8*(25/100) -> 1.07 | D8: =C8+B8 -> 5.35 | G8: 1.34 | K8: 2.54 | L8: =E8*Prices!B$2 -> 0 | M8: =F8*Prices!C$2 -> 0 | N8: =G8*Prices!D$2 -> 261300 | O8: =H8*Prices!E$2 -> 0 | P8: =I8*2000+J8*10000+K8*500 -> 1270 | Q8: =D8*Prices!A$2 -> 95497.5 | R8: =L8+M8+N8+O8 -> 261300 | S8: =R8+Q8+P8 -> 358067.5 | T8: 7 | U8: Available | V8: A
A9: 8 | B9: 1.98 | C9: =B9*(25/100) -> 0.495 | D9: =C9+B9 -> 2.475 | E9: 0.31 | K9: 2.17 | L9: =E9*Prices!B$2 -> 34100 | M9: =F9*Prices!C$2 -> 0 | N9: =G9*Prices!D$2 -> 0 | O9: =H9*Prices!E$2 -> 0 | P9: =I9*2000+J9*10000+K9*500 -> 1085 | Q9: =D9*Prices!A$2 -> 44178.75 | R9: =L9+M9+N9+O9 -> 34100 | S9: =R9+Q9+P9 -> 79363.75 | T9: 8 | U9: Available | V9: A
A10: 9 | B10: 5.49 | C10: =B10*(25/100) -> 1.3725 | D10: =C10+B10 -> 6.8625 | E10: 0.59 | L10: =E10*Prices!B$2 -> 64900 | M10: =F10*Prices!C$2 -> 0 | N10: =G10*Prices!D$2 -> 0 | O10: =H10*Prices!E$2 -> 0 | P10: =I10*2000+J10*10000+K10*1800 -> 0 | Q10: =D10*Prices!A$2 -> 122495.62 | R10: =L10+M10+N10+O10 -> 64900 | S10: =R10+Q10+P10 -> 187395.62 | T10: 9 | U10: Sold
A11: 10 | B11: 8.81 | C11: =B11*(25/100) -> 2.2025 | D11: =C11+B11 -> 11.0125 | E11: 2.23 | L11: =E11*Prices!B$2 -> 245300 | M11: =F11*Prices!C$2 -> 0 | N11: =G11*Prices!D$2 -> 0 | O11: =H11*Prices!E$2 -> 0 | P11: =I11*2000+J11*10000+K11*1800 -> 0 | Q11: =D11*Prices!A$2 -> 196573.12 | R11: =L11+M11+N11+O11 -> 245300 | S11: =R11+Q11+P11 -> 441873.12 | T11: 10 | U11: Available | V11: A
A12: 11 | B12: 1.784 | C12: =B12*(25/100) -> 0.446 | D12: =C12+B12 -> 2.23 | E12: 0.31 | L12: =E12*Prices!B$2 -> 34100 | M12: =F12*Prices!C$2 -> 0 | N12: =G12*Prices!D$2 -> 0 | O12: =H12*Prices!E$2 -> 0 | P12: =I12*2000+J12*10000+K12*1800 -> 0 | Q12: =D12*Prices!A$2 -> 39805.5 | R12: =L12+M12+N12+O12 -> 34100 | S12: =R12+Q12+P12 -> 73905.5 | T12: 11 | U12: Sold
A13: 12 | B13: 2.516 | C13: =B13*(25/100) -> 0.629 | D13: =C13+B13 -> 3.145 | E13: 1.22 | L13: =E13*Prices!B$2 -> 134200 | M13: =F13*Prices!C$2 -> 0 | N13: =G13*Prices!D$2 -> 0 | O13: =H13*Prices!E$2 -> 0 | P13: =I13*2000+J13*10000+K13*1800 -> 0 | Q13: =D13*Prices!A$2 -> 56138.25 | R13: =L13+M13+N13+O13 -> 134200 | S13: =R13+Q13+P13 -> 190338.25 | T13: 12 | U13: Available | V13: A
A14: 13 | B14: 2.76 | C14: =B14*(25/100) -> 0.69 | D14: =C14+B14 -> 3.45 | E14: 0.25 | L14: =E14*Prices!B$2 -> 27500 | M14: =F14*Prices!C$2 -> 0 | N14: =G14*Prices!D$2 -> 0 | O14: =H14*Prices!E$2 -> 0 | P14: =I14*2000+J14*10000+K14*1800 -> 0 | Q14: =D14*Prices!A$2 -> 61582.5 | R14: =L14+M14+N14+O14 -> 27500 | S14: =R14+Q14+P14 -> 89082.5 | T14: 13 | U14: Available | V14: A
A15: 14 | B15: 7.68 | C15: =B15*(25/100) -> 1.92 | D15: =C15+B15 -> 9.6 | E15: 1.23 | L15: =E15*Prices!B$2 -> 135300 | M15: =F15*Prices!C$2 -> 0 | N15: =G15*Prices!D$2 -> 0 | O15: =H15*Prices!E$2 -> 0 | P15: =I15*2000+J15*10000+K15*1800 -> 0 | Q15: =D15*Prices!A$2 -> 171360 | R15: =L15+M15+N15+O15 -> 135300 | S15: =R15+Q15+P15 -> 306660 | T15: 14 | U15: Return
A16: 15 | B16: 1.62 | C16: =B16*(25/100) -> 0.405 | D16: =C16+B16 -> 2.025 | E16: 0.36 | L16: =E16*Prices!B$2 -> 39600 | M16: =F16*Prices!C$2 -> 0 | N16: =G16*Prices!D$2 -> 0 | O16: =H16*Prices!E$2 -> 0 | P16: =I16*2000+J16*10000+K16*1800 -> 0 | Q16: =D16*Prices!A$2 -> 36146.25 | R16: =L16+M16+N16+O16 -> 39600 | S16: =R16+Q16+P16 -> 75746.25 | T16: 15 | U16: Sold
A17: 16 | B17: 5.232 | C17: =B17*(25/100) -> 1.308 | D17: =C17+B17 -> 6.54 | E17: 0.24 | L17: =E17*Prices!B$2 -> 26400 | M17: =F17*Prices!C$2 -> 0 | N17: =G17*Prices!D$2 -> 0 | O17: =H17*Prices!E$2 -> 0 | P17: =I17*2000+J17*10000+K17*1800 -> 0 | Q17: =D17*Prices!A$2 -> 116739 | R17: =L17+M17+N17+O17 -> 26400 | S17: =R17+Q17+P17 -> 143139 | T17: 16 | U17: Available | V17: A
A18: 17 | B18: 2.28 | C18: =B18*(25/100) -> 0.57 | D18: =C18+B18 -> 2.85 | E18: 0.57 | L18: =E18*Prices!B$2 -> 62700 | M18: =F18*Prices!C$2 -> 0 | N18: =G18*Prices!D$2 -> 0 | O18: =H18*Prices!E$2 -> 0 | P18: =I18*2000+J18*10000+K18*1800 -> 0 | Q18: =D18*Prices!A$2 -> 50872.5 | R18: =L18+M18+N18+O18 -> 62700 | S18: =R18+Q18+P18 -> 113572.5 | T18: 17 | U18: Sold
A19: 18 | B19: 2.27 | C19: =B19*(25/100) -> 0.5675 | D19: =C19+B19 -> 2.8375 | E19: 0.46 | K19: 3.21 | L19: =E19*Prices!B$2 -> 50600 | M19: =F19*Prices!C$2 -> 0 | N19: =G19*Prices!D$2 -> 0 | O19: =H19*Prices!E$2 -> 0 | P19: =I19*2000+J19*10000+K19*1800 -> 5778 | Q19: =D19*Prices!A$2 -> 50649.375 | R19: =L19+M19+N19+O19 -> 50600 | S19: =R19+Q19+P19 -> 107027.38 | T19: 18 | U19: Available | V19: A
A20: 19 | B20: 2.38 | C20: =B20*(25/100) -> 0.595 | D20: =C20+B20 -> 2.975 | E20: 0.35 | K20: 4.83 | L20: =E20*Prices!B$2 -> 38500 | M20: =F20*Prices!C$2 -> 0 | N20: =G20*Prices!D$2 -> 0 | O20: =H20*Prices!E$2 -> 0 | P20: =I20*2000+J20*10000+K20*1800 -> 8694 | Q20: =D20*Prices!A$2 -> 53103.75 | R20: =L20+M20+N20+O20 -> 38500 | S20: =R20+Q20+P20 -> 100297.75 | T20: 19 | U20: Available | V20: A
A21: 20 | B21: 12.63 | C21: =B21*(25/100) -> 3.1575 | D21: =C21+B21 -> 15.7875 | E21: 2.55 | L21: =E21*Prices!B$2 -> 280500 | M21: =F21*Prices!C$2 -> 0 | N21: =G21*Prices!D$2 -> 0 | O21: =H21*Prices!E$2 -> 0 | P21: =I21*2000+J21*10000+K21*1800 -> 0 | Q21: =D21*Prices!A$2 -> 281806.88 | R21: =L21+M21+N21+O21 -> 280500 | S21: =R21+Q21+P21 -> 562306.88 | T21: 20 | U21: Sold
A22: 21 | B22: 14.55 | C22: =B22*(25/100) -> 3.6375 | D22: =C22+B22 -> 18.1875 | E22: =2.6+0.55 -> 3.15 | K22: 3.85 | L22: =E22*Prices!B$2 -> 346500 | M22: =F22*Prices!C$2 -> 0 | N22: =G22*Prices!D$2 -> 0 | O22: =H22*Prices!E$2 -> 0 | P22: =I22*2000+J22*10000+K22*500 -> 1925 | Q22: =D22*Prices!A$2 -> 324646.88 | R22: =L22+M22+N22+O22 -> 346500 | S22: =R22+Q22+P22 -> 673071.88 | T22: 21 | U22: Available | V22: A
A23: 22 | B23: 6.716 | C23: =B23*(25/100) -> 1.679 | D23: =C23+B23 -> 8.395 | E23: 1.36 | K23: 1.56 | L23: =E23*Prices!B$2 -> 149600 | M23: =F23*Prices!C$2 -> 0 | N23: =G23*Prices!D$2 -> 0 | O23: =H23*Prices!E$2 -> 0 | P23: =I23*2000+J23*10000+K23*1800 -> 2808 | Q23: =D23*Prices!A$2 -> 149850.75 | R23: =L23+M23+N23+O23 -> 149600 | S23: =R23+Q23+P23 -> 302258.75 | T23: 22 | U23: Available | V23: A
A24: 23 | B24: 5.14 | C24: =B24*(25/100) -> 1.285 | D24: =C24+B24 -> 6.425 | E24: =0.86+0.34 -> 1.2 | L24: =E24*Prices!B$2 -> 132000 | M24: =F24*Prices!C$2 -> 0 | N24: =G24*Prices!D$2 -> 0 | O24: =H24*Prices!E$2 -> 0 | P24: =I24*2000+J24*10000+K24*1800 -> 0 | Q24: =D24*Prices!A$2 -> 114686.25 | R24: =L24+M24+N24+O24 -> 132000 | S24: =R24+Q24+P24 -> 246686.25 | T24: 23 | U24: Available | V24: A
A25: 24 | B25: 3.03 | C25: =B25*(25/100) -> 0.7575 | D25: =C25+B25 -> 3.7875 | E25: 0.53 | L25: =E25*Prices!B$2 -> 58300 | M25: =F25*Prices!C$2 -> 0 | N25: =G25*Prices!D$2 -> 0 | O25: =H25*Prices!E$2 -> 0 | P25: =I25*2000+J25*10000+K25*1800 -> 0 | Q25: =D25*Prices!A$2 -> 67606.875 | R25: =L25+M25+N25+O25 -> 58300 | S25: =R25+Q25+P25 -> 125906.88 | T25: 24 | U25: Sold
A26: 25 | B26: 1.23 | C26: =B26*(25/100) -> 0.3075 | D26: =C26+B26 -> 1.5375 | E26: 0.2 | L26: =E26*Prices!B$2 -> 22000 | M26: =F26*Prices!C$2 -> 0 | N26: =G26*Prices!D$2 -> 0 | O26: =H26*Prices!E$2 -> 0 | P26: =I26*2000+J26*10000+K26*1800 -> 0 | Q26: =D26*Prices!A$2 -> 27444.375 | R26: =L26+M26+N26+O26 -> 22000 | S26: =R26+Q26+P26 -> 49444.375 | T26: 25 | U26: Sold
A27: 26 | B27: 2.03 | C27: =B27*(25/100) -> 0.5075 | D27: =C27+B27 -> 2.5375 | E27: 0.83 | L27: =E27*Prices!B$2 -> 91300 | M27: =F27*Prices!C$2 -> 0 | N27: =G27*Prices!D$2 -> 0 | O27: =H27*Prices!E$2 -> 0 | P27: =I27*2000+J27*10000+K27*1800 -> 0 | Q27: =D27*Prices!A$2 -> 45294.375 | R27: =L27+M27+N27+O27 -> 91300 | S27: =R27+Q27+P27 -> 136594.38 | T27: 26 | U27: Available | V27: A
A28: 27 | B28: 2.64 | C28: =B28*(25/100) -> 0.66 | D28: =C28+B28 -> 3.3 | E28: 0.28 | L28: =E28*Prices!B$2 -> 30800 | M28: =F28*Prices!C$2 -> 0 | N28: =G28*Prices!D$2 -> 0 | O28: =H28*Prices!E$2 -> 0 | P28: =I28*2000+J28*10000+K28*1800 -> 0 | Q28: =D28*Prices!A$2 -> 58905 | R28: =L28+M28+N28+O28 -> 30800 | S28: =R28+Q28+P28 -> 89705 | T28: 27 | U28: Sold
A29: 28 | B29: 2.194 | C29: =B29*(25/100) -> 0.5485 | D29: =C29+B29 -> 2.7425 | E29: 0.56 | I29: 0.8 | L29: =E29*Prices!B$2 -> 61600 | M29: =F29*Prices!C$2 -> 0 | N29: =G29*Prices!D$2 -> 0 | O29: =H29*Prices!E$2 -> 0 | P29: =I29*2000+J29*10000+K29*1800 -> 1600 | Q29: =D29*Prices!A$2 -> 48953.625 | R29: =L29+M29+N29+O29 -> 61600 | S29: =R29+Q29+P29 -> 112153.62 | T29: 28 | U29: Available | V29: A
A30: 29 | B30: 6.23 | C30: =B30*(25/100) -> 1.5575 | D30: =C30+B30 -> 7.7875 | E30: 1 | K30: 8.25 | L30: =E30*Prices!B$2 -> 110000 | M30: =F30*Prices!C$2 -> 0 | N30: =G30*Prices!D$2 -> 0 | O30: =H30*Prices!E$2 -> 0 | P30: =I30*2000+J30*10000+K30*1800 -> 14850 | Q30: =D30*Prices!A$2 -> 139006.88 | R30: =L30+M30+N30+O30 -> 110000 | S30: =R30+Q30+P30 -> 263856.88 | T30: 29 | U30: Sold
A31: 30 | B31: 10.906 | C31: =B31*(25/100) -> 2.7265 | D31: =C31+B31 -> 13.6325 | E31: 2.63 | K31: 20.29 | L31: =E31*Prices!B$2 -> 289300 | M31: =F31*Prices!C$2 -> 0 | N31: =G31*Prices!D$2 -> 0 | O31: =H31*Prices!E$2 -> 0 | P31: =I31*2000+J31*10000+K31*1800 -> 36522 | Q31: =D31*Prices!A$2 -> 243340.12 | R31: =L31+M31+N31+O31 -> 289300 | S31: =R31+Q31+P31 -> 569162.12 | T31: 30 | U31: Sold
A32: 31 | B32: 10.96 | C32: =B32*(25/100) -> 2.74 | D32: =C32+B32 -> 13.7 | E32: 1 | L32: =E32*Prices!B$2 -> 110000 | M32: =F32*Prices!C$2 -> 0 | N32: =G32*Prices!D$2 -> 0 | O32: =H32*Prices!E$2 -> 0 | P32: =I32*2000+J32*10000+K32*1800 -> 0 | Q32: =D32*Prices!A$2 -> 244545 | R32: =L32+M32+N32+O32 -> 110000 | S32: =R32+Q32+P32 -> 354545 | T32: 31 | U32: Sold
A33: 32 | B33: 5.49 | C33: =B33*(25/100) -> 1.3725 | D33: =C33+B33 -> 6.8625 | E33: 1.85 | K33: 4 | L33: =E33*Prices!B$2 -> 203500 | M33: =F33*Prices!C$2 -> 0 | N33: =G33*Prices!D$2 -> 0 | O33: =H33*Prices!E$2 -> 0 | P33: =I33*2000+J33*10000+K33*1800 -> 7200 | Q33: =D33*Prices!A$2 -> 122495.62 | R33: =L33+M33+N33+O33 -> 203500 | S33: =R33+Q33+P33 -> 333195.62 | T33: 32 | U33: Available | V33: A
A34: 33 | B34: 11.73 | C34: =B34*(25/100) -> 2.9325 | D34: =C34+B34 -> 14.6625 | E34: 1.54 | L34: =E34*Prices!B$2 -> 169400 | M34: =F34*Prices!C$2 -> 0 | N34: =G34*Prices!D$2 -> 0 | O34: =H34*Prices!E$2 -> 0 | P34: =I34*2000+J34*10000+K34*1800 -> 0 | Q34: =D34*Prices!A$2 -> 261725.62 | R34: =L34+M34+N34+O34 -> 169400 | S34: =R34+Q34+P34 -> 431125.62 | T34: 33 | U34: Available | V34: A
A35: 34 | B35: 17.217 | C35: =B35*(25/100) -> 4.30425 | D35: =C35+B35 -> 21.52125 | E35: 3.54 | K35: 11.27 | L35: =E35*Prices!B$2 -> 389400 | M35: =F35*Prices!C$2 -> 0 | N35: =G35*Prices!D$2 -> 0 | O35: =H35*Prices!E$2 -> 0 | P35: =I35*2000+J35*10000+K35*500 -> 5635 | Q35: =D35*Prices!A$2 -> 384154.31 | R35: =L35+M35+N35+O35 -> 389400 | S35: =R35+Q35+P35 -> 779189.31 | T35: 34 | U35: Available | V35: A
A36: 35 | B36: 3.464 | C36: =B36*(25/100) -> 0.866 | D36: =C36+B36 -> 4.33 | E36: 1.23 | K36: 1.4 | L36: =E36*Prices!B$2 -> 135300 | M36: =F36*Prices!C$2 -> 0 | N36: =G36*Prices!D$2 -> 0 | O36: =H36*Prices!E$2 -> 0 | P36: =I36*2000+J36*10000+K36*1800 -> 2520 | Q36: =D36*Prices!A$2 -> 77290.5 | R36: =L36+M36+N36+O36 -> 135300 | S36: =R36+Q36+P36 -> 215110.5 | T36: 35 | U36: Available | V36: A
A37: 36 | B37: 5.46 | C37: =B37*(25/100) -> 1.365 | D37: =C37+B37 -> 6.825 | E37: 1.57 | K37: 2.38 | L37: =E37*Prices!B$2 -> 172700 | M37: =F37*Prices!C$2 -> 0 | N37: =G37*Prices!D$2 -> 0 | O37: =H37*Prices!E$2 -> 0 | P37: =I37*2000+J37*10000+K37*500 -> 1190 | Q37: =D37*Prices!A$2 -> 121826.25 | R37: =L37+M37+N37+O37 -> 172700 | S37: =R37+Q37+P37 -> 295716.25 | T37: 36 | U37: Available | V37: A
A38: 37 | B38: 3.198 | C38: =B38*(25/100) -> 0.7995 | D38: =C38+B38 -> 3.9975 | E38: 0.58 | K38: 3.23 | L38: =E38*Prices!B$2 -> 63800 | M38: =F38*Prices!C$2 -> 0 | N38: =G38*Prices!D$2 -> 0 | O38: =H38*Prices!E$2 -> 0 | P38: =I38*2000+J38*10000+K38*500 -> 1615 | Q38: =D38*Prices!A$2 -> 71355.375 | R38: =L38+M38+N38+O38 -> 63800 | S38: =R38+Q38+P38 -> 136770.38 | T38: 37 | U38: Available | V38: A
A39: 38 | B39: 7.4 | C39: =B39*(25/100) -> 1.85 | D39: =C39+B39 -> 9.25 | E39: =1.52+0.39 -> 1.91 | K39: 1.84 | L39: =E39*Prices!B$2 -> 210100 | M39: =F39*Prices!C$2 -> 0 | N39: =G39*Prices!D$2 -> 0 | O39: =H39*Prices!E$2 -> 0 | P39: =I39*2000+J39*10000+K39*1800 -> 3312 | Q39: =D39*Prices!A$2 -> 165112.5 | R39: =L39+M39+N39+O39 -> 210100 | S39: =R39+Q39+P39 -> 378524.5 | T39: 38 | U39: Return
A40: 39 | B40: 3.45 | C40: =B40*(25/100) -> 0.8625 | D40: =C40+B40 -> 4.3125 | E40: 0.93 | L40: =E40*Prices!B$2 -> 102300 | M40: =F40*Prices!C$2 -> 0 | N40: =G40*Prices!D$2 -> 0 | O40: =H40*Prices!E$2 -> 0 | P40: =I40*2000+J40*10000+K40*1800 -> 0 | Q40: =D40*Prices!A$2 -> 76978.125 | R40: =L40+M40+N40+O40 -> 102300 | S40: =R40+Q40+P40 -> 179278.12 | T40: 39 | U40: Return
A41: 40 | B41: 2.81 | C41: =B41*(25/100) -> 0.7025 | D41: =C41+B41 -> 3.5125 | E41: 0.18 | K41: 1.82 | L41: =E41*Prices!B$2 -> 19800 | M41: =F41*Prices!C$2 -> 0 | N41: =G41*Prices!D$2 -> 0 | O41: =H41*Prices!E$2 -> 0 | P41: =I41*2000+J41*10000+K41*500 -> 910 | Q41: =D41*Prices!A$2 -> 62698.125 | R41: =L41+M41+N41+O41 -> 19800 | S41: =R41+Q41+P41 -> 83408.125 | T41: 40 | U41: Available | V41: A
A42: 41 | B42: 2.654 | C42: =B42*(25/100) -> 0.6635 | D42: =C42+B42 -> 3.3175 | E42: 0.98 | L42: =E42*Prices!B$2 -> 107800 | M42: =F42*Prices!C$2 -> 0 | N42: =G42*Prices!D$2 -> 0 | O42: =H42*Prices!E$2 -> 0 | P42: =I42*2000+J42*10000+K42*1800 -> 0 | Q42: =D42*Prices!A$2 -> 59217.375 | R42: =L42+M42+N42+O42 -> 107800 | S42: =R42+Q42+P42 -> 167017.38 | T42: 41 | U42: Available | V42: A
A43: 42 | B43: 1.258 | C43: =B43*(25/100) -> 0.3145 | D43: =C43+B43 -> 1.5725 | E43: 0.59 | F43: 0.12 | L43: =E43*Prices!B$2 -> 64900 | M43: =F43*Prices!C$2 -> 19200 | N43: =G43*Prices!D$2 -> 0 | O43: =H43*Prices!E$2 -> 0 | P43: =I43*2000+J43*10000+K43*1800 -> 0 | Q43: =D43*Prices!A$2 -> 28069.125 | R43: =L43+M43+N43+O43 -> 84100 | S43: =R43+Q43+P43 -> 112169.12 | T43: 42 | U43: Sold
A44: 45 | B44: 6.582 | C44: =B44*(25/100) -> 1.6455 | D44: =C44+B44 -> 8.2275 | E44: 1.26 | K44: 4.88 | L44: =E44*Prices!B$2 -> 138600 | M44: =F44*Prices!C$2 -> 0 | N44: =G44*Prices!D$2 -> 0 | O44: =H44*Prices!E$2 -> 0 | P44: =I44*2000+J44*10000+K44*1800 -> 8784 | Q44: =D44*Prices!A$2 -> 146860.88 | R44: =L44+M44+N44+O44 -> 138600 | S44: =R44+Q44+P44 -> 294244.88 | T44: 45 | U44: Available | V44: A
A45: 46 | B45: 4.674 | C45: =B45*(25/100) -> 1.1685 | D45: =C45+B45 -> 5.8425 | E45: =0.63+1.8 -> 2.43 | L45: =E45*Prices!B$2 -> 267300 | M45: =F45*Prices!C$2 -> 0 | N45: =G45*Prices!D$2 -> 0 | O45: =H45*Prices!E$2 -> 0 | P45: =I45*2000+J45*10000+K45*1800 -> 0 | Q45: =D45*Prices!A$2 -> 104288.62 | R45: =L45+M45+N45+O45 -> 267300 | S45: =R45+Q45+P45 -> 371588.62 | T45: 46 | U45: Sold
A46: 47 | B46: 15.326 | C46: =B46*(25/100) -> 3.8315 | D46: =C46+B46 -> 19.1575 | E46: 3.62 | K46: 19.2 | L46: =E46*Prices!B$2 -> 398200 | M46: =F46*Prices!C$2 -> 0 | N46: =G46*Prices!D$2 -> 0 | O46: =H46*Prices!E$2 -> 0 | P46: =I46*2000+J46*10000+K46*1800 -> 34560 | Q46: =D46*Prices!A$2 -> 341961.38 | R46: =L46+M46+N46+O46 -> 398200 | S46: =R46+Q46+P46 -> 774721.38 | T46: 47 | U46: Sold
A47: 48 | B47: 8.882 | C47: =B47*(25/100) -> 2.2205 | D47: =C47+B47 -> 11.1025 | E47: 2.34 | L47: =E47*Prices!B$2 -> 257400 | M47: =F47*Prices!C$2 -> 0 | N47: =G47*Prices!D$2 -> 0 | O47: =H47*Prices!E$2 -> 0 | P47: =I47*2000+J47*10000+K47*1800 -> 0 | Q47: =D47*Prices!A$2 -> 198179.62 | R47: =L47+M47+N47+O47 -> 257400 | S47: =R47+Q47+P47 -> 455579.62 | T47: 48 | U47: Sold
A48: 49 | B48: 6.1 | C48: =B48*(25/100) -> 1.525 | D48: =C48+B48 -> 7.625 | E48: 1.265 | L48: =E48*Prices!B$2 -> 139150 | M48: =F48*Prices!C$2 -> 0 | N48: =G48*Prices!D$2 -> 0 | O48: =H48*Prices!E$2 -> 0 | P48: =I48*2000+J48*10000+K48*1800 -> 0 | Q48: =D48*Prices!A$2 -> 136106.25 | R48: =L48+M48+N48+O48 -> 139150 | S48: =R48+Q48+P48 -> 275256.25 | T48: 49 | U48: Available | V48: A
A49: 50 | B49: 2.176 | C49: =B49*(25/100) -> 0.544 | D49: =C49+B49 -> 2.72 | E49: 0.25 | K49: 2.32 | L49: =E49*Prices!B$2 -> 27500 | M49: =F49*Prices!C$2 -> 0 | N49: =G49*Prices!D$2 -> 0 | O49: =H49*Prices!E$2 -> 0 | P49: =I49*2000+J49*10000+K49*1800 -> 4176 | Q49: =D49*Prices!A$2 -> 48552 | R49: =L49+M49+N49+O49 -> 27500 | S49: =R49+Q49+P49 -> 80228 | T49: 50 | U49: Sold
A50: 51 | B50: 1.616 | C50: =B50*(25/100) -> 0.404 | D50: =C50+B50 -> 2.02 | E50: 0.29 | K50: 1.68 | L50: =E50*Prices!B$2 -> 31900 | M50: =F50*Prices!C$2 -> 0 | N50: =G50*Prices!D$2 -> 0 | O50: =H50*Prices!E$2 -> 0 | P50: =I50*2000+J50*10000+K50*1800 -> 3024 | Q50: =D50*Prices!A$2 -> 36057 | R50: =L50+M50+N50+O50 -> 31900 | S50: =R50+Q50+P50 -> 70981 | T50: 51 | U50: Sold
A51: 52 | B51: 4.596 | C51: =B51*(25/100) -> 1.149 | D51: =C51+B51 -> 5.745 | E51: 0.22 | L51: =E51*Prices!B$2 -> 24200 | M51: =F51*Prices!C$2 -> 0 | N51: =G51*Prices!D$2 -> 0 | O51: =H51*Prices!E$2 -> 0 | P51: =I51*2000+J51*10000+K51*1800 -> 0 | Q51: =D51*Prices!A$2 -> 102548.25 | R51: =L51+M51+N51+O51 -> 24200 | S51: =R51+Q51+P51 -> 126748.25 | T51: 52 | U51: Sold
A52: 53 | B52: 3.246 | C52: =B52*(25/100) -> 0.8115 | D52: =C52+B52 -> 4.0575 | E52: =0.19+0.58 -> 0.77 | J52: 4.4 | L52: =E52*Prices!B$2 -> 84700 | M52: =F52*Prices!C$2 -> 0 | N52: =G52*Prices!D$2 -> 0 | O52: =H52*Prices!E$2 -> 0 | P52: =I52*2000+J52*10000+K52*1800 -> 44000 | Q52: =D52*Prices!A$2 -> 72426.375 | R52: =L52+M52+N52+O52 -> 84700 | S52: =R52+Q52+P52 -> 201126.38 | T52: 53 | U52: Sold
A53: 54 | B53: 2.458 | C53: =B53*(25/100) -> 0.6145 | D53: =C53+B53 -> 3.0725 | E53: 0.49 | G53: 0.37 | L53: =E53*Prices!B$2 -> 53900 | M53: =F53*Prices!C$2 -> 0 | N53: =G53*Prices!D$2 -> 72150 | O53: =H53*Prices!E$2 -> 0 | P53: =I53*2000+J53*10000+K53*1800 -> 0 | Q53: =D53*Prices!A$2 -> 54844.125 | R53: =L53+M53+N53+O53 -> 126050 | S53: =R53+Q53+P53 -> 180894.12 | T53: 54 | U53: Sold
A54: 55 | B54: 1.568 | C54: =B54*(25/100) -> 0.392 | D54: =C54+B54 -> 1.96 | E54: 0.16 | I54: 0.8 | L54: =E54*Prices!B$2 -> 17600 | M54: =F54*Prices!C$2 -> 0 | N54: =G54*Prices!D$2 -> 0 | O54: =H54*Prices!E$2 -> 0 | P54: =I54*2000+J54*10000+K54*1800 -> 1600 | Q54: =D54*Prices!A$2 -> 34986 | R54: =L54+M54+N54+O54 -> 17600 | S54: =R54+Q54+P54 -> 54186 | T54: 55 | U54: Available | V54: A
A55: 56 | B55: 1.486 | C55: =B55*(25/100) -> 0.3715 | D55: =C55+B55 -> 1.8575 | E55: 0.16 | I55: 0.61 | L55: =E55*Prices!B$2 -> 17600 | M55: =F55*Prices!C$2 -> 0 | N55: =G55*Prices!D$2 -> 0 | O55: =H55*Prices!E$2 -> 0 | P55: =I55*2000+J55*10000+K55*1800 -> 1220 | Q55: =D55*Prices!A$2 -> 33156.375 | R55: =L55+M55+N55+O55 -> 17600 | S55: =R55+Q55+P55 -> 51976.375 | T55: 56 | U55: Available | V55: A
A56: 57 | B56: 1.606 | C56: =B56*(25/100) -> 0.4015 | D56: =C56+B56 -> 2.0075 | E56: 0.16 | I56: 0.66 | L56: =E56*Prices!B$2 -> 17600 | M56: =F56*Prices!C$2 -> 0 | N56: =G56*Prices!D$2 -> 0 | O56: =H56*Prices!E$2 -> 0 | P56: =I56*2000+J56*10000+K56*1800 -> 1320 | Q56: =D56*Prices!A$2 -> 35833.875 | R56: =L56+M56+N56+O56 -> 17600 | S56: =R56+Q56+P56 -> 54753.875 | T56: 57 | U56: Sold
A57: 58 | B57: 1.534 | C57: =B57*(25/100) -> 0.3835 | D57: =C57+B57 -> 1.9175 | E57: 0.16 | I57: 0.77 | L57: =E57*Prices!B$2 -> 17600 | M57: =F57*Prices!C$2 -> 0 | N57: =G57*Prices!D$2 -> 0 | O57: =H57*Prices!E$2 -> 0 | P57: =I57*2000+J57*10000+K57*1800 -> 1540 | Q57: =D57*Prices!A$2 -> 34227.375 | R57: =L57+M57+N57+O57 -> 17600 | S57: =R57+Q57+P57 -> 53367.375 | T57: 58 | U57: Sold
A58: 59 | B58: 1.476 | C58: =B58*(25/100) -> 0.369 | D58: =C58+B58 -> 1.845 | E58: 0.16 | I58: 0.76 | L58: =E58*Prices!B$2 -> 17600 | M58: =F58*Prices!C$2 -> 0 | N58: =G58*Prices!D$2 -> 0 | O58: =H58*Prices!E$2 -> 0 | P58: =I58*2000+J58*10000+K58*1800 -> 1520 | Q58: =D58*Prices!A$2 -> 32933.25 | R58: =L58+M58+N58+O58 -> 17600 | S58: =R58+Q58+P58 -> 52053.25 | T58: 59 | U58: Sold
A59: 60 | B59: 7.802 | C59: =B59*(25/100) -> 1.9505 | D59: =C59+B59 -> 9.7525 | E59: 2.22 | K59: 17.17 | L59: =E59*Prices!B$2 -> 244200 | M59: =F59*Prices!C$2 -> 0 | N59: =G59*Prices!D$2 -> 0 | O59: =H59*Prices!E$2 -> 0 | P59: =I59*2000+J59*10000+K59*1800 -> 30906 | Q59: =D59*Prices!A$2 -> 174082.12 | R59: =L59+M59+N59+O59 -> 244200 | S59: =R59+Q59+P59 -> 449188.12 | T59: 60 | U59: Sold
A60: 61 | B60: 1.622 | C60: =B60*(25/100) -> 0.4055 | D60: =C60+B60 -> 2.0275 | E60: 0.12 | I60: 0.62 | L60: =E60*Prices!B$2 -> 13200 | M60: =F60*Prices!C$2 -> 0 | N60: =G60*Prices!D$2 -> 0 | O60: =H60*Prices!E$2 -> 0 | P60: =I60*2000+J60*10000+K60*1800 -> 1240 | Q60: =D60*Prices!A$2 -> 36190.875 | R60: =L60+M60+N60+O60 -> 13200 | S60: =R60+Q60+P60 -> 50630.875 | T60: 61 | U60: Sold
A61: 62 | B61: 1.694 | C61: =B61*(25/100) -> 0.4235 | D61: =C61+B61 -> 2.1175 | E61: 0.25 | I61: 0.93 | L61: =E61*Prices!B$2 -> 27500 | M61: =F61*Prices!C$2 -> 0 | N61: =G61*Prices!D$2 -> 0 | O61: =H61*Prices!E$2 -> 0 | P61: =I61*2000+J61*10000+K61*1800 -> 1860 | Q61: =D61*Prices!A$2 -> 37797.375 | R61: =L61+M61+N61+O61 -> 27500 | S61: =R61+Q61+P61 -> 67157.375 | T61: 62 | U61: Sold
A62: 63 | B62: 2.096 | C62: =B62*(25/100) -> 0.524 | D62: =C62+B62 -> 2.62 | E62: 0.31 | I62: 1.66 | L62: =E62*Prices!B$2 -> 34100 | M62: =F62*Prices!C$2 -> 0 | N62: =G62*Prices!D$2 -> 0 | O62: =H62*Prices!E$2 -> 0 | P62: =I62*2000+J62*10000+K62*1800 -> 3320 | Q62: =D62*Prices!A$2 -> 46767 | R62: =L62+M62+N62+O62 -> 34100 | S62: =R62+Q62+P62 -> 84187 | T62: 63 | U62: Sold
A63: 64 | B63: 1.492 | C63: =B63*(25/100) -> 0.373 | D63: =C63+B63 -> 1.865 | E63: 0.22 | K63: 0.67 | L63: =E63*Prices!B$2 -> 24200 | M63: =F63*Prices!C$2 -> 0 | N63: =G63*Prices!D$2 -> 0 | O63: =H63*Prices!E$2 -> 0 | P63: =I63*2000+J63*10000+K63*1800 -> 1206 | Q63: =D63*Prices!A$2 -> 33290.25 | R63: =L63+M63+N63+O63 -> 24200 | S63: =R63+Q63+P63 -> 58696.25 | T63: 64 | U63: Sold
A64: 65 | B64: 2.05 | C64: =B64*(25/100) -> 0.5125 | D64: =C64+B64 -> 2.5625 | E64: 0.1 | L64: =E64*Prices!B$2 -> 11000 | M64: =F64*Prices!C$2 -> 0 | N64: =G64*Prices!D$2 -> 0 | O64: =H64*Prices!E$2 -> 0 | P64: =I64*2000+J64*10000+K64*1800 -> 0 | Q64: =D64*Prices!A$2 -> 45740.625 | R64: =L64+M64+N64+O64 -> 11000 | S64: =R64+Q64+P64 -> 56740.625 | T64: 65 | U64: Available | V64: A
A65: 66 | B65: 2.252 | C65: =B65*(25/100) -> 0.563 | D65: =C65+B65 -> 2.815 | E65: 0.14 | L65: =E65*Prices!B$2 -> 15400 | M65: =F65*Prices!C$2 -> 0 | N65: =G65*Prices!D$2 -> 0 | O65: =H65*Prices!E$2 -> 0 | P65: =I65*2000+J65*10000+K65*1800 -> 0 | Q65: =D65*Prices!A$2 -> 50247.75 | R65: =L65+M65+N65+O65 -> 15400 | S65: =R65+Q65+P65 -> 65647.75 | T65: 66 | U65: Sold
A66: 67 | B66: 6.258 | C66: =B66*(25/100) -> 1.5645 | D66: =C66+B66 -> 7.8225 | E66: 0.46 | L66: =E66*Prices!B$2 -> 50600 | M66: =F66*Prices!C$2 -> 0 | N66: =G66*Prices!D$2 -> 0 | O66: =H66*Prices!E$2 -> 0 | P66: =I66*2000+J66*10000+K66*1800 -> 0 | Q66: =D66*Prices!A$2 -> 139631.62 | R66: =L66+M66+N66+O66 -> 50600 | S66: =R66+Q66+P66 -> 190231.62 | T66: 67 | U66: Available | V66: A
A67: 68 | B67: 1.588 | C67: =B67*(25/100) -> 0.397 | D67: =C67+B67 -> 1.985 | E67: 0.34 | K67: 4.47 | L67: =E67*Prices!B$2 -> 37400 | M67: =F67*Prices!C$2 -> 0 | N67: =G67*Prices!D$2 -> 0 | O67: =H67*Prices!E$2 -> 0 | P67: =I67*2000+J67*10000+K67*1800 -> 8046 | Q67: =D67*Prices!A$2 -> 35432.25 | R67: =L67+M67+N67+O67 -> 37400 | S67: =R67+Q67+P67 -> 80878.25 | T67: 68 | U67: Available | V67: A
A68: 69 | B68: 1.15 | C68: =B68*(25/100) -> 0.2875 | D68: =C68+B68 -> 1.4375 | E68: 0.26 | J68: 0.94 | L68: =E68*Prices!B$2 -> 28600 | M68: =F68*Prices!C$2 -> 0 | N68: =G68*Prices!D$2 -> 0 | O68: =H68*Prices!E$2 -> 0 | P68: =I68*2000+J68*8000+K68*1800 -> 7520 | Q68: =D68*Prices!A$2 -> 25659.375 | R68: =L68+M68+N68+O68 -> 28600 | S68: =R68+Q68+P68 -> 61779.375 | T68: 69 | U68: Available | V68: A
A69: 70 | B69: 1.534 | C69: =B69*(25/100) -> 0.3835 | D69: =C69+B69 -> 1.9175 | E69: 0.4 | J69: 2.48 | L69: =E69*Prices!B$2 -> 44000 | M69: =F69*Prices!C$2 -> 0 | N69: =G69*Prices!D$2 -> 0 | O69: =H69*Prices!E$2 -> 0 | P69: =I69*2000+J69*8000+K69*1800 -> 19840 | Q69: =D69*Prices!A$2 -> 34227.375 | R69: =L69+M69+N69+O69 -> 44000 | S69: =R69+Q69+P69 -> 98067.375 | T69: 70 | U69: Sold
A70: 71 | B70: 7.786 | C70: =B70*(25/100) -> 1.9465 | D70: =C70+B70 -> 9.7325 | E70: 2.12 | J70: 2.8 | L70: =E70*Prices!B$2 -> 233200 | M70: =F70*Prices!C$2 -> 0 | N70: =G70*Prices!D$2 -> 0 | O70: =H70*Prices!E$2 -> 0 | P70: =I70*2000+J70*8000+K70*1800 -> 22400 | Q70: =D70*Prices!A$2 -> 173725.12 | R70: =L70+M70+N70+O70 -> 233200 | S70: =R70+Q70+P70 -> 429325.12 | T70: 71 | U70: Sold
A71: 72 | B71: 0.872 | C71: =B71*(25/100) -> 0.218 | D71: =C71+B71 -> 1.09 | E71: 0.06 | J71: 0.38 | L71: =E71*Prices!B$2 -> 6600 | M71: =F71*Prices!C$2 -> 0 | N71: =G71*Prices!D$2 -> 0 | O71: =H71*Prices!E$2 -> 0 | P71: =I71*2000+J71*8000+K71*1800 -> 3040 | Q71: =D71*Prices!A$2 -> 19456.5 | R71: =L71+M71+N71+O71 -> 6600 | S71: =R71+Q71+P71 -> 29096.5 | T71: 72 | U71: Available | V71: A
A72: 73 | B72: 0.952 | C72: =B72*(25/100) -> 0.238 | D72: =C72+B72 -> 1.19 | E72: 0.06 | J72: 0.83 | L72: =E72*Prices!B$2 -> 6600 | M72: =F72*Prices!C$2 -> 0 | N72: =G72*Prices!D$2 -> 0 | O72: =H72*Prices!E$2 -> 0 | P72: =I72*2000+J72*8000+K72*1800 -> 6640 | Q72: =D72*Prices!A$2 -> 21241.5 | R72: =L72+M72+N72+O72 -> 6600 | S72: =R72+Q72+P72 -> 34481.5 | T72: 73 | U72: Sold
A73: 74 | B73: 14.604 | C73: =B73*(25/100) -> 3.651 | D73: =C73+B73 -> 18.255 | E73: 4.29 | L73: =E73*Prices!B$2 -> 471900 | M73: =F73*Prices!C$2 -> 0 | N73: =G73*Prices!D$2 -> 0 | O73: =H73*Prices!E$2 -> 0 | P73: =I73*2000+J73*10000+K73*1800 -> 0 | Q73: =D73*Prices!A$2 -> 325851.75 | R73: =L73+M73+N73+O73 -> 471900 | S73: =R73+Q73+P73 -> 797751.75 | T73: 74 | U73: Available | V73: A
A74: 75 | B74: 13.428 | C74: =B74*(25/100) -> 3.357 | D74: =C74+B74 -> 16.785 | E74: 3.21 | L74: =E74*Prices!B$2 -> 353100 | M74: =F74*Prices!C$2 -> 0 | N74: =G74*Prices!D$2 -> 0 | O74: =H74*Prices!E$2 -> 0 | P74: =I74*2000+J74*10000+K74*1800 -> 0 | Q74: =D74*Prices!A$2 -> 299612.25 | R74: =L74+M74+N74+O74 -> 353100 | S74: =R74+Q74+P74 -> 652712.25 | T74: 75 | U74: Available | V74: A
A75: 76 | B75: 14.282 | C75: =B75*(25/100) -> 3.5705 | D75: =C75+B75 -> 17.8525 | E75: 3.14 | I75: 0.95 | L75: =E75*Prices!B$2 -> 345400 | M75: =F75*Prices!C$2 -> 0 | N75: =G75*Prices!D$2 -> 0 | O75: =H75*Prices!E$2 -> 0 | P75: =I75*2000+J75*10000+K75*1800 -> 1900 | Q75: =D75*Prices!A$2 -> 318667.12 | R75: =L75+M75+N75+O75 -> 345400 | S75: =R75+Q75+P75 -> 665967.12 | T75: 76 | U75: Sold
A76: 77 | B76: 3 | C76: =B76*(25/100) -> 0.75 | D76: =C76+B76 -> 3.75 | E76: 0.25 | L76: =E76*Prices!B$2 -> 27500 | M76: =F76*Prices!C$2 -> 0 | N76: =G76*Prices!D$2 -> 0 | O76: =H76*Prices!E$2 -> 0 | P76: =I76*2000+J76*10000+K76*1800 -> 0 | Q76: =D76*Prices!A$2 -> 66937.5 | R76: =L76+M76+N76+O76 -> 27500 | S76: =R76+Q76+P76 -> 94437.5 | T76: 77 | U76: Sold
A77: 78 | B77: 1.982 | C77: =B77*(25/100) -> 0.4955 | D77: =C77+B77 -> 2.4775 | E77: 0.59 | L77: =E77*Prices!B$2 -> 64900 | M77: =F77*Prices!C$2 -> 0 | N77: =G77*Prices!D$2 -> 0 | O77: =H77*Prices!E$2 -> 0 | P77: =I77*2000+J77*10000+K77*1800 -> 0 | Q77: =D77*Prices!A$2 -> 44223.375 | R77: =L77+M77+N77+O77 -> 64900 | S77: =R77+Q77+P77 -> 109123.38 | T77: 78 | U77: Sold
A78: 79 | B78: 2.846 | C78: =B78*(25/100) -> 0.7115 | D78: =C78+B78 -> 3.5575 | E78: 1.01 | L78: =E78*Prices!B$2 -> 111100 | M78: =F78*Prices!C$2 -> 0 | N78: =G78*Prices!D$2 -> 0 | O78: =H78*Prices!E$2 -> 0 | P78: =I78*2000+J78*10000+K78*1800 -> 0 | Q78: =D78*Prices!A$2 -> 63501.375 | R78: =L78+M78+N78+O78 -> 111100 | S78: =R78+Q78+P78 -> 174601.38 | T78: 79 | U78: Available | V78: A
A79: 80 | B79: 4.822 | C79: =B79*(25/100) -> 1.2055 | D79: =C79+B79 -> 6.0275 | E79: 0.64 | L79: =E79*Prices!B$2 -> 70400 | M79: =F79*Prices!C$2 -> 0 | N79: =G79*Prices!D$2 -> 0 | O79: =H79*Prices!E$2 -> 0 | P79: =I79*2000+J79*10000+K79*1800 -> 0 | Q79: =D79*Prices!A$2 -> 107590.88 | R79: =L79+M79+N79+O79 -> 70400 | S79: =R79+Q79+P79 -> 177990.88 | T79: 80 | U79: Available | V79: A
A80: 81 | B80: 3.13 | C80: =B80*(25/100) -> 0.7825 | D80: =C80+B80 -> 3.9125 | E80: 0.57 | K80: 2.18 | L80: =E80*Prices!B$2 -> 62700 | M80: =F80*Prices!C$2 -> 0 | N80: =G80*Prices!D$2 -> 0 | O80: =H80*Prices!E$2 -> 0 | P80: =I80*2000+J80*10000+K80*1800 -> 3924 | Q80: =D80*Prices!A$2 -> 69838.125 | R80: =L80+M80+N80+O80 -> 62700 | S80: =R80+Q80+P80 -> 136462.12 | T80: 81 | U80: Available | V80: A
A81: 82 | B81: 2.222 | C81: =B81*(25/100) -> 0.5555 | D81: =C81+B81 -> 2.7775 | E81: 0.46 | K81: 2.23 | L81: =E81*Prices!B$2 -> 50600 | M81: =F81*Prices!C$2 -> 0 | N81: =G81*Prices!D$2 -> 0 | O81: =H81*Prices!E$2 -> 0 | P81: =I81*2000+J81*10000+K81*1800 -> 4014 | Q81: =D81*Prices!A$2 -> 49578.375 | R81: =L81+M81+N81+O81 -> 50600 | S81: =R81+Q81+P81 -> 104192.38 | T81: 82 | U81: Available | V81: A
A82: 83 | B82: 2.284 | C82: =B82*(25/100) -> 0.571 | D82: =C82+B82 -> 2.855 | E82: 0.6 | K82: 1.43 | L82: =E82*Prices!B$2 -> 66000 | M82: =F82*Prices!C$2 -> 0 | N82: =G82*Prices!D$2 -> 0 | O82: =H82*Prices!E$2 -> 0 | P82: =I82*2000+J82*10000+K82*1800 -> 2574 | Q82: =D82*Prices!A$2 -> 50961.75 | R82: =L82+M82+N82+O82 -> 66000 | S82: =R82+Q82+P82 -> 119535.75 | T82: 83 | U82: Available | V82: A
A83: 84 | B83: 2.146 | C83: =B83*(25/100) -> 0.5365 | D83: =C83+B83 -> 2.6825 | E83: 0.27 | I83: 1.2 | L83: =E83*Prices!B$2 -> 29700 | M83: =F83*Prices!C$2 -> 0 | N83: =G83*Prices!D$2 -> 0 | O83: =H83*Prices!E$2 -> 0 | P83: =I83*2000+J83*10000+K83*1800 -> 2400 | Q83: =D83*Prices!A$2 -> 47882.625 | R83: =L83+M83+N83+O83 -> 29700 | S83: =R83+Q83+P83 -> 79982.625 | T83: 84 | U83: Sold
A84: 85 | B84: 2.26 | C84: =B84*(25/100) -> 0.565 | D84: =C84+B84 -> 2.825 | E84: 0.36 | I84: 1.79 | L84: =E84*Prices!B$2 -> 39600 | M84: =F84*Prices!C$2 -> 0 | N84: =G84*Prices!D$2 -> 0 | O84: =H84*Prices!E$2 -> 0 | P84: =I84*2000+J84*10000+K84*1800 -> 3580 | Q84: =D84*Prices!A$2 -> 50426.25 | R84: =L84+M84+N84+O84 -> 39600 | S84: =R84+Q84+P84 -> 93606.25 | T84: 85 | U84: Available | V84: A
A85: 86 | B85: 2.02 | C85: =B85*(25/100) -> 0.505 | D85: =C85+B85 -> 2.525 | E85: 0.4 | I85: 1.75 | L85: =E85*Prices!B$2 -> 44000 | M85: =F85*Prices!C$2 -> 0 | N85: =G85*Prices!D$2 -> 0 | O85: =H85*Prices!E$2 -> 0 | P85: =I85*2000+J85*10000+K85*1800 -> 3500 | Q85: =D85*Prices!A$2 -> 45071.25 | R85: =L85+M85+N85+O85 -> 44000 | S85: =R85+Q85+P85 -> 92571.25 | T85: 86 | U85: Available | V85: A
A86: 87 | B86: 1.568 | C86: =B86*(25/100) -> 0.392 | D86: =C86+B86 -> 1.96 | E86: 0.16 | I86: 0.7 | L86: =E86*Prices!B$2 -> 17600 | M86: =F86*Prices!C$2 -> 0 | N86: =G86*Prices!D$2 -> 0 | O86: =H86*Prices!E$2 -> 0 | P86: =I86*2000+J86*10000+K86*1800 -> 1400 | Q86: =D86*Prices!A$2 -> 34986 | R86: =L86+M86+N86+O86 -> 17600 | S86: =R86+Q86+P86 -> 53986 | T86: 87 | U86: Sold
A87: 88 | B87: 1.528 | C87: =B87*(25/100) -> 0.382 | D87: =C87+B87 -> 1.91 | E87: 0.16 | I87: 0.65 | L87: =E87*Prices!B$2 -> 17600 | M87: =F87*Prices!C$2 -> 0 | N87: =G87*Prices!D$2 -> 0 | O87: =H87*Prices!E$2 -> 0 | P87: =I87*2000+J87*10000+K87*1800 -> 1300 | Q87: =D87*Prices!A$2 -> 34093.5 | R87: =L87+M87+N87+O87 -> 17600 | S87: =R87+Q87+P87 -> 52993.5 | T87: 88 | U87: Sold
A88: 89 | B88: 1.428 | C88: =B88*(25/100) -> 0.357 | D88: =C88+B88 -> 1.785 | E88: 0.14 | I88: 0.97 | L88: =E88*Prices!B$2 -> 15400 | M88: =F88*Prices!C$2 -> 0 | N88: =G88*Prices!D$2 -> 0 | O88: =H88*Prices!E$2 -> 0 | P88: =I88*2000+J88*10000+K88*1800 -> 1940 | Q88: =D88*Prices!A$2 -> 31862.25 | R88: =L88+M88+N88+O88 -> 15400 | S88: =R88+Q88+P88 -> 49202.25 | T88: 89 | U88: Sold
A89: 90 | B89: 1.39 | C89: =B89*(25/100) -> 0.3475 | D89: =C89+B89 -> 1.7375 | E89: 0.15 | I89: 0.45 | L89: =E89*Prices!B$2 -> 16500 | M89: =F89*Prices!C$2 -> 0 | N89: =G89*Prices!D$2 -> 0 | O89: =H89*Prices!E$2 -> 0 | P89: =I89*2000+J89*10000+K89*1800 -> 900 | Q89: =D89*Prices!A$2 -> 31014.375 | R89: =L89+M89+N89+O89 -> 16500 | S89: =R89+Q89+P89 -> 48414.375 | T89: 90 | U89: Available | V89: A
A90: 91 | B90: 1.452 | C90: =B90*(25/100) -> 0.363 | D90: =C90+B90 -> 1.815 | E90: 0.14 | I90: 1.25 | L90: =E90*Prices!B$2 -> 15400 | M90: =F90*Prices!C$2 -> 0 | N90: =G90*Prices!D$2 -> 0 | O90: =H90*Prices!E$2 -> 0 | P90: =I90*2000+J90*10000+K90*1800 -> 2500 | Q90: =D90*Prices!A$2 -> 32397.75 | R90: =L90+M90+N90+O90 -> 15400 | S90: =R90+Q90+P90 -> 50297.75 | T90: 91 | U90: Sold
A91: 92 | B91: 1.558 | C91: =B91*(25/100) -> 0.3895 | D91: =C91+B91 -> 1.9475 | E91: 0.36 | J91: 2.08 | L91: =E91*Prices!B$2 -> 39600 | M91: =F91*Prices!C$2 -> 0 | N91: =G91*Prices!D$2 -> 0 | O91: =H91*Prices!E$2 -> 0 | P91: =I91*2000+J91*10000+K91*1800 -> 20800 | Q91: =D91*Prices!A$2 -> 34762.875 | R91: =L91+M91+N91+O91 -> 39600 | S91: =R91+Q91+P91 -> 95162.875 | T91: 92 | U91: Available | V91: A
A92: 93 | B92: 1.488 | C92: =B92*(25/100) -> 0.372 | D92: =C92+B92 -> 1.86 | E92: 0.61 | L92: =E92*Prices!B$2 -> 67100 | M92: =F92*Prices!C$2 -> 0 | N92: =G92*Prices!D$2 -> 0 | O92: =H92*Prices!E$2 -> 0 | P92: =I92*2000+J92*10000+K92*1800 -> 0 | Q92: =D92*Prices!A$2 -> 33201 | R92: =L92+M92+N92+O92 -> 67100 | S92: =R92+Q92+P92 -> 100301 | T92: 93 | U92: Available | V92: A
A93: 94 | B93: 2.052 | C93: =B93*(25/100) -> 0.513 | D93: =C93+B93 -> 2.565 | E93: 0.74 | L93: =E93*Prices!B$2 -> 81400 | M93: =F93*Prices!C$2 -> 0 | N93: =G93*Prices!D$2 -> 0 | O93: =H93*Prices!E$2 -> 0 | P93: =I93*2000+J93*10000+K93*1800 -> 0 | Q93: =D93*Prices!A$2 -> 45785.25 | R93: =L93+M93+N93+O93 -> 81400 | S93: =R93+Q93+P93 -> 127185.25 | T93: 94 | U93: Sold
A94: 95 | B94: 1.772 | C94: =B94*(25/100) -> 0.443 | D94: =C94+B94 -> 2.215 | E94: 1.14 | L94: =E94*Prices!B$2 -> 125400 | M94: =F94*Prices!C$2 -> 0 | N94: =G94*Prices!D$2 -> 0 | O94: =H94*Prices!E$2 -> 0 | P94: =I94*2000+J94*10000+K94*1800 -> 0 | Q94: =D94*Prices!A$2 -> 39537.75 | R94: =L94+M94+N94+O94 -> 125400 | S94: =R94+Q94+P94 -> 164937.75 | T94: 95 | U94: Sold
A95: 96 | B95: 2.568 | C95: =B95*(25/100) -> 0.642 | D95: =C95+B95 -> 3.21 | E95: 0.66 | L95: =E95*Prices!B$2 -> 72600 | M95: =F95*Prices!C$2 -> 0 | N95: =G95*Prices!D$2 -> 0 | O95: =H95*Prices!E$2 -> 0 | P95: =I95*2000+J95*10000+K95*1800 -> 0 | Q95: =D95*Prices!A$2 -> 57298.5 | R95: =L95+M95+N95+O95 -> 72600 | S95: =R95+Q95+P95 -> 129898.5 | T95: 96 | U95: Available | V95: A
A96: 97 | B96: 1.848 | C96: =B96*(25/100) -> 0.462 | D96: =C96+B96 -> 2.31 | E96: 0.71 | L96: =E96*Prices!B$2 -> 78100 | M96: =F96*Prices!C$2 -> 0 | N96: =G96*Prices!D$2 -> 0 | O96: =H96*Prices!E$2 -> 0 | P96: =I96*2000+J96*10000+K96*1800 -> 0 | Q96: =D96*Prices!A$2 -> 41233.5 | R96: =L96+M96+N96+O96 -> 78100 | S96: =R96+Q96+P96 -> 119333.5 | T96: 97 | U96: Available | V96: A
A97: 98 | B97: 2.086 | C97: =B97*(25/100) -> 0.5215 | D97: =C97+B97 -> 2.6075 | E97: 0.77 | L97: =E97*Prices!B$2 -> 84700 | M97: =F97*Prices!C$2 -> 0 | N97: =G97*Prices!D$2 -> 0 | O97: =H97*Prices!E$2 -> 0 | P97: =I97*2000+J97*10000+K97*1800 -> 0 | Q97: =D97*Prices!A$2 -> 46543.875 | R97: =L97+M97+N97+O97 -> 84700 | S97: =R97+Q97+P97 -> 131243.88 | T97: 98 | U97: Available | V97: A
A98: 99 | B98: 2.478 | C98: =B98*(25/100) -> 0.6195 | D98: =C98+B98 -> 3.0975 | E98: 0.86 | L98: =E98*Prices!B$2 -> 94600 | M98: =F98*Prices!C$2 -> 0 | N98: =G98*Prices!D$2 -> 0 | O98: =H98*Prices!E$2 -> 0 | P98: =I98*2000+J98*10000+K98*1800 -> 0 | Q98: =D98*Prices!A$2 -> 55290.375 | R98: =L98+M98+N98+O98 -> 94600 | S98: =R98+Q98+P98 -> 149890.38 | T98: 99 | U98: Available | V98: A
A99: 100 | B99: 2.772 | C99: =B99*(25/100) -> 0.693 | D99: =C99+B99 -> 3.465 | E99: 0.45 | I99: 1.99 | L99: =E99*Prices!B$2 -> 49500 | M99: =F99*Prices!C$2 -> 0 | N99: =G99*Prices!D$2 -> 0 | O99: =H99*Prices!E$2 -> 0 | P99: =I99*4000+J99*10000+K99*1800 -> 7960 | Q99: =D99*Prices!A$2 -> 61850.25 | R99: =L99+M99+N99+O99 -> 49500 | S99: =R99+Q99+P99 -> 119310.25 | T99: 100 | U99: Available | V99: A
A100: 101 | B100: 2.134 | C100: =B100*(25/100) -> 0.5335 | D100: =C100+B100 -> 2.6675 | E100: 0.83 | L100: =E100*Prices!B$2 -> 91300 | M100: =F100*Prices!C$2 -> 0 | N100: =G100*Prices!D$2 -> 0 | O100: =H100*Prices!E$2 -> 0 | P100: =I100*2000+J100*10000+K100*1800 -> 0 | Q100: =D100*Prices!A$2 -> 47614.875 | R100: =L100+M100+N100+O100 -> 91300 | S100: =R100+Q100+P100 -> 138914.88 | T100: 101 | U100: Available | V100: A
...

Sheet Jagganath
A1: Sn | B1: Net Weight | C1: Wstg + MC | D1: Gross weight | E1: Dmd <0.06 | F1: Dmd <0.12 | G1: Dmd <0.17 | H1: Dmd Big | I1: Ruby | J1: Emreld | K1: Muga | L1: Dmd Price | M1: Dmd Price | N1: Dmd Price | O1: Dmd Price | P1: Stn Price | Q1: Gold Price | R1: Ttl dmd Price | S1: Total Price | T1: Sn
A2: r10 | B2: 1.348 | C2: =B2*(25/100) -> 0.337 | D2: =C2+B2 -> 1.685 | E2: 0.11 | L2: =E2*Prices!B$2 -> 12100 | M2: =F2*Prices!C$2 -> 0 | N2: =G2*Prices!D$2 -> 0 | O2: =H2*Prices!E$2 -> 0 | P2: =I2*2000+J2*4000+K2*650 -> 0 | Q2: =D2*Prices!A$2 -> 30077.25 | R2: =L2+M2+N2+O2 -> 12100 | S2: =R2+Q2+P2 -> 42177.25 | T2: 10 | U2: Sold
A3: e2 | B3: 8.98 | C3: =B3*(25/100) -> 2.245 | D3: =C3+B3 -> 11.225 | E3: 1.2 | L3: =E3*Prices!B$2 -> 132000 | M3: =F3*Prices!C$2 -> 0 | N3: =G3*Prices!D$2 -> 0 | O3: =H3*Prices!E$2 -> 0 | P3: =I3*2000+J3*4000+K3*650 -> 0 | Q3: =D3*Prices!A$2 -> 200366.25 | R3: =L3+M3+N3+O3 -> 132000 | S3: =R3+Q3+P3 -> 332366.25 | T3: e2 | U3: Sold
A4: 1 | B4: 3.23 | C4: =B4*(25/100) -> 0.8075 | D4: =C4+B4 -> 4.0375 | E4: 0.81 | L4: =E4*Prices!B$2 -> 89100 | M4: =F4*Prices!C$2 -> 0 | N4: =G4*Prices!D$2 -> 0 | O4: =H4*Prices!E$2 -> 0 | P4: =I4*2000+J4*4000+K4*650 -> 0 | Q4: =D4*Prices!A$2 -> 72069.375 | R4: =L4+M4+N4+O4 -> 89100 | S4: =R4+Q4+P4 -> 161169.38 | T4: 1 | U4: Sold
A5: 2 | B5: 4.14 | C5: =B5*(25/100) -> 1.035 | D5: =C5+B5 -> 5.175 | E5: 1 | L5: =E5*Prices!B$2 -> 110000 | M5: =F5*Prices!C$2 -> 0 | N5: =G5*Prices!D$2 -> 0 | O5: =H5*Prices!E$2 -> 0 | P5: =I5*2000+J5*4000+K5*650 -> 0 | Q5: =D5*Prices!A$2 -> 92373.75 | R5: =L5+M5+N5+O5 -> 110000 | S5: =R5+Q5+P5 -> 202373.75 | T5: 2 | U5: Sold
A6: 3 | B6: 2.59 | C6: =B6*(25/100) -> 0.6475 | D6: =C6+B6 -> 3.2375 | E6: 0.5 | L6: =E6*Prices!B$2 -> 55000 | M6: =F6*Prices!C$2 -> 0 | N6: =G6*Prices!D$2 -> 0 | O6: =H6*Prices!E$2 -> 0 | P6: =I6*2000+J6*4000+K6*650 -> 0 | Q6: =D6*Prices!A$2 -> 57789.375 | R6: =L6+M6+N6+O6 -> 55000 | S6: =R6+Q6+P6 -> 112789.38 | T6: 3 | U6: Sold
A7: 4 | B7: 2.97 | C7: =B7*(25/100) -> 0.7425 | D7: =C7+B7 -> 3.7125 | E7: 0.85 | L7: =E7*Prices!B$2 -> 93500 | M7: =F7*Prices!C$2 -> 0 | N7: =G7*Prices!D$2 -> 0 | O7: =H7*Prices!E$2 -> 0 | P7: =I7*2000+J7*4000+K7*650 -> 0 | Q7: =D7*Prices!A$2 -> 66268.125 | R7: =L7+M7+N7+O7 -> 93500 | S7: =R7+Q7+P7 -> 159768.12 | T7: 4 | U7: Available | V7: A
A8: 5 | B8: 4.27 | C8: =B8*(25/100) -> 1.0675 | D8: =C8+B8 -> 5.3375 | E8: 1.44 | L8: =E8*Prices!B$2 -> 158400 | M8: =F8*Prices!C$2 -> 0 | N8: =G8*Prices!D$2 -> 0 | O8: =H8*Prices!E$2 -> 0 | P8: =I8*2000+J8*4000+K8*650 -> 0 | Q8: =D8*Prices!A$2 -> 95274.375 | R8: =L8+M8+N8+O8 -> 158400 | S8: =R8+Q8+P8 -> 253674.38 | T8: 5 | U8: Sold
A9: 6 | B9: 2.96 | C9: =B9*(25/100) -> 0.74 | D9: =C9+B9 -> 3.7 | E9: 0.4 | L9: =E9*Prices!B$2 -> 44000 | M9: =F9*Prices!C$2 -> 0 | N9: =G9*Prices!D$2 -> 0 | O9: =H9*Prices!E$2 -> 0 | P9: =I9*2000+J9*4000+K9*650 -> 0 | Q9: =D9*Prices!A$2 -> 66045 | R9: =L9+M9+N9+O9 -> 44000 | S9: =R9+Q9+P9 -> 110045 | T9: 6 | U9: Sold
A10: 7 | B10: 3.55 | C10: =B10*(25/100) -> 0.8875 | D10: =C10+B10 -> 4.4375 | E10: 0.83 | L10: =E10*Prices!B$2 -> 91300 | M10: =F10*Prices!C$2 -> 0 | N10: =G10*Prices!D$2 -> 0 | O10: =H10*Prices!E$2 -> 0 | P10: =I10*2000+J10*4000+K10*650 -> 0 | Q10: =D10*Prices!A$2 -> 79209.375 | R10: =L10+M10+N10+O10 -> 91300 | S10: =R10+Q10+P10 -> 170509.38 | T10: 7 | U10: Available | V10: A
A11: 8 | B11: 7.16 | C11: =B11*(25/100) -> 1.79 | D11: =C11+B11 -> 8.95 | E11: 1.58 | L11: =E11*Prices!B$2 -> 173800 | M11: =F11*Prices!C$2 -> 0 | N11: =G11*Prices!D$2 -> 0 | O11: =H11*Prices!E$2 -> 0 | P11: =I11*2000+J11*4000+K11*650 -> 0 | Q11: =D11*Prices!A$2 -> 159757.5 | R11: =L11+M11+N11+O11 -> 173800 | S11: =R11+Q11+P11 -> 333557.5 | T11: 8 | U11: Available | V11: A
A12: 9 | B12: 3.57 | C12: =B12*(25/100) -> 0.8925 | D12: =C12+B12 -> 4.4625 | E12: 0.62 | L12: =E12*Prices!B$2 -> 68200 | M12: =F12*Prices!C$2 -> 0 | N12: =G12*Prices!D$2 -> 0 | O12: =H12*Prices!E$2 -> 0 | P12: =I12*2000+J12*4000+K12*650 -> 0 | Q12: =D12*Prices!A$2 -> 79655.625 | R12: =L12+M12+N12+O12 -> 68200 | S12: =R12+Q12+P12 -> 147855.62 | T12: 9 | U12: Sold
A13: 10 | B13: 2.9 | C13: =B13*(25/100) -> 0.725 | D13: =C13+B13 -> 3.625 | E13: 0.3 | L13: =E13*Prices!B$2 -> 33000 | M13: =F13*Prices!C$2 -> 0 | N13: =G13*Prices!D$2 -> 0 | O13: =H13*Prices!E$2 -> 0 | P13: =I13*2000+J13*4000+K13*650 -> 0 | Q13: =D13*Prices!A$2 -> 64706.25 | R13: =L13+M13+N13+O13 -> 33000 | S13: =R13+Q13+P13 -> 97706.25 | T13: 10 | U13: Sold
A14: 11 | B14: 3.51 | C14: =B14*(25/100) -> 0.8775 | D14: =C14+B14 -> 4.3875 | E14: 0.53 | L14: =E14*Prices!B$2 -> 58300 | M14: =F14*Prices!C$2 -> 0 | N14: =G14*Prices!D$2 -> 0 | O14: =H14*Prices!E$2 -> 0 | P14: =I14*2000+J14*4000+K14*650 -> 0 | Q14: =D14*Prices!A$2 -> 78316.875 | R14: =L14+M14+N14+O14 -> 58300 | S14: =R14+Q14+P14 -> 136616.88 | T14: 11 | U14: Available | V14: A
A15: 12 | B15: 8.26 | C15: =B15*(25/100) -> 2.065 | D15: =C15+B15 -> 10.325 | E15: 1.85 | L15: =E15*Prices!B$2 -> 203500 | M15: =F15*Prices!C$2 -> 0 | N15: =G15*Prices!D$2 -> 0 | O15: =H15*Prices!E$2 -> 0 | P15: =I15*2000+J15*4000+K15*650 -> 0 | Q15: =D15*Prices!A$2 -> 184301.25 | R15: =L15+M15+N15+O15 -> 203500 | S15: =R15+Q15+P15 -> 387801.25 | T15: 12 | U15: Sold
A16: 13 | B16: 16 | C16: =B16*(25/100) -> 4 | D16: =C16+B16 -> 20 | E16: 2.68 | L16: =E16*Prices!B$2 -> 294800 | M16: =F16*Prices!C$2 -> 0 | N16: =G16*Prices!D$2 -> 0 | O16: =H16*Prices!E$2 -> 0 | P16: =I16*2000+J16*4000+K16*650 -> 0 | Q16: =D16*Prices!A$2 -> 357000 | R16: =L16+M16+N16+O16 -> 294800 | S16: =R16+Q16+P16 -> 651800 | T16: 13 | U16: Sold
A17: 14 | B17: 3.18 | C17: =B17*(25/100) -> 0.795 | D17: =C17+B17 -> 3.975 | E17: 0.85 | L17: =E17*Prices!B$2 -> 93500 | M17: =F17*Prices!C$2 -> 0 | N17: =G17*Prices!D$2 -> 0 | O17: =H17*Prices!E$2 -> 0 | P17: =I17*2000+J17*4000+K17*650 -> 0 | Q17: =D17*Prices!A$2 -> 70953.75 | R17: =L17+M17+N17+O17 -> 93500 | S17: =R17+Q17+P17 -> 164453.75 | T17: 14 | U17: Available | V17: A
A18: 15 | B18: 3.17 | C18: =B18*(25/100) -> 0.7925 | D18: =C18+B18 -> 3.9625 | E18: 0.83 | L18: =E18*Prices!B$2 -> 91300 | M18: =F18*Prices!C$2 -> 0 | N18: =G18*Prices!D$2 -> 0 | O18: =H18*Prices!E$2 -> 0 | P18: =I18*2000+J18*4000+K18*650 -> 0 | Q18: =D18*Prices!A$2 -> 70730.625 | R18: =L18+M18+N18+O18 -> 91300 | S18: =R18+Q18+P18 -> 162030.62 | T18: 15 | U18: Available | V18: A
A19: 16 | B19: 3.78 | C19: =B19*(25/100) -> 0.945 | D19: =C19+B19 -> 4.725 | E19: 0.68 | L19: =E19*Prices!B$2 -> 74800 | M19: =F19*Prices!C$2 -> 0 | N19: =G19*Prices!D$2 -> 0 | O19: =H19*Prices!E$2 -> 0 | P19: =I19*2000+J19*4000+K19*650 -> 0 | Q19: =D19*Prices!A$2 -> 84341.25 | R19: =L19+M19+N19+O19 -> 74800 | S19: =R19+Q19+P19 -> 159141.25 | T19: 16 | U19: Available | V19: A
A20: 17 | B20: 2.7 | C20: =B20*(25/100) -> 0.675 | D20: =C20+B20 -> 3.375 | E20: 0.38 | L20: =E20*Prices!B$2 -> 41800 | M20: =F20*Prices!C$2 -> 0 | N20: =G20*Prices!D$2 -> 0 | O20: =H20*Prices!E$2 -> 0 | P20: =I20*2000+J20*4000+K20*650 -> 0 | Q20: =D20*Prices!A$2 -> 60243.75 | R20: =L20+M20+N20+O20 -> 41800 | S20: =R20+Q20+P20 -> 102043.75 | T20: 17 | U20: Available | V20: A
A21: 18 | B21: 1.15 | C21: =B21*(25/100) -> 0.2875 | D21: =C21+B21 -> 1.4375 | E21: 0.08 | L21: =E21*Prices!B$2 -> 8800 | M21: =F21*Prices!C$2 -> 0 | N21: =G21*Prices!D$2 -> 0 | O21: =H21*Prices!E$2 -> 0 | P21: =I21*2000+J21*4000+K21*650 -> 0 | Q21: =D21*Prices!A$2 -> 25659.375 | R21: =L21+M21+N21+O21 -> 8800 | S21: =R21+Q21+P21 -> 34459.375 | T21: 18 | U21: Available | V21: A
A22: 19 | B22: 2.04 | C22: =B22*(25/100) -> 0.51 | D22: =C22+B22 -> 2.55 | E22: 0.39 | L22: =E22*Prices!B$2 -> 42900 | M22: =F22*Prices!C$2 -> 0 | N22: =G22*Prices!D$2 -> 0 | O22: =H22*Prices!E$2 -> 0 | P22: =I22*2000+J22*4000+K22*650 -> 0 | Q22: =D22*Prices!A$2 -> 45517.5 | R22: =L22+M22+N22+O22 -> 42900 | S22: =R22+Q22+P22 -> 88417.5 | T22: 19 | U22: Sold
A23: 20 | B23: 2.68 | C23: =B23*(25/100) -> 0.67 | D23: =C23+B23 -> 3.35 | E23: 0.33 | L23: =E23*Prices!B$2 -> 36300 | M23: =F23*Prices!C$2 -> 0 | N23: =G23*Prices!D$2 -> 0 | O23: =H23*Prices!E$2 -> 0 | P23: =I23*2000+J23*4000+K23*650 -> 0 | Q23: =D23*Prices!A$2 -> 59797.5 | R23: =L23+M23+N23+O23 -> 36300 | S23: =R23+Q23+P23 -> 96097.5 | T23: 20 | U23: Available
A24: 21 | B24: 1.55 | C24: =B24*(25/100) -> 0.3875 | D24: =C24+B24 -> 1.9375 | E24: 0.37 | L24: =E24*Prices!B$2 -> 40700 | M24: =F24*Prices!C$2 -> 0 | N24: =G24*Prices!D$2 -> 0 | O24: =H24*Prices!E$2 -> 0 | P24: =I24*2000+J24*4000+K24*650 -> 0 | Q24: =D24*Prices!A$2 -> 34584.375 | R24: =L24+M24+N24+O24 -> 40700 | S24: =R24+Q24+P24 -> 75284.375 | T24: 21 | U24: Available | V24: A
A25: 22 | B25: 0.81 | C25: =B25*(25/100) -> 0.2025 | D25: =C25+B25 -> 1.0125 | E25: 0.42 | L25: =E25*Prices!B$2 -> 46200 | M25: =F25*Prices!C$2 -> 0 | N25: =G25*Prices!D$2 -> 0 | O25: =H25*Prices!E$2 -> 0 | P25: =I25*2000+J25*4000+K25*650 -> 0 | Q25: =D25*Prices!A$2 -> 18073.125 | R25: =L25+M25+N25+O25 -> 46200 | S25: =R25+Q25+P25 -> 64273.125 | T25: 22 | U25: Available | V25: A
A26: 23 | B26: 1.88 | C26: =B26*(25/100) -> 0.47 | D26: =C26+B26 -> 2.35 | E26: 0.27 | L26: =E26*Prices!B$2 -> 29700 | M26: =F26*Prices!C$2 -> 0 | N26: =G26*Prices!D$2 -> 0 | O26: =H26*Prices!E$2 -> 0 | P26: =I26*2000+J26*4000+K26*650 -> 0 | Q26: =D26*Prices!A$2 -> 41947.5 | R26: =L26+M26+N26+O26 -> 29700 | S26: =R26+Q26+P26 -> 71647.5 | T26: 23 | U26: Sold
A27: 24 | B27: 0.54 | C27: =B27*(25/100) -> 0.135 | D27: =C27+B27 -> 0.675 | E27: 0.11 | L27: =E27*Prices!B$2 -> 12100 | M27: =F27*Prices!C$2 -> 0 | N27: =G27*Prices!D$2 -> 0 | O27: =H27*Prices!E$2 -> 0 | P27: =I27*2000+J27*4000+K27*650 -> 0 | Q27: =D27*Prices!A$2 -> 12048.75 | R27: =L27+M27+N27+O27 -> 12100 | S27: =R27+Q27+P27 -> 24148.75 | T27: 24 | U27: Sold
A28: 25 | B28: 1.61 | C28: =B28*(25/100) -> 0.4025 | D28: =C28+B28 -> 2.0125 | E28: 0.24 | L28: =E28*Prices!B$2 -> 26400 | M28: =F28*Prices!C$2 -> 0 | N28: =G28*Prices!D$2 -> 0 | O28: =H28*Prices!E$2 -> 0 | P28: =I28*2000+J28*4000+K28*650 -> 0 | Q28: =D28*Prices!A$2 -> 35923.125 | R28: =L28+M28+N28+O28 -> 26400 | S28: =R28+Q28+P28 -> 62323.125 | T28: 25 | U28: Sold
A29: 26 | B29: 1.25 | C29: =B29*(25/100) -> 0.3125 | D29: =C29+B29 -> 1.5625 | E29: 0.2 | L29: =E29*Prices!B$2 -> 22000 | M29: =F29*Prices!C$2 -> 0 | N29: =G29*Prices!D$2 -> 0 | O29: =H29*Prices!E$2 -> 0 | P29: =I29*2000+J29*4000+K29*650 -> 0 | Q29: =D29*Prices!A$2 -> 27890.625 | R29: =L29+M29+N29+O29 -> 22000 | S29: =R29+Q29+P29 -> 49890.625 | T29: 26 | U29: Sold
A30: 27 | B30: 1.3 | C30: =B30*(25/100) -> 0.325 | D30: =C30+B30 -> 1.625 | E30: 0.19 | L30: =E30*Prices!B$2 -> 20900 | M30: =F30*Prices!C$2 -> 0 | N30: =G30*Prices!D$2 -> 0 | O30: =H30*Prices!E$2 -> 0 | P30: =I30*2000+J30*4000+K30*650 -> 0 | Q30: =D30*Prices!A$2 -> 29006.25 | R30: =L30+M30+N30+O30 -> 20900 | S30: =R30+Q30+P30 -> 49906.25 | T30: 27 | U30: Sold
A31: 28 | B31: 1.09 | C31: =B31*(25/100) -> 0.2725 | D31: =C31+B31 -> 1.3625 | E31: 0.21 | L31: =E31*Prices!B$2 -> 23100 | M31: =F31*Prices!C$2 -> 0 | N31: =G31*Prices!D$2 -> 0 | O31: =H31*Prices!E$2 -> 0 | P31: =I31*2000+J31*4000+K31*650 -> 0 | Q31: =D31*Prices!A$2 -> 24320.625 | R31: =L31+M31+N31+O31 -> 23100 | S31: =R31+Q31+P31 -> 47420.625 | T31: 28 | U31: Available | V31: A
A32: 29 | B32: 1.15 | C32: =B32*(25/100) -> 0.2875 | D32: =C32+B32 -> 1.4375 | E32: 0.17 | L32: =E32*Prices!B$2 -> 18700 | M32: =F32*Prices!C$2 -> 0 | N32: =G32*Prices!D$2 -> 0 | O32: =H32*Prices!E$2 -> 0 | P32: =I32*2000+J32*4000+K32*650 -> 0 | Q32: =D32*Prices!A$2 -> 25659.375 | R32: =L32+M32+N32+O32 -> 18700 | S32: =R32+Q32+P32 -> 44359.375 | T32: 29 | U32: Available | V32: A
A33: 30 | B33: 15.85 | C33: =B33*(25/100) -> 3.9625 | D33: =C33+B33 -> 19.8125 | E33: 2.9 | L33: =E33*Prices!B$2 -> 319000 | M33: =F33*Prices!C$2 -> 0 | N33: =G33*Prices!D$2 -> 0 | O33: =H33*Prices!E$2 -> 0 | P33: =I33*2000+J33*4000+K33*650 -> 0 | Q33: =D33*Prices!A$2 -> 353653.12 | R33: =L33+M33+N33+O33 -> 319000 | S33: =R33+Q33+P33 -> 672653.12 | T33: 30 | U33: Sold
A34: 31 | B34: 8.64 | C34: =B34*(25/100) -> 2.16 | D34: =C34+B34 -> 10.8 | E34: 1.67 | L34: =E34*Prices!B$2 -> 183700 | M34: =F34*Prices!C$2 -> 0 | N34: =G34*Prices!D$2 -> 0 | O34: =H34*Prices!E$2 -> 0 | P34: =I34*2000+J34*4000+K34*650 -> 0 | Q34: =D34*Prices!A$2 -> 192780 | R34: =L34+M34+N34+O34 -> 183700 | S34: =R34+Q34+P34 -> 376480 | T34: 31 | U34: Available | V34: A
A35: 32 | B35: 16.59 | C35: =B35*(25/100) -> 4.1475 | D35: =C35+B35 -> 20.7375 | E35: 3.86 | L35: =E35*Prices!B$2 -> 424600 | M35: =F35*Prices!C$2 -> 0 | N35: =G35*Prices!D$2 -> 0 | O35: =H35*Prices!E$2 -> 0 | P35: =I35*2000+J35*4000+K35*650 -> 0 | Q35: =D35*Prices!A$2 -> 370164.38 | R35: =L35+M35+N35+O35 -> 424600 | S35: =R35+Q35+P35 -> 794764.38 | T35: 32 | U35: Sold
A36: 33 | B36: 4.35 | C36: =B36*(25/100) -> 1.0875 | D36: =C36+B36 -> 5.4375 | E36: 1.18 | L36: =E36*Prices!B$2 -> 129800 | M36: =F36*Prices!C$2 -> 0 | N36: =G36*Prices!D$2 -> 0 | O36: =H36*Prices!E$2 -> 0 | P36: =I36*2000+J36*4000+K36*650 -> 0 | Q36: =D36*Prices!A$2 -> 97059.375 | R36: =L36+M36+N36+O36 -> 129800 | S36: =R36+Q36+P36 -> 226859.38 | T36: 33 | U36: Sold
A37: 34 | B37: 16.42 | C37: =B37*(25/100) -> 4.105 | D37: =C37+B37 -> 20.525 | E37: 4.02 | J37: 3.7 | L37: =E37*Prices!B$2 -> 442200 | M37: =F37*Prices!C$2 -> 0 | N37: =G37*Prices!D$2 -> 0 | O37: =H37*Prices!E$2 -> 0 | P37: =I37*2000+J37*5000+K37*650 -> 18500 | Q37: =D37*Prices!A$2 -> 366371.25 | R37: =L37+M37+N37+O37 -> 442200 | S37: =R37+Q37+P37 -> 827071.25 | T37: 34 | U37: Available | V37: A
A38: 35 | B38: 6.68 | C38: =B38*(25/100) -> 1.67 | D38: =C38+B38 -> 8.35 | E38: 2.42 | J38: 5.18 | L38: =E38*Prices!B$2 -> 266200 | M38: =F38*Prices!C$2 -> 0 | N38: =G38*Prices!D$2 -> 0 | O38: =H38*Prices!E$2 -> 0 | P38: =I38*2000+J38*5000+K38*650 -> 25900 | Q38: =D38*Prices!A$2 -> 149047.5 | R38: =L38+M38+N38+O38 -> 266200 | S38: =R38+Q38+P38 -> 441147.5 | T38: 35 | U38: Available | V38: A
A39: 36 | B39: 2.15 | C39: =B39*(25/100) -> 0.5375 | D39: =C39+B39 -> 2.6875 | E39: 0.32 | L39: =E39*Prices!B$2 -> 35200 | M39: =F39*Prices!C$2 -> 0 | N39: =G39*Prices!D$2 -> 0 | O39: =H39*Prices!E$2 -> 0 | P39: =I39*2000+J39*4000+K39*650 -> 0 | Q39: =D39*Prices!A$2 -> 47971.875 | R39: =L39+M39+N39+O39 -> 35200 | S39: =R39+Q39+P39 -> 83171.875 | T39: 36 | U39: Sold
A40: 37 | B40: 19.89 | C40: =B40*(25/100) -> 4.9725 | D40: =C40+B40 -> 24.8625 | E40: 4.34 | L40: =E40*Prices!B$2 -> 477400 | M40: =F40*Prices!C$2 -> 0 | N40: =G40*Prices!D$2 -> 0 | O40: =H40*Prices!E$2 -> 0 | P40: =I40*2000+J40*4000+K40*650 -> 0 | Q40: =D40*Prices!A$2 -> 443795.62 | R40: =L40+M40+N40+O40 -> 477400 | S40: =R40+Q40+P40 -> 921195.62 | T40: 37 | U40: Sold
A41: 38 | B41: 7.56 | C41: =B41*(25/100) -> 1.89 | D41: =C41+B41 -> 9.45 | E41: 1.77 | L41: =E41*Prices!B$2 -> 194700 | M41: =F41*Prices!C$2 -> 0 | N41: =G41*Prices!D$2 -> 0 | O41: =H41*Prices!E$2 -> 0 | P41: =I41*2000+J41*4000+K41*650 -> 0 | Q41: =D41*Prices!A$2 -> 168682.5 | R41: =L41+M41+N41+O41 -> 194700 | S41: =R41+Q41+P41 -> 363382.5 | T41: 38 | U41: Sold
A42: 39 | B42: 17.24 | C42: =B42*(25/100) -> 4.31 | D42: =C42+B42 -> 21.55 | E42: 4.2 | J42: 4.219 | L42: =E42*Prices!B$2 -> 462000 | M42: =F42*Prices!C$2 -> 0 | N42: =G42*Prices!D$2 -> 0 | O42: =H42*Prices!E$2 -> 0 | P42: =I42*2000+J42*5000+K42*650 -> 21095 | Q42: =D42*Prices!A$2 -> 384667.5 | R42: =L42+M42+N42+O42 -> 462000 | S42: =R42+Q42+P42 -> 867762.5 | T42: 39 | U42: Available | V42: A
A43: 40 | B43: 5.94 | C43: =B43*(25/100) -> 1.485 | D43: =C43+B43 -> 7.425 | E43: 1.12 | J43: 3.36 | L43: =E43*Prices!B$2 -> 123200 | M43: =F43*Prices!C$2 -> 0 | N43: =G43*Prices!D$2 -> 0 | O43: =H43*Prices!E$2 -> 0 | P43: =I43*2000+J43*5000+K43*650 -> 16800 | Q43: =D43*Prices!A$2 -> 132536.25 | R43: =L43+M43+N43+O43 -> 123200 | S43: =R43+Q43+P43 -> 272536.25 | T43: 40 | U43: Available | V43: A
A44: 41 | B44: 22.63 | C44: =B44*(25/100) -> 5.6575 | D44: =C44+B44 -> 28.2875 | E44: 3.97 | K44: 12.58 | L44: =E44*Prices!B$2 -> 436700 | M44: =F44*Prices!C$2 -> 0 | N44: =G44*Prices!D$2 -> 0 | O44: =H44*Prices!E$2 -> 0 | P44: =I44*2000+J44*4000+K44*2000 -> 25160 | Q44: =D44*Prices!A$2 -> 504931.88 | R44: =L44+M44+N44+O44 -> 436700 | S44: =R44+Q44+P44 -> 966791.88 | T44: 41 | U44: Available | V44: A
A45: 42 | B45: 9.19 | C45: =B45*(25/100) -> 2.2975 | D45: =C45+B45 -> 11.4875 | E45: 1.44 | K45: 5.52 | L45: =E45*Prices!B$2 -> 158400 | M45: =F45*Prices!C$2 -> 0 | N45: =G45*Prices!D$2 -> 0 | O45: =H45*Prices!E$2 -> 0 | P45: =I45*2000+J45*4000+K45*2000 -> 11040 | Q45: =D45*Prices!A$2 -> 205051.88 | R45: =L45+M45+N45+O45 -> 158400 | S45: =R45+Q45+P45 -> 374491.88 | T45: 42 | U45: Available | V45: A
A46: 43 | B46: 31.08 | C46: =B46*(25/100) -> 7.77 | D46: =C46+B46 -> 38.85 | E46: 4.15 | L46: =E46*Prices!B$2 -> 456500 | M46: =F46*Prices!C$2 -> 0 | N46: =G46*Prices!D$2 -> 0 | O46: =H46*Prices!E$2 -> 0 | P46: =I46*2000+J46*4000+K46*300 -> 0 | Q46: =D46*Prices!A$2 -> 693472.5 | R46: =L46+M46+N46+O46 -> 456500 | S46: =R46+Q46+P46 -> 1149972.5 | T46: 43 | U46: Available | V46: A
A47: 44 | B47: 9.252 | C47: =B47*(25/100) -> 2.313 | D47: =C47+B47 -> 11.565 | E47: 1.24 | L47: =E47*Prices!B$2 -> 136400 | M47: =F47*Prices!C$2 -> 0 | N47: =G47*Prices!D$2 -> 0 | O47: =H47*Prices!E$2 -> 0 | P47: =I47*2000+J47*4000+K47*300 -> 0 | Q47: =D47*Prices!A$2 -> 206435.25 | R47: =L47+M47+N47+O47 -> 136400 | S47: =R47+Q47+P47 -> 342835.25 | T47: 44 | U47: Available | V47: A
A48: 45 | B48: 10.21 | C48: =B48*(25/100) -> 2.5525 | D48: =C48+B48 -> 12.7625 | E48: 1.33 | K48: 9.2 | L48: =E48*Prices!B$2 -> 146300 | M48: =F48*Prices!C$2 -> 0 | N48: =G48*Prices!D$2 -> 0 | O48: =H48*Prices!E$2 -> 0 | P48: =I48*2000+J48*4000+K48*300 -> 2760 | Q48: =D48*Prices!A$2 -> 227810.62 | R48: =L48+M48+N48+O48 -> 146300 | S48: =R48+Q48+P48 -> 376870.62 | T48: 45 | U48: Available | V48: A
A49: 46 | B49: 5.506 | C49: =B49*(25/100) -> 1.3765 | D49: =C49+B49 -> 6.8825 | E49: 1.07 | K49: 4.15 | L49: =E49*Prices!B$2 -> 117700 | M49: =F49*Prices!C$2 -> 0 | N49: =G49*Prices!D$2 -> 0 | O49: =H49*Prices!E$2 -> 0 | P49: =I49*2000+J49*4000+K49*300 -> 1245 | Q49: =D49*Prices!A$2 -> 122852.62 | R49: =L49+M49+N49+O49 -> 117700 | S49: =R49+Q49+P49 -> 241797.62 | T49: 46 | U49: Available | V49: A
A50: 47 | B50: 16.02 | C50: =B50*(25/100) -> 4.005 | D50: =C50+B50 -> 20.025 | E50: 3.54 | L50: =E50*Prices!B$2 -> 389400 | M50: =F50*Prices!C$2 -> 0 | N50: =G50*Prices!D$2 -> 0 | O50: =H50*Prices!E$2 -> 0 | P50: =I50*2000+J50*4000+K50*300 -> 0 | Q50: =D50*Prices!A$2 -> 357446.25 | R50: =L50+M50+N50+O50 -> 389400 | S50: =R50+Q50+P50 -> 746846.25 | T50: 47 | U50: Available | V50: A
A51: 48 | B51: 5.44 | C51: =B51*(25/100) -> 1.36 | D51: =C51+B51 -> 6.8 | E51: 0.89 | L51: =E51*Prices!B$2 -> 97900 | M51: =F51*Prices!C$2 -> 0 | N51: =G51*Prices!D$2 -> 0 | O51: =H51*Prices!E$2 -> 0 | P51: =I51*2000+J51*4000+K51*300 -> 0 | Q51: =D51*Prices!A$2 -> 121380 | R51: =L51+M51+N51+O51 -> 97900 | S51: =R51+Q51+P51 -> 219280 | T51: 48 | U51: Available | V51: A
A52: 49 | B52: 9.298 | C52: =B52*(25/100) -> 2.3245 | D52: =C52+B52 -> 11.6225 | E52: 1.41 | L52: =E52*Prices!B$2 -> 155100 | M52: =F52*Prices!C$2 -> 0 | N52: =G52*Prices!D$2 -> 0 | O52: =H52*Prices!E$2 -> 0 | P52: =I52*2000+J52*4000+K52*300 -> 0 | Q52: =D52*Prices!A$2 -> 207461.62 | R52: =L52+M52+N52+O52 -> 155100 | S52: =R52+Q52+P52 -> 362561.62 | T52: 49 | U52: Available | V52: A
A53: 50 | C53: =B53*(25/100) -> 0 | D53: =C53+B53 -> 0 | L53: =E53*Prices!B$2 -> 0 | M53: =F53*Prices!C$2 -> 0 | N53: =G53*Prices!D$2 -> 0 | O53: =H53*Prices!E$2 -> 0 | P53: =I53*2000+J53*4000+K53*300 -> 0 | Q53: =D53*Prices!A$2 -> 0 | R53: =L53+M53+N53+O53 -> 0 | S53: =R53+Q53+P53 -> 0 | T53: 50
A54: 51 | B54: 11.634 | C54: =B54*(25/100) -> 2.9085 | D54: =C54+B54 -> 14.5425 | E54: 2.58 | L54: =E54*Prices!B$2 -> 283800 | M54: =F54*Prices!C$2 -> 0 | N54: =G54*Prices!D$2 -> 0 | O54: =H54*Prices!E$2 -> 0 | P54: =I54*2000+J54*4000+K54*300 -> 0 | Q54: =D54*Prices!A$2 -> 259583.62 | R54: =L54+M54+N54+O54 -> 283800 | S54: =R54+Q54+P54 -> 543383.62 | T54: 51 | U54: Available | V54: A
A55: 52 | C55: =B55*(25/100) -> 0 | D55: =C55+B55 -> 0 | L55: =E55*Prices!B$2 -> 0 | M55: =F55*Prices!C$2 -> 0 | N55: =G55*Prices!D$2 -> 0 | O55: =H55*Prices!E$2 -> 0 | P55: =I55*2000+J55*4000+K55*300 -> 0 | Q55: =D55*Prices!A$2 -> 0 | R55: =L55+M55+N55+O55 -> 0 | S55: =R55+Q55+P55 -> 0 | T55: 52

Sheet Prithivi
A1: Sn | B1: Net Weight | C1: Wstg + MC | D1: Gross Weight | E1: Dmd <0.06 | F1: Dmd < 0.12 | G1: Dmd <0.17 | H1: Dmd Big | I1: Ruby | J1: Emreld | K1: Muga | L1: Dmd Price | M1: Dmd Price | N1: Dmd Price | O1: Dmd Price | P1: Stn Price | Q1: Gold Price | R1: Ttl dmd Price | S1: Total Price | T1: Sn
A2: 85370 | B2: 4.731 | C2: =B2*(25/100) -> 1.18275 | D2: =C2+B2 -> 5.91375 | E2: 0.53 | L2: =E2*Prices!B$2 -> 58300 | M2: =F2*Prices!C$2 -> 0 | N2: =G2*Prices!D$2 -> 0 | O2: =H2*Prices!E$2 -> 0 | P2: =I2*2000+J2*4000+K2*650 -> 0 | Q2: =D2*Prices!A$2 -> 105560.44 | R2: =L2+M2+N2+O2 -> 58300 | S2: =R2+Q2+P2 -> 163860.44 | T2: 85370 | U2: Available
A3: 85743 | B3: 4.512 | C3: =B3*(25/100) -> 1.128 | D3: =C3+B3 -> 5.64 | E3: 0.41 | L3: =E3*Prices!B$2 -> 45100 | M3: =F3*Prices!C$2 -> 0 | N3: =G3*Prices!D$2 -> 0 | O3: =H3*Prices!E$2 -> 0 | P3: =I3*2000+J3*4000+K3*650 -> 0 | Q3: =D3*Prices!A$2 -> 100674 | R3: =L3+M3+N3+O3 -> 45100 | S3: =R3+Q3+P3 -> 145774 | T3: 85743 | U3: Sold
A4: 85753 | B4: 4.538 | C4: =B4*(25/100) -> 1.1345 | D4: =C4+B4 -> 5.6725 | E4: 0.25 | L4: =E4*Prices!B$2 -> 27500 | M4: =F4*Prices!C$2 -> 0 | N4: =G4*Prices!D$2 -> 0 | O4: =H4*Prices!E$2 -> 0 | P4: =I4*2000+J4*4000+K4*650 -> 0 | Q4: =D4*Prices!A$2 -> 101254.12 | R4: =L4+M4+N4+O4 -> 27500 | S4: =R4+Q4+P4 -> 128754.12 | T4: 85753 | U4: Available
A5: 85720 | B5: 1.878 | C5: =B5*(25/100) -> 0.4695 | D5: =C5+B5 -> 2.3475 | E5: 0.37 | L5: =E5*Prices!B$2 -> 40700 | M5: =F5*Prices!C$2 -> 0 | N5: =G5*Prices!D$2 -> 0 | O5: =H5*Prices!E$2 -> 0 | P5: =I5*2000+J5*4000+K5*650 -> 0 | Q5: =D5*Prices!A$2 -> 41902.875 | R5: =L5+M5+N5+O5 -> 40700 | S5: =R5+Q5+P5 -> 82602.875 | T5: 85720 | U5: Sold
A6: 140782 | B6: 8.964 | C6: =B6*(25/100) -> 2.241 | D6: =C6+B6 -> 11.205 | E6: 0.87 | L6: =E6*Prices!B$2 -> 95700 | M6: =F6*Prices!C$2 -> 0 | N6: =G6*Prices!D$2 -> 0 | O6: =H6*Prices!E$2 -> 0 | P6: =I6*2000+J6*4000+K6*650 -> 0 | Q6: =D6*Prices!A$2 -> 200009.25 | R6: =L6+M6+N6+O6 -> 95700 | S6: =R6+Q6+P6 -> 295709.25 | T6: 140782 | U6: Available
A7: 140785 | B7: 1.3 | C7: =B7*(25/100) -> 0.325 | D7: =C7+B7 -> 1.625 | E7: 0.12 | L7: =E7*Prices!B$2 -> 13200 | M7: =F7*Prices!C$2 -> 0 | N7: =G7*Prices!D$2 -> 0 | O7: =H7*Prices!E$2 -> 0 | P7: =I7*2000+J7*4000+K7*650 -> 0 | Q7: =D7*Prices!A$2 -> 29006.25 | R7: =L7+M7+N7+O7 -> 13200 | S7: =R7+Q7+P7 -> 42206.25 | T7: 140785 | U7: Available
A8: 140818 | B8: 9.879 | C8: =B8*(25/100) -> 2.46975 | D8: =C8+B8 -> 12.34875 | E8: 1.25 | L8: =E8*Prices!B$2 -> 137500 | M8: =F8*Prices!C$2 -> 0 | N8: =G8*Prices!D$2 -> 0 | O8: =H8*Prices!E$2 -> 0 | P8: =I8*2000+J8*4000+K8*650 -> 0 | Q8: =D8*Prices!A$2 -> 220425.19 | R8: =L8+M8+N8+O8 -> 137500 | S8: =R8+Q8+P8 -> 357925.19 | T8: 140818 | U8: Sold
A9: 140819 | B9: 2.122 | C9: =B9*(25/100) -> 0.5305 | D9: =C9+B9 -> 2.6525 | E9: 0.23 | L9: =E9*Prices!B$2 -> 25300 | M9: =F9*Prices!C$2 -> 0 | N9: =G9*Prices!D$2 -> 0 | O9: =H9*Prices!E$2 -> 0 | P9: =I9*2000+J9*4000+K9*650 -> 0 | Q9: =D9*Prices!A$2 -> 47347.125 | R9: =L9+M9+N9+O9 -> 25300 | S9: =R9+Q9+P9 -> 72647.125 | T9: 140819 | U9: Available
L10: =E10*Prices!B$2 -> 0 | M10: =F10*Prices!C$2 -> 0 | N10: =G10*Prices!D$2 -> 0 | O10: =H10*Prices!E$2 -> 0 | P10: =I10*2000+J10*4000+K10*650 -> 0 | Q10: =D10*Prices!A$2 -> 0 | R10: =L10+M10+N10+O10 -> 0 | S10: =R10+Q10+P10 -> 0

Sheet Necklace
A1: Sn | B1: Net Weight | C1: Wstg + MC | D1: Gross Weight | E1: Dmd <0.06 | F1: Dmd < 0.12 | G1: Dmd <0.17 | H1: Dmd Big | I1: Ruby | J1: Emreld | K1: Muga | L1: Dmd Price | M1: Dmd Price | N1: Dmd Price | O1: Dmd Price | P1: Stn Price | Q1: Gold Price | R1: Ttl dmd Price | S1: Total Price | T1: Sn
A2: 1 | B2: 23.132 | C2: =B2*(25/100) -> 5.783 | D2: =C2+B2 -> 28.915 | E2: 6.1 | K2: 2.79 | L2: =E2*Prices!B$2 -> 671000 | M2: =F2*Prices!C$2 -> 0 | N2: =G2*Prices!D$2 -> 0 | O2: =H2*Prices!E$2 -> 0 | P2: =I2*2000+J2*4000+K2*650 -> 1813.5 | Q2: =D2*Prices!A$2 -> 516132.75 | R2: =L2+M2+N2+O2 -> 671000 | S2: =R2+Q2+P2 -> 1188946.2 | T2: 1 | U2: Available

Sheet Chura
A1: Sn | B1: Net Weight | C1: Wstg + MC | D1: Gross Weight | E1: Dmd <0.06 | F1: Dmd < 0.12 | G1: Dmd <0.17 | H1: Dmd Big | I1: Ruby | J1: Emreld | K1: Muga | L1: Dmd Price | M1: Dmd Price | N1: Dmd Price | O1: Dmd Price | P1: Stn Price | Q1: Gold Price | R1: Ttl dmd Price | S1: Total Price | T1: Sn
A2: 268 | B2: 33.17 | C2: =B2*0.25 -> 8.2925 | D2: =C2+B2 -> 41.4625 | E2: 4.59 | L2: =E2*Prices!B$2 -> 504900 | M2: =F2*Prices!C$2 -> 0 | N2: =G2*Prices!D$2 -> 0 | O2: =H2*Prices!E$2 -> 0 | P2: =I2*2000+J2*4000+K2*650 -> 0 | Q2: =D2*Prices!A$2 -> 740105.62 | R2: =L2+M2+N2+O2 -> 504900 | S2: =R2+Q2+P2 -> 1245005.6 | T2: 268 | U2: Available
A3: 462 | B3: 11 | C3: =B3*0.25 -> 2.75 | D3: =C3+B3 -> 13.75 | E3: 1.25 | L3: =E3*Prices!B$2 -> 137500 | M3: =F3*Prices!C$2 -> 0 | N3: =G3*Prices!D$2 -> 0 | O3: =H3*Prices!E$2 -> 0 | P3: =I3*2000+J3*4000+K3*650 -> 0 | Q3: =D3*Prices!A$2 -> 245437.5 | R3: =L3+M3+N3+O3 -> 137500 | S3: =R3+Q3+P3 -> 382937.5 | T3: 462 | U3: Sold

Sheet Nosepin
A1: Sn | B1: Net Weight | C1: Wstg + MC | D1: Gross Weight | E1: Dmd <0.06 | F1: Dmd >0.06 | G1: Dmd Price | H1: Dmd Price | I1: Gold Price | J1: Total Price | K1: Sn
A2: 1 | B2: 0.5 | C2: =B2*(25/100) -> 0.125 | D2: =C2+B2 -> 0.625 | F2: 0.4 | G2: =E2*225000 -> 0 | H2: =F2*200000 -> 80000 | I2: =(D2*Prices!$A$2)+3000 -> 14156.25 | J2: =G2+I2+H2 -> 94156.25
A3: 2 | B3: 0.39 | C3: =B3*(25/100) -> 0.0975 | D3: =C3+B3 -> 0.4875 | F3: 0.35 | G3: =E3*215000 -> 0 | H3: =F3*185000 -> 64750 | I3: =(D3*Prices!$A$2)+3000 -> 11701.875 | J3: =G3+I3+H3 -> 76451.875
A4: 3 | B4: 0.326 | C4: =B4*(25/100) -> 0.0815 | D4: =C4+B4 -> 0.4075 | F4: 0.32 | G4: =E4*215000 -> 0 | H4: =F4*185000 -> 59200 | I4: =(D4*Prices!$A$2)+3000 -> 10273.875 | J4: =G4+I4+H4 -> 69473.875
A5: 4 | B5: 0.37 | C5: =B5*(25/100) -> 0.0925 | D5: =C5+B5 -> 0.4625 | F5: 0.25 | G5: =E5*180000 -> 0 | H5: =F5*165000 -> 41250 | I5: =(D5*Prices!$A$2)+3000 -> 11255.625 | J5: =G5+I5+H5 -> 52505.625
A6: 5 | B6: 0.36 | C6: =B6*(25/100) -> 0.09 | D6: =C6+B6 -> 0.45 | F6: 0.25 | G6: =E6*225000 -> 0 | H6: =F6*165000 -> 41250 | I6: =(D6*Prices!$A$2)+3000 -> 11032.5 | J6: =G6+I6+H6 -> 52282.5
A7: 6 | B7: 0.406 | C7: =B7*(25/100) -> 0.1015 | D7: =C7+B7 -> 0.5075 | F7: 0.22 | G7: =E7*225000 -> 0 | H7: =F7*155000 -> 34100 | I7: =(D7*Prices!$A$2)+3000 -> 12058.875 | J7: =G7+I7+H7 -> 46158.875
A8: 7 | B8: 0.286 | C8: =B8*(25/100) -> 0.0715 | D8: =C8+B8 -> 0.3575 | F8: 0.17 | G8: =E8*225000 -> 0 | H8: =F8*125000 -> 21250 | I8: =(D8*Prices!$A$2)+3000 -> 9381.375 | J8: =G8+I8+H8 -> 30631.375
A9: 8 | B9: 0.28 | C9: =B9*(25/100) -> 0.07 | D9: =C9+B9 -> 0.35 | F9: 0.15 | G9: =E9*225000 -> 0 | H9: =F9*125000 -> 18750 | I9: =(D9*Prices!$A$2)+3000 -> 9247.5 | J9: =G9+I9+H9 -> 27997.5
A10: 9 | B10: 0.316 | C10: =B10*(25/100) -> 0.079 | D10: =C10+B10 -> 0.395 | F10: 0.12 | G10: =E10*225000 -> 0 | H10: =F10*105000 -> 12600 | I10: =(D10*Prices!$A$2)+3000 -> 10050.75 | J10: =G10+I10+H10 -> 22650.75
A11: 10 | B11: 0.247 | C11: =B11*(25/100) -> 0.06175 | D11: =C11+B11 -> 0.30875 | F11: 0.09 | G11: =E11*225000 -> 0 | H11: =F11*105000 -> 9450 | I11: =(D11*Prices!$A$2)+3000 -> 8511.1875 | J11: =G11+I11+H11 -> 17961.188
A12: 11 | B12: 0.247 | C12: =B12*(25/100) -> 0.06175 | D12: =C12+B12 -> 0.30875 | F12: 0.09 | G12: =E12*225000 -> 0 | H12: =F12*105000 -> 9450 | I12: =(D12*Prices!$A$2)+3000 -> 8511.1875 | J12: =G12+I12+H12 -> 17961.188
A13: 12 | B13: 0.255 | C13: =B13*(25/100) -> 0.06375 | D13: =C13+B13 -> 0.31875 | F13: 0.06 | G13: =E13*225000 -> 0 | H13: =F13*65000 -> 3900 | I13: =(D13*Prices!$A$2)+3000 -> 8689.6875 | J13: =G13+I13+H13 -> 12589.688
A14: 13 | B14: 0.23 | C14: =B14*(25/100) -> 0.0575 | D14: =C14+B14 -> 0.2875 | F14: 0.05 | G14: =E14*225000 -> 0 | H14: =F14*100000 -> 5000 | I14: =(D14*Prices!$A$2)+3000 -> 8131.875 | J14: =G14+I14+H14 -> 13131.875 | K14: lc
A15: 14 | B15: 0.255 | C15: =B15*(25/100) -> 0.06375 | D15: =C15+B15 -> 0.31875 | F15: 0.06 | G15: =E15*225000 -> 0 | H15: =F15*65000 -> 3900 | I15: =(D15*Prices!$A$2)+3000 -> 8689.6875 | J15: =G15+I15+H15 -> 12589.688
A16: 15 | B16: 0.255 | C16: =B16*(25/100) -> 0.06375 | D16: =C16+B16 -> 0.31875 | F16: 0.06 | G16: =E16*225000 -> 0 | H16: =F16*65000 -> 3900 | I16: =(D16*Prices!$A$2)+3000 -> 8689.6875 | J16: =G16+I16+H16 -> 12589.688
A17: 16 | B17: 0.23 | C17: =B17*(25/100) -> 0.0575 | D17: =C17+B17 -> 0.2875 | F17: 0.05 | G17: =E17*225000 -> 0 | H17: =F17*225000 -> 11250 | I17: =(D17*Prices!$A$2)+3000 -> 8131.875 | J17: =G17+I17+H17 -> 19381.875 | K17: lc
A18: 17 | B18: 0.31 | C18: =B18*(25/100) -> 0.0775 | D18: =C18+B18 -> 0.3875 | F18: 0.25 | G18: =E18*225000 -> 0 | H18: =F18*225000 -> 56250 | I18: =(D18*Prices!$A$2)+3000 -> 9916.875 | J18: =G18+I18+H18 -> 66166.875 | K18: lc
A19: 18 | B19: 0.27 | C19: =B19*(25/100) -> 0.0675 | D19: =C19+B19 -> 0.3375 | F19: 0.2 | G19: =E19*225000 -> 0 | H19: =F19*225000 -> 45000 | I19: =(D19*Prices!$A$2)+3000 -> 9024.375 | J19: =G19+I19+H19 -> 54024.375 | K19: lc
A20: 19 | B20: 0.3 | C20: =B20*(25/100) -> 0.075 | D20: =C20+B20 -> 0.375 | F20: 0.15 | G20: =E20*225000 -> 0 | H20: =F20*225000 -> 33750 | I20: =(D20*Prices!$A$2)+3000 -> 9693.75 | J20: =G20+I20+H20 -> 43443.75 | K20: lc
A21: 20 | B21: 0.27 | C21: =B21*(25/100) -> 0.0675 | D21: =C21+B21 -> 0.3375 | F21: 0.1 | G21: =E21*225000 -> 0 | H21: =F21*225000 -> 22500 | I21: =(D21*Prices!$A$2)+3000 -> 9024.375 | J21: =G21+I21+H21 -> 31524.375 | K21: lc
A22: 21 | C22: =B22*(25/100) -> 0 | D22: =C22+B22 -> 0 | G22: =E22*225000 -> 0 | H22: =F22*225000 -> 0 | I22: =(D22*Prices!$A$2)+3000 -> 3000 | J22: =G22+I22+H22 -> 3000
A23: 22 | C23: =B23*(25/100) -> 0 | D23: =C23+B23 -> 0 | G23: =E23*225000 -> 0 | H23: =F23*225000 -> 0 | I23: =(D23*Prices!$A$2)+3000 -> 3000 | J23: =G23+I23+H23 -> 3000
A24: 23 | C24: =B24*(25/100) -> 0 | D24: =C24+B24 -> 0 | G24: =E24*225000 -> 0 | H24: =F24*225000 -> 0 | I24: =(D24*Prices!$A$2)+3000 -> 3000 | J24: =G24+I24+H24 -> 3000
A25: 24 | C25: =B25*(25/100) -> 0 | D25: =C25+B25 -> 0 | G25: =E25*225000 -> 0 | H25: =F25*225000 -> 0 | I25: =(D25*Prices!$A$2)+3000 -> 3000 | J25: =G25+I25+H25 -> 3000
A26: 25 | C26: =B26*(25/100) -> 0 | D26: =C26+B26 -> 0 | G26: =E26*225000 -> 0 | H26: =F26*225000 -> 0 | I26: =(D26*Prices!$A$2)+3000 -> 3000 | J26: =G26+I26+H26 -> 3000
A27: 26 | C27: =B27*(25/100) -> 0 | D27: =C27+B27 -> 0 | G27: =E27*225000 -> 0 | H27: =F27*225000 -> 0 | I27: =(D27*Prices!$A$2)+3000 -> 3000 | J27: =G27+I27+H27 -> 3000

Sheet Check Price
A1: Sn | B1: Net Weight | C1: Wstg + MC | D1: Gross Weight | E1: Dmd <0.06 | F1: Dmd < 0.12 | G1: Dmd <0.17 | H1: Dmd Big | I1: Ruby | J1: Emreld | K1: Muga | L1: Dmd Price | M1: Dmd Price | N1: Dmd Price | O1: Dmd Price | P1: Stn Price | Q1: Gold Price | R1: TAX | S1: Ttl dmd Price | T1: Total Price | U1: Disocunt Price | V1: 40 | W1: Cost
B2: 2 | C2: =B2*(25/100) -> 0.5 | D2: =C2+B2 -> 2.5 | E2: 0.15 | L2: =E2*Prices!B$2 -> 16500 | M2: =F2*180000 -> 0 | N2: =G2*375000 -> 0 | O2: =H2*Prices!E$2 -> 0 | P2: =I2*5000+J2*14000+K2*1800 -> 0 | Q2: =D2*Prices!$A$2 -> 44625 | R2: =Q2*0.02 -> 892.5 | S2: =L2+M2+N2+O2 -> 16500 | T2: =S2+Q2+P2 -> 61125 | U2: =P2+Q2+(S2-(S2*($V$1/100))) -> 54525 | V2: =T2-U2 -> 6600 | W2: =((D2*0.6)/11.664)*Prices!$A$4+E2*38000+F2*51900+G2*60900+K2*600 -> 45823.457
B3: 2.808 | C3: =B3*(25/100) -> 0.702 | D3: =C3+B3 -> 3.51 | F3: 0.6 | J3: 4.66 | L3: =E3*Prices!B$2 -> 0 | M3: =F3*180000 -> 108000 | N3: =G3*375000 -> 0 | O3: =H3*Prices!E$2 -> 0 | P3: =I3*5000+J3*18000+K3*1800 -> 83880 | Q3: =D3*Prices!$A$2 -> 62653.5 | R3: =Q3*0.02 -> 1253.07 | S3: =L3+M3+N3+O3 -> 108000 | T3: =S3+Q3+P3 -> 254533.5 | U3: =P3+Q3+(S3-(S3*($V$1/100))) -> 211333.5 | V3: =T3-U3 -> 43200 | W3: =((D3*0.6)/11.664)*Prices!$A$4+E3*38000+F3*51900+G3*60900+K3*600 -> 87473.333
B4: 4.5 | C4: =B4*(25/100) -> 1.125 | D4: =C4+B4 -> 5.625 | E4: 0.5 | J4: 16 | L4: =E4*Prices!B$2 -> 55000 | M4: =F4*180000 -> 0 | N4: =G4*375000 -> 0 | O4: =H4*Prices!E$2 -> 0 | P4: =I4*5000+J4*8000+K4*1800 -> 128000 | Q4: =D4*Prices!$A$2 -> 100406.25 | R4: =Q4*0.02 -> 2008.125 | S4: =L4+M4+N4+O4 -> 55000 | T4: =S4+Q4+P4 -> 283406.25 | U4: =P4+Q4+(S4-(S4*($V$1/100))) -> 261406.25 | V4: =T4-U4 -> 22000 | W4: =((D4*0.6)/11.664)*Prices!$A$4+E4*38000+F4*51900+G4*60900+K4*600 -> 109277.78
C5: =B5*(25/100) -> 0 | D5: =C5+B5 -> 0 | L5: =E5*Prices!B$2 -> 0 | M5: =F5*180000 -> 0 | N5: =G5*375000 -> 0 | O5: =H5*Prices!E$2 -> 0 | P5: =I5*5000+J5*14000+K5*1800 -> 0 | Q5: =D5*Prices!$A$2 -> 0 | R5: =Q5*0.02 -> 0 | S5: =L5+M5+N5+O5 -> 0 | T5: =S5+Q5+P5 -> 0 | U5: =P5+Q5+(S5-(S5*($V$1/100))) -> 0 | V5: =T5-U5 -> 0 | W5: =((D5*0.6)/11.664)*Prices!$A$4+E5*38000+F5*51900+G5*60900+K5*600 -> 0
